Workbook
Name AB_DIV: '4. Paramètres'!$C$62
Name ASSIETTE_CSG_SAL: '4. Paramètres'!$C$23
Name AUTRES_REV: '5. Profil'!$C$21
Name BENEFICE_IS: '5. Profil'!$C$28
Name CAPITAL_TNS: '5. Profil'!$C$16
Name CASHBACK_BADGE: '5. Profil'!$C$61
Name CASHBACK_MODE: '5. Profil'!$C$59
Name CDHR_SEUIL_C: '4. Paramètres'!$C$93
Name CDHR_SEUIL_C_HAUT: '4. Paramètres'!$C$95
Name CDHR_SEUIL_M: '4. Paramètres'!$C$94
Name CDHR_SEUIL_M_HAUT: '4. Paramètres'!$C$96
Name CDHR_TAUX_PLANCHER: '4. Paramètres'!$C$92
Name CEHR_SEUIL_C1: '4. Paramètres'!$C$85
Name CEHR_SEUIL_C2: '4. Paramètres'!$C$86
Name CEHR_SEUIL_M1: '4. Paramètres'!$C$87
Name CEHR_SEUIL_M2: '4. Paramètres'!$C$88
Name CEHR_TX_1: '4. Paramètres'!$C$83
Name CEHR_TX_2: '4. Paramètres'!$C$84
Name CLIENT_NAME: '5. Profil'!$C$5
Name DIVIDENDES_FOYER: '5. Profil'!$C$22
Name EFFECTIF: '5. Profil'!$C$14
Name ENVELOPPE: '5. Profil'!$C$27
Name FORME_JURIDIQUE: '5. Profil'!$C$12
Name FS_ABO_GE50: '4. Paramètres'!$C$42
Name FS_ABO_LT50: '4. Paramètres'!$C$41
Name FS_INT_GE250: '4. Paramètres'!$C$40
Name FS_INT_LT250: '4. Paramètres'!$C$39
Name FS_PART_50_249: '4. Paramètres'!$C$37
Name FS_PART_GE250: '4. Paramètres'!$C$38
Name FS_PART_LT50: '4. Paramètres'!$C$36
Name HORIZON_PROJ: '4. Paramètres'!$C$103
Name IR_PLAFOND_T1: '4. Paramètres'!$C$11
Name IR_PLAFOND_T2: '4. Paramètres'!$C$12
Name IR_PLAFOND_T3: '4. Paramètres'!$C$13
Name IR_PLAFOND_T4: '4. Paramètres'!$C$14
Name IR_TAUX_T2: '4. Paramètres'!$D$12
Name IR_TAUX_T3: '4. Paramètres'!$D$13
Name IR_TAUX_T4: '4. Paramètres'!$D$14
Name IR_TAUX_T5: '4. Paramètres'!$D$15
Name IS_PLAF_REDUIT: '4. Paramètres'!$C$69
Name M_ABO_PEE: '5. Profil'!$C$47
Name M_ABO_PER: '5. Profil'!$C$48
Name M_AVANTAGES: '5. Profil'!$C$50
Name M_CADO: '5. Profil'!$C$53
Name M_CASHBACK: '5. Profil'!$C$56
Name M_CESU: '5. Profil'!$C$52
Name M_IK: '5. Profil'!$C$55
Name M_INTERESSEMENT: '5. Profil'!$C$46
Name M_MUTUELLE: '5. Profil'!$C$54
Name M_PARTICIPATION: '5. Profil'!$C$45
Name M_PERIN: '5. Profil'!$C$49
Name M_TR: '5. Profil'!$C$51
Name MODE_PILOTAGE: '5. Profil'!$C$26
Name PARTS: '5. Profil'!$C$20
Name PASS_2025: '4. Paramètres'!$C$6
Name PLAF_QF_DEMI_PART: '4. Paramètres'!$C$74
Name PLAF_QF_INVALIDE: '4. Paramètres'!$C$78
Name PLAF_QF_PARENT_ISOLE: '4. Paramètres'!$C$75
Name PLAF_QF_PERS_SEULE_L: '4. Paramètres'!$C$76
Name PLAF_QF_VEUF: '4. Paramètres'!$C$77

Sheet 1. Garde
B3: Outil d'arbitrage de la rémunération du dirigeant
B4: Simulateur multi-population - TNS, assimilé salarié, libéral, salarié
B6: [Logo cabinet]
B10: Cabinet | D10: =INDEX('5. Profil'!C:C,MATCH("Cabinet",'5. Profil'!B:B,0))
B11: Client | D11: =CLIENT_NAME
B12: Date de la simulation | D12: =INDEX('5. Profil'!C:C,MATCH("Date de la simulation",'5. Profil'!B:B,0))
B13: Référentiel fiscal | D13: 2026 (revenus 2025)
B14: Version | D14: v19 - généré le 11/05/2026
B15: Historique | D15: v19 : Tests étendus 10→20 + 10 vérifications cohérence inter-feuilles automatiques
B17: SOMMAIRE
B18: 2. Dashboard | D18: 🟢 Synthèse rendez-vous client (1 page)
B19: 3. Mode d'emploi | D19: Logique de l'outil et codes couleurs
B20: 4. Paramètres fiscaux | D20: Référentiel 2026 (à mettre à jour annuellement)
B21: 5. Profil client | D21: Saisir les inputs du dossier
B22: 6. Comparateur | D22: Matrice de rentabilité par dispositif
B23: 7. Module Assimilé salarié | D23: Président SAS / SASU / SELAS, gérant min.
B24: 8. Module TNS | D24: Gérant majoritaire SARL/EURL, EI
B25: 9. Module Libéral | D25: BNC + SEL
B26: 10. Module Salarié | D26: Cadre / non-cadre - optimisation
B27: 11. Arbitrage global | D27: 4 stratégies à enveloppe constante
B28: 12. Synthèse dirigeant | D28: Livrable client final
B29: 13. Sources & disclaimer | D29: Références légales et limites
B32: AVERTISSEMENT
B33: Cet outil constitue une aide à la décision à usage professionnel et ne se substitue pas au conseil personnalisé d'un expert-comptable, d'un avocat fiscaliste ou d'un conseil en gestion de patrimoine. Les paramètres fiscaux et sociaux 2026 doivent être mis à jour annuellement (cf. feuille « 13. Sources »). Les calculs reposent sur des taux moyens indicatifs et des hypothèses simplificatrices documentées dans chaque module. Le cabinet décline toute responsabilité quant à l'usage qui pourrait en être fait.

Sheet 2. Dashboard
B2: Tableau de bord - arbitrage rémunération | G2: ↩ Sommaire
B3: Client : | C3: =CLIENT_NAME | E3: Régime : | F3: =REGIME_SOCIAL
B4: Date : | C4: =INDEX('5. Profil'!C:C,MATCH("Date de la simulation",'5. Profil'!B:B,0)) | E4: Effectif : | F4: =EFFECTIF
B5: 🎯 Stratégie recommandée | D5: =IF(MAX(INDEX('11. Arbitrage'!C:C,MATCH("TOTAL NET DIRIGEANT APRÈS FISCALITÉ (€)",'11. Arbitrage'!B:B,0)),INDEX('11. Arbitrage'!D:D,MATCH("TOTAL NET DIRIGEANT APRÈS FISCALITÉ (€)",'11. Arbitrage'!B:B,0)),INDEX('11. Arbitrage'!E:E,MATCH("TOTAL NET DIRIGEANT APRÈS FISCALITÉ (€)",'11. Arbitrage'!B:B,0)),INDEX('11. Arbitrage'!F:F,MATCH("TOTAL NET DIRIGEANT APRÈS FISCALITÉ (€)",'11. Arbitrage'!B:B,0)))=INDEX('11. Arbitrage'!C:C,MATCH("TOTAL NET DIRIGEANT APRÈS FISCALITÉ (€)",'11. Arbitrage'!B:B,0)),"A - 100 % rémunération directe",IF(MAX(INDEX('11. Arbitrage'!C:C,MATCH("TOTAL NET DIRIGEANT APRÈS FISCALITÉ (€)",'11. Arbitrage'!B:B,0)),INDEX('11. Arbitrage'!D:D,MATCH("TOTAL NET DIRIGEANT APRÈS FISCALITÉ (€)",'11. Arbitrage'!B:B,0)),INDEX('11. Arbitrage'!E:E,MATCH("TOTAL NET DIRIGEANT APRÈS FISCALITÉ (€)",'11. Arbitrage'!B:B,0)),INDEX('11. Arbitrage'!F:F,MATCH("TOTAL NET DIRIGEANT APRÈS FISCALITÉ (€)",'11. Arbitrage'!B:B,0)))=INDEX('11. Arbitrage'!D:D,MATCH("TOTAL NET DIRIGEANT APRÈS FISCALITÉ (€)",'11. Arbitrage'!B:B,0)),"B - Salaire optimisé + dividendes",IF(MAX(INDEX('11. Arbitrage'!C:C,MATCH("TOTAL NET DIRIGEANT APRÈS FISCALITÉ (€)",'11. Arbitrage'!B:B,0)),INDEX('11. Arbitrage'!D:D,MATCH("TOTAL NET DIRIGEANT APRÈS FISCALITÉ (€)",'11. Arbitrage'!B:B,0)),INDEX('11. Arbitrage'!E:E,MATCH("TOTAL NET DIRIGEANT APRÈS FISCALITÉ (€)",'11. Arbitrage'!B:B,0)),INDEX('11. Arbitrage'!F:F,MATCH("TOTAL NET DIRIGEANT APRÈS FISCALITÉ (€)",'11. Arbitrage'!B:B,0)))=INDEX('11. Arbitrage'!E:E,MATCH("TOTAL NET DIRIGEANT APRÈS FISCALITÉ (€)",'11. Arbitrage'!B:B,0)),"C - + Épargne salariale & PER","D - Stratégie complète + périphériques")))
B6: Stratégie sélectionnée | C6: Reco automatique (max net dirigeant) | E6: Stratégie retenue : | F6: =IF($C$6="Reco automatique (max net dirigeant)",IF(MAX(INDEX('11. Arbitrage'!C:C,MATCH("TOTAL NET DIRIGEANT APRÈS FISCALITÉ (€)",'11. Arbitrage'!B:B,0)),INDEX('11. Arbitrage'!D:D,MATCH("TOTAL NET DIRIGEANT APRÈS FISCALITÉ (€)",'11. Arbitrage'!B:B,0)),INDEX('11. Arbitrage'!E:E,MATCH("TOTAL NET DIRIGEANT APRÈS FISCALITÉ (€)",'11. Arbitrage'!B:B,0)),INDEX('11. Arbitrage'!F:F,MATCH("TOTAL NET DIRIGEANT APRÈS FISCALITÉ (€)",'11. Arbitrage'!B:B,0)))=INDEX('11. Arbitrage'!C:C,MATCH("TOTAL NET DIRIGEANT APRÈS FISCALITÉ (€)",'11. Arbitrage'!B:B,0)),"A",IF(MAX(INDEX('11. Arbitrage'!C:C,MATCH("TOTAL NET DIRIGEANT APRÈS FISCALITÉ (€)",'11. Arbitrage'!B:B,0)),INDEX('11. Arbitrage'!D:D,MATCH("TOTAL NET DIRIGEANT APRÈS FISCALITÉ (€)",'11. Arbitrage'!B:B,0)),INDEX('11. Arbitrage'!E:E,MATCH("TOTAL NET DIRIGEANT APRÈS FISCALITÉ (€)",'11. Arbitrage'!B:B,0)),INDEX('11. Arbitrage'!F:F,MATCH("TOTAL NET DIRIGEANT APRÈS FISCALITÉ (€)",'11. Arbitrage'!B:B,0)))=INDEX('11. Arbitrage'!D:D,MATCH("TOTAL NET DIRIGEANT APRÈS FISCALITÉ (€)",'11. Arbitrage'!B:B,0)),"B",IF(MAX(INDEX('11. Arbitrage'!C:C,MATCH("TOTAL NET DIRIGEANT APRÈS FISCALITÉ (€)",'11. Arbitrage'!B:B,0)),INDEX('11. Arbitrage'!D:D,MATCH("TOTAL NET DIRIGEANT APRÈS FISCALITÉ (€)",'11. Arbitrage'!B:B,0)),INDEX('11. Arbitrage'!E:E,MATCH("TOTAL NET DIRIGEANT APRÈS FISCALITÉ (€)",'11. Arbitrage'!B:B,0)),INDEX('11. Arbitrage'!F:F,MATCH("TOTAL NET DIRIGEANT APRÈS FISCALITÉ (€)",'11. Arbitrage'!B:B,0)))=INDEX('11. Arbitrage'!E:E,MATCH("TOTAL NET DIRIGEANT APRÈS FISCALITÉ (€)",'11. Arbitrage'!B:B,0)),"C","D"))),LEFT($C$6,1)) | G6: ← lettre A/B/C/D
B7: Statut de la sélection | C7: =IF($C$6="Reco automatique (max net dirigeant)","✓ Mode automatique - stratégie alignée sur la reco ("&IF(MAX(INDEX('11. Arbitrage'!C:C,MATCH("TOTAL NET DIRIGEANT APRÈS FISCALITÉ (€)",'11. Arbitrage'!B:B,0)),INDEX('11. Arbitrage'!D:D,MATCH("TOTAL NET DIRIGEANT APRÈS FISCALITÉ (€)",'11. Arbitrage'!B:B,0)),INDEX('11. Arbitrage'!E:E,MATCH("TOTAL NET DIRIGEANT APRÈS FISCALITÉ (€)",'11. Arbitrage'!B:B,0)),INDEX('11. Arbitrage'!F:F,MATCH("TOTAL NET DIRIGEANT APRÈS FISCALITÉ (€)",'11. Arbitrage'!B:B,0)))=INDEX('11. Arbitrage'!C:C,MATCH("TOTAL NET DIRIGEANT APRÈS FISCALITÉ (€)",'11. Arbitrage'!B:B,0)),"A",IF(MAX(INDEX('11. Arbitrage'!C:C,MATCH("TOTAL NET DIRIGEANT APRÈS FISCALITÉ (€)",'11. Arbitrage'!B:B,0)),INDEX('11. Arbitrage'!D:D,MATCH("TOTAL NET DIRIGEANT APRÈS FISCALITÉ (€)",'11. Arbitrage'!B:B,0)),INDEX('11. Arbitrage'!E:E,MATCH("TOTAL NET DIRIGEANT APRÈS FISCALITÉ (€)",'11. Arbitrage'!B:B,0)),INDEX('11. Arbitrage'!F:F,MATCH("TOTAL NET DIRIGEANT APRÈS FISCALITÉ (€)",'11. Arbitrage'!B:B,0)))=INDEX('11. Arbitrage'!D:D,MATCH("TOTAL NET DIRIGEANT APRÈS FISCALITÉ (€)",'11. Arbitrage'!B:B,0)),"B",IF(MAX(INDEX('11. Arbitrage'!C:C,MATCH("TOTAL NET DIRIGEANT APRÈS FISCALITÉ (€)",'11. Arbitrage'!B:B,0)),INDEX('11. Arbitrage'!D:D,MATCH("TOTAL NET DIRIGEANT APRÈS FISCALITÉ (€)",'11. Arbitrage'!B:B,0)),INDEX('11. Arbitrage'!E:E,MATCH("TOTAL NET DIRIGEANT APRÈS FISCALITÉ (€)",'11. Arbitrage'!B:B,0)),INDEX('11. Arbitrage'!F:F,MATCH("TOTAL NET DIRIGEANT APRÈS FISCALITÉ (€)",'11. Arbitrage'!B:B,0)))=INDEX('11. Arbitrage'!E:E,MATCH("TOTAL NET DIRIGEANT APRÈS FISCALITÉ (€)",'11. Arbitrage'!B:B,0)),"C","D")))&")",IF(LEFT($C$6,1)=IF(MAX(INDEX('11. Arbitrage'!C:C,MATCH("TOTAL NET DIRIGEANT APRÈS FISCALITÉ (€)",'11. Arbitrage'!B:B,0)),INDEX('11. Arbitrage'!D:D,MATCH("TOTAL NET DIRIGEANT APRÈS FISCALITÉ (€)",'11. Arbitrage'!B:B,0)),INDEX('11. Arbitrage'!E:E,MATCH("TOTAL NET DIRIGEANT APRÈS FISCALITÉ (€)",'11. Arbitrage'!B:B,0)),INDEX('11. Arbitrage'!F:F,MATCH("TOTAL NET DIRIGEANT APRÈS FISCALITÉ (€)",'11. Arbitrage'!B:B,0)))=INDEX('11. Arbitrage'!C:C,MATCH("TOTAL NET DIRIGEANT APRÈS FISCALITÉ (€)",'11. Arbitrage'!B:B,0)),"A",IF(MAX(INDEX('11. Arbitrage'!C:C,MATCH("TOTAL NET DIRIGEANT APRÈS FISCALITÉ (€)",'11. Arbitrage'!B:B,0)),INDEX('11. Arbitrage'!D:D,MATCH("TOTAL NET DIRIGEANT APRÈS FISCALITÉ (€)",'11. Arbitrage'!B:B,0)),INDEX('11. Arbitrage'!E:E,MATCH("TOTAL NET DIRIGEANT APRÈS FISCALITÉ (€)",'11. Arbitrage'!B:B,0)),INDEX('11. Arbitrage'!F:F,MATCH("TOTAL NET DIRIGEANT APRÈS FISCALITÉ (€)",'11. Arbitrage'!B:B,0)))=INDEX('11. Arbitrage'!D:D,MATCH("TOTAL NET DIRIGEANT APRÈS FISCALITÉ (€)",'11. Arbitrage'!B:B,0)),"B",IF(MAX(INDEX('11. Arbitrage'!C:C,MATCH("TOTAL NET DIRIGEANT APRÈS FISCALITÉ (€)",'11. Arbitrage'!B:B,0)),INDEX('11. Arbitrage'!D:D,MATCH("TOTAL NET DIRIGEANT APRÈS FISCALITÉ (€)",'11. Arbitrage'!B:B,0)),INDEX('11. Arbitrage'!E:E,MATCH("TOTAL NET DIRIGEANT APRÈS FISCALITÉ (€)",'11. Arbitrage'!B:B,0)),INDEX('11. Arbitrage'!F:F,MATCH("TOTAL NET DIRIGEANT APRÈS FISCALITÉ (€)",'11. Arbitrage'!B:B,0)))=INDEX('11. Arbitrage'!E:E,MATCH("TOTAL NET DIRIGEANT APRÈS FISCALITÉ (€)",'11. Arbitrage'!B:B,0)),"C","D"))),"✓ Sélection manuelle alignée sur la reco ("&IF(MAX(INDEX('11. Arbitrage'!C:C,MATCH("TOTAL NET DIRIGEANT APRÈS FISCALITÉ (€)",'11. Arbitrage'!B:B,0)),INDEX('11. Arbitrage'!D:D,MATCH("TOTAL NET DIRIGEANT APRÈS FISCALITÉ (€)",'11. Arbitrage'!B:B,0)),INDEX('11. Arbitrage'!E:E,MATCH("TOTAL NET DIRIGEANT APRÈS FISCALITÉ (€)",'11. Arbitrage'!B:B,0)),INDEX('11. Arbitrage'!F:F,MATCH("TOTAL NET DIRIGEANT APRÈS FISCALITÉ (€)",'11. Arbitrage'!B:B,0)))=INDEX('11. Arbitrage'!C:C,MATCH("TOTAL NET DIRIGEANT APRÈS FISCALITÉ (€)",'11. Arbitrage'!B:B,0)),"A",IF(MAX(INDEX('11. Arbitrage'!C:C,MATCH("TOTAL NET DIRIGEANT APRÈS FISCALITÉ (€)",'11. Arbitrage'!B:B,0)),INDEX('11. Arbitrage'!D:D,MATCH("TOTAL NET DIRIGEANT APRÈS FISCALITÉ (€)",'11. Arbitrage'!B:B,0)),INDEX('11. Arbitrage'!E:E,MATCH("TOTAL NET DIRIGEANT APRÈS FISCALITÉ (€)",'11. Arbitrage'!B:B,0)),INDEX('11. Arbitrage'!F:F,MATCH("TOTAL NET DIRIGEANT APRÈS FISCALITÉ (€)",'11. Arbitrage'!B:B,0)))=INDEX('11. Arbitrage'!D:D,MATCH("TOTAL NET DIRIGEANT APRÈS FISCALITÉ (€)",'11. Arbitrage'!B:B,0)),"B",IF(MAX(INDEX('11. Arbitrage'!C:C,MATCH("TOTAL NET DIRIGEANT APRÈS FISCALITÉ (€)",'11. Arbitrage'!B:B,0)),INDEX('11. Arbitrage'!D:D,MATCH("TOTAL NET DIRIGEANT APRÈS FISCALITÉ (€)",'11. Arbitrage'!B:B,0)),INDEX('11. Arbitrage'!E:E,MATCH("TOTAL NET DIRIGEANT APRÈS FISCALITÉ (€)",'11. Arbitrage'!B:B,0)),INDEX('11. Arbitrage'!F:F,MATCH("TOTAL NET DIRIGEANT APRÈS FISCALITÉ (€)",'11. Arbitrage'!B:B,0)))=INDEX('11. Arbitrage'!E:E,MATCH("TOTAL NET DIRIGEANT APRÈS FISCALITÉ (€)",'11. Arbitrage'!B:B,0)),"C","D")))&")","⚠ Écart vs reco - la reco automatique est "&IF(MAX(INDEX('11. Arbitrage'!C:C,MATCH("TOTAL NET DIRIGEANT APRÈS FISCALITÉ (€)",'11. Arbitrage'!B:B,0)),INDEX('11. Arbitrage'!D:D,MATCH("TOTAL NET DIRIGEANT APRÈS FISCALITÉ (€)",'11. Arbitrage'!B:B,0)),INDEX('11. Arbitrage'!E:E,MATCH("TOTAL NET DIRIGEANT APRÈS FISCALITÉ (€)",'11. Arbitrage'!B:B,0)),INDEX('11. Arbitrage'!F:F,MATCH("TOTAL NET DIRIGEANT APRÈS FISCALITÉ (€)",'11. Arbitrage'!B:B,0)))=INDEX('11. Arbitrage'!C:C,MATCH("TOTAL NET DIRIGEANT APRÈS FISCALITÉ (€)",'11. Arbitrage'!B:B,0)),"A",IF(MAX(INDEX('11. Arbitrage'!C:C,MATCH("TOTAL NET DIRIGEANT APRÈS FISCALITÉ (€)",'11. Arbitrage'!B:B,0)),INDEX('11. Arbitrage'!D:D,MATCH("TOTAL NET DIRIGEANT APRÈS FISCALITÉ (€)",'11. Arbitrage'!B:B,0)),INDEX('11. Arbitrage'!E:E,MATCH("TOTAL NET DIRIGEANT APRÈS FISCALITÉ (€)",'11. Arbitrage'!B:B,0)),INDEX('11. Arbitrage'!F:F,MATCH("TOTAL NET DIRIGEANT APRÈS FISCALITÉ (€)",'11. Arbitrage'!B:B,0)))=INDEX('11. Arbitrage'!D:D,MATCH("TOTAL NET DIRIGEANT APRÈS FISCALITÉ (€)",'11. Arbitrage'!B:B,0)),"B",IF(MAX(INDEX('11. Arbitrage'!C:C,MATCH("TOTAL NET DIRIGEANT APRÈS FISCALITÉ (€)",'11. Arbitrage'!B:B,0)),INDEX('11. Arbitrage'!D:D,MATCH("TOTAL NET DIRIGEANT APRÈS FISCALITÉ (€)",'11. Arbitrage'!B:B,0)),INDEX('11. Arbitrage'!E:E,MATCH("TOTAL NET DIRIGEANT APRÈS FISCALITÉ (€)",'11. Arbitrage'!B:B,0)),INDEX('11. Arbitrage'!F:F,MATCH("TOTAL NET DIRIGEANT APRÈS FISCALITÉ (€)",'11. Arbitrage'!B:B,0)))=INDEX('11. Arbitrage'!E:E,MATCH("TOTAL NET DIRIGEANT APRÈS FISCALITÉ (€)",'11. Arbitrage'!B:B,0)),"C","D")))&" (vous avez choisi "&LEFT($C$6,1)&")"))
B8: COÛT TOTAL SOCIÉTÉ | E8: NET DIRIGEANT
B9: =ENVELOPPE | E9: =IF($F$6="A",INDEX('11. Arbitrage'!C:C,MATCH("TOTAL NET DIRIGEANT APRÈS FISCALITÉ (€)",'11. Arbitrage'!B:B,0)),IF($F$6="B",INDEX('11. Arbitrage'!D:D,MATCH("TOTAL NET DIRIGEANT APRÈS FISCALITÉ (€)",'11. Arbitrage'!B:B,0)),IF($F$6="C",INDEX('11. Arbitrage'!E:E,MATCH("TOTAL NET DIRIGEANT APRÈS FISCALITÉ (€)",'11. Arbitrage'!B:B,0)),INDEX('11. Arbitrage'!F:F,MATCH("TOTAL NET DIRIGEANT APRÈS FISCALITÉ (€)",'11. Arbitrage'!B:B,0)))))
B11: GAIN vs STRATÉGIE A | E11: EFFICACITÉ FISCALE
B12: =IF($F$6="A",INDEX('11. Arbitrage'!C:C,MATCH("TOTAL NET DIRIGEANT APRÈS FISCALITÉ (€)",'11. Arbitrage'!B:B,0)),IF($F$6="B",INDEX('11. Arbitrage'!D:D,MATCH("TOTAL NET DIRIGEANT APRÈS FISCALITÉ (€)",'11. Arbitrage'!B:B,0)),IF($F$6="C",INDEX('11. Arbitrage'!E:E,MATCH("TOTAL NET DIRIGEANT APRÈS FISCALITÉ (€)",'11. Arbitrage'!B:B,0)),INDEX('11. Arbitrage'!F:F,MATCH("TOTAL NET DIRIGEANT APRÈS FISCALITÉ (€)",'11. Arbitrage'!B:B,0)))))-INDEX('11. Arbitrage'!C:C,MATCH("TOTAL NET DIRIGEANT APRÈS FISCALITÉ (€)",'11. Arbitrage'!B:B,0)) | E12: =IFERROR((IF($F$6="A",INDEX('11. Arbitrage'!C:C,MATCH("TOTAL NET DIRIGEANT APRÈS FISCALITÉ (€)",'11. Arbitrage'!B:B,0)),IF($F$6="B",INDEX('11. Arbitrage'!D:D,MATCH("TOTAL NET DIRIGEANT APRÈS FISCALITÉ (€)",'11. Arbitrage'!B:B,0)),IF($F$6="C",INDEX('11. Arbitrage'!E:E,MATCH("TOTAL NET DIRIGEANT APRÈS FISCALITÉ (€)",'11. Arbitrage'!B:B,0)),INDEX('11. Arbitrage'!F:F,MATCH("TOTAL NET DIRIGEANT APRÈS FISCALITÉ (€)",'11. Arbitrage'!B:B,0))))))/ENVELOPPE,0)
B14: Lecture en une phrase
B15: ="Avec un budget de "&TEXT(ROUND(ENVELOPPE,0),"# ##0")&" €, la stratégie "&$F$6&" génère "&TEXT(ROUND(IF($F$6="A",INDEX('11. Arbitrage'!C:C,MATCH("TOTAL NET DIRIGEANT APRÈS FISCALITÉ (€)",'11. Arbitrage'!B:B,0)),IF($F$6="B",INDEX('11. Arbitrage'!D:D,MATCH("TOTAL NET DIRIGEANT APRÈS FISCALITÉ (€)",'11. Arbitrage'!B:B,0)),IF($F$6="C",INDEX('11. Arbitrage'!E:E,MATCH("TOTAL NET DIRIGEANT APRÈS FISCALITÉ (€)",'11. Arbitrage'!B:B,0)),INDEX('11. Arbitrage'!F:F,MATCH("TOTAL NET DIRIGEANT APRÈS FISCALITÉ (€)",'11. Arbitrage'!B:B,0))))),0),"# ##0")&" € nets pour le dirigeant, soit un gain de "&TEXT(ROUND((IF($F$6="A",INDEX('11. Arbitrage'!C:C,MATCH("TOTAL NET DIRIGEANT APRÈS FISCALITÉ (€)",'11. Arbitrage'!B:B,0)),IF($F$6="B",INDEX('11. Arbitrage'!D:D,MATCH("TOTAL NET DIRIGEANT APRÈS FISCALITÉ (€)",'11. Arbitrage'!B:B,0)),IF($F$6="C",INDEX('11. Arbitrage'!E:E,MATCH("TOTAL NET DIRIGEANT APRÈS FISCALITÉ (€)",'11. Arbitrage'!B:B,0)),INDEX('11. Arbitrage'!F:F,MATCH("TOTAL NET DIRIGEANT APRÈS FISCALITÉ (€)",'11. Arbitrage'!B:B,0))))))-INDEX('11. Arbitrage'!C:C,MATCH("TOTAL NET DIRIGEANT APRÈS FISCALITÉ (€)",'11. Arbitrage'!B:B,0)),0),"+# ##0;-# ##0;0")&" €"&" ("&IF(INDEX('11. Arbitrage'!C:C,MATCH("TOTAL NET DIRIGEANT APRÈS FISCALITÉ (€)",'11. Arbitrage'!B:B,0))>0,TEXT((IF($F$6="A",INDEX('11. Arbitrage'!C:C,MATCH("TOTAL NET DIRIGEANT APRÈS FISCALITÉ (€)",'11. Arbitrage'!B:B,0)),IF($F$6="B",INDEX('11. Arbitrage'!D:D,MATCH("TOTAL NET DIRIGEANT APRÈS FISCALITÉ (€)",'11. Arbitrage'!B:B,0)),IF($F$6="C",INDEX('11. Arbitrage'!E:E,MATCH("TOTAL NET DIRIGEANT APRÈS FISCALITÉ (€)",'11. Arbitrage'!B:B,0)),INDEX('11. Arbitrage'!F:F,MATCH("TOTAL NET DIRIGEANT APRÈS FISCALITÉ (€)",'11. Arbitrage'!B:B,0))))))/INDEX('11. Arbitrage'!C:C,MATCH("TOTAL NET DIRIGEANT APRÈS FISCALITÉ (€)",'11. Arbitrage'!B:B,0))-1,"+0,0%;-0,0%"),"-")&") vs Stratégie A - salaire classique ("&TEXT(ROUND(INDEX('11. Arbitrage'!C:C,MATCH("TOTAL NET DIRIGEANT APRÈS FISCALITÉ (€)",'11. Arbitrage'!B:B,0)),0),"# ##0")&" € nets)."
B19: Podium - top 3 dispositifs (score ajusté du Comparateur)
B20: 🥇 | C20: =IFERROR(INDEX('6. Comparateur'!B:B,MATCH("🥇",'6. Comparateur'!N:N,0)),"-") | F20: =IFERROR(INDEX('6. Comparateur'!M:M,MATCH("🥇",'6. Comparateur'!N:N,0)),"-") | G20: =IFERROR(INDEX('6. Comparateur'!L:L,MATCH("🥇",'6. Comparateur'!N:N,0)),"-")
B21: 🥈 | C21: =IFERROR(INDEX('6. Comparateur'!B:B,MATCH("🥈",'6. Comparateur'!N:N,0)),"-") | F21: =IFERROR(INDEX('6. Comparateur'!M:M,MATCH("🥈",'6. Comparateur'!N:N,0)),"-") | G21: =IFERROR(INDEX('6. Comparateur'!L:L,MATCH("🥈",'6. Comparateur'!N:N,0)),"-")
B22: 🥉 | C22: =IFERROR(INDEX('6. Comparateur'!B:B,MATCH("🥉",'6. Comparateur'!N:N,0)),"-") | F22: =IFERROR(INDEX('6. Comparateur'!M:M,MATCH("🥉",'6. Comparateur'!N:N,0)),"-") | G22: =IFERROR(INDEX('6. Comparateur'!L:L,MATCH("🥉",'6. Comparateur'!N:N,0)),"-")
B24: =("Composition de la stratégie sélectionnée - "&$F$6)
B25: Inclus | C25: Dispositif | E25: Montant | F25: Risque | G25: Commentaire
B26: =IF(AND(TOG_PARTICIPATION="Oui",$F$6>="B"),"✓","") | C26: Participation | E26: =IF(AND(TOG_PARTICIPATION="Oui",$F$6>="B"),M_PARTICIPATION,"") | F26: 🟢 Sécurisé | G26: Cadre légal stable, exo IR si placement 5 ans en PEE.
B27: =IF(AND(TOG_INTERESSEMENT="Oui",$F$6>="B"),"✓","") | C27: Intéressement | E27: =IF(AND(TOG_INTERESSEMENT="Oui",$F$6>="B"),M_INTERESSEMENT,"") | F27: 🟢 Sécurisé | G27: Accord triennal ; aléatoire et collectif.
B28: =IF(AND(TOG_ABO_PEE="Oui",$F$6>="B"),"✓","") | C28: Abondement PEE | E28: =IF(AND(TOG_ABO_PEE="Oui",$F$6>="B"),M_ABO_PEE,"") | F28: 🟢 Sécurisé | G28: Plafond 8 % PASS, triplement contributions salarié.
B29: =IF(AND(TOG_ABO_PER="Oui",$F$6>="B"),"✓","") | C29: Abondement PER collectif | E29: =IF(AND(TOG_ABO_PER="Oui",$F$6>="B"),M_ABO_PER,"") | F29: 🟢 Sécurisé | G29: Plafond 16 % PASS.
B30: =IF(AND(TOG_PERIN="Oui",$F$6>="B"),"✓","") | C30: PER individuel | E30: =IF(AND(TOG_PERIN="Oui",$F$6>="B"),M_PERIN,"") | F30: 🟢 Sécurisé | G30: Versement déductible IR. Fiscalité différée à la sortie.
B31: =IF(AND(TOG_AVANTAGES="Oui",$F$6>="C"),"✓","") | C31: Avantages en nature | E31: =IF(AND(TOG_AVANTAGES="Oui",$F$6>="C"),M_AVANTAGES,"") | F31: 🟠 À valider | G31: Évaluation forfait vs réel - vérifier conformité arrêté 25/12/2002.
B32: =IF(AND(TOG_TR="Oui",$F$6>="B"),"✓","") | C32: Tickets restaurant | E32: =IF(AND(TOG_TR="Oui",$F$6>="B"),M_TR,"") | F32: 🟢 Sécurisé | G32: Part employeur exo ≤ 7,26 €/titre (60 % max).
B33: =IF(AND(TOG_CESU="Oui",$F$6>="B"),"✓","") | C33: CESU préfinancé | E33: =IF(AND(TOG_CESU="Oui",$F$6>="B"),M_CESU,"") | F33: 🟢 Sécurisé | G33: Exo ≤ 2 540 €/an/salarié.
B34: =IF(AND(TOG_CADO="Oui",$F$6>="C"),"✓","") | C34: Chèques cadeaux & vacances | E34: =IF(AND(TOG_CADO="Oui",$F$6>="C"),M_CADO,"") | F34: 🟠 À valider | G34: Tolérance URSSAF - non opposable de droit ; respecter les seuils.
B35: =IF(AND(TOG_MUTUELLE="Oui",$F$6>="B"),"✓","") | C35: Mutuelle / prévoyance | E35: =IF(AND(TOG_MUTUELLE="Oui",$F$6>="B"),M_MUTUELLE,"") | F35: 🟢 Sécurisé | G35: Contrat collectif obligatoire. Part patronale CSG/CRDS.
B36: =IF(AND(TOG_IK="Oui",$F$6>="C"),"✓","") | C36: Indemnités kilométriques | E36: =IF(AND(TOG_IK="Oui",$F$6>="C"),M_IK,"") | F36: 🟠 À valider | G36: Respecter le barème fiscal annuel ; justifier les déplacements.
B37: =IF(AND(TOG_CASHBACK="Oui",$F$6>="D"),"✓","") | C37: 💸 Cashback (programme partenaire) | E37: =IF(AND(TOG_CASHBACK="Oui",$F$6>="D"),M_CASHBACK,"") | F37: =CASHBACK_BADGE | G37: Risque selon mode de déploiement (cf. Profil §7) - note technique en feuille « 13. Sources ».
B38: Note : la rémunération directe (salaire/dividendes) absorbe le solde de l'enveloppe = ENVELOPPE − somme des dispositifs ci-dessus.
B40: ℹ La recommandation de stratégie est basée sur le net dirigeant maximal. Le scoring (podium ci-dessus) sert à comparer les dispositifs individuellement - il n'influence pas la sélection de la stratégie.
B41: =IF(AND(TOG_CASHBACK="Oui",$F$6>="D"),"⚠ Cashback inclus dans cette stratégie - Mode de déploiement défini en Profil §7. Susceptible de requalification URSSAF selon l'usage et la fréquence. Sécuriser avec le cabinet avant déploiement. Cf. note technique en feuille « 13. Sources ».","")
B44: Document préparé par [Cabinet] - Outil indicatif à usage professionnel ne se substituant pas à un conseil personnalisé. Paramètres fiscaux à mettre à jour annuellement. Cf. feuille « 13. Sources ».

Sheet 3. Mode emploi
A1: 3. Mode d'emploi | H1: ↩ Retour sommaire
A2: Comment utiliser l'outil - workflow recommandé.
B4: WORKFLOW RECOMMANDÉ
B5: Étape 1 | C5: Vérifier les paramètres fiscaux (feuille « 4. Paramètres »). Mettre à jour les cellules jaunes si nécessaire (changements LF / PLFSS de l'année).
B6: Étape 2 | C6: Saisir le profil du client (feuille « 5. Profil ») : forme juridique, foyer fiscal, enveloppe à arbitrer, et activer/désactiver les dispositifs souhaités.
B7: Étape 3 | C7: Consulter le comparateur (feuille « 6. Comparateur ») pour identifier les dispositifs les plus efficaces (ratio net/coût).
B8: Étape 4 | C8: Approfondir avec le module population (feuilles 6 à 9) correspondant au régime social du client.
B9: Étape 5 | C9: Modéliser 4 stratégies à enveloppe constante (feuille « 11. Arbitrage ») et choisir la combinaison optimale.
B10: Étape 6 | C10: Présenter la synthèse dirigeant (feuille « 12. Synthèse ») au client. Imprimer ou exporter en PDF.
B12: LÉGENDE DES COULEURS
B13: Cellule bleue / fond jaune clair | C13: Input modifiable par l'utilisateur (montants, choix client).
B14: Cellule bleue / fond jaune marqué | C14: Paramètre fiscal à mettre à jour annuellement.
B15: Cellule noire | C15: Cellule de calcul / formule dérivée - ne pas modifier.
B16: Texte vert | C16: Lien vers une autre feuille (defined name ou référence inter-feuilles).
B17: Bandeau bleu marine | C17: En-tête de section.
B19: ONGLETS - CODES COULEUR
B20: Gris | C20: Page de garde, mode d'emploi, sources & disclaimer
B21: Violet | C21: Référentiel fiscal & social (paramètres)
B22: Orange | C22: Inputs / profil client
B23: Bleu marine | C23: Modules de calcul (comparateur + modules par population + arbitrage)
B24: Vert | C24: Synthèse dirigeant - livrable client
B26: EXPORT PDF & PERSONNALISATION CABINET
B27: 1. Renommer le fichier | C27: Avant export, renommer le classeur sous la forme « [Nom_Cabinet]_Outil_arbitrage_[ClientX]_v13.xlsx ». Ce nom apparaîtra automatiquement dans le pied de page de chaque page imprimée (signature cabinet).
B28: 2. Saisir les inputs cabinet | C28: En feuille « 5. Profil » section 1 : renseigner « Cabinet », « Expert-comptable en charge » et « Nom du client ». Ces valeurs se propagent automatiquement sur la page de garde et la synthèse.
B29: 3. Générer le PDF | C29: Fichier → Exporter → Créer un document PDF/XPS. Dans « Options », cocher « Feuilles » et sélectionner manuellement l'ordre suivant : 1. Garde / 2. Dashboard / 12. Synthèse / Scénarios A vs B (si pertinent) / 11. Arbitrage / 13. Sources.
B30: 4. Personnaliser le footer (optionnel) | C30: Pour ajouter un libellé spécifique (ex : « Cabinet Dupont - Confidentiel ») : Mise en page → Pied de page → modifier le bloc gauche. Le réglage est conservé sur toutes les feuilles configurées pour l'export.
A33: Outil indicatif à usage professionnel - ne se substitue pas à un conseil personnalisé. Paramètres fiscaux à mettre à jour annuellement (cf. feuille « 13. Sources »).

Sheet 4. Paramètres
A1: 3. Paramètres fiscaux & sociaux | H1: ↩ Retour sommaire
A2: Référentiel 2025 - à mettre à jour annuellement (cellules jaunes)
B4: 1. PLAFOND DE LA SÉCURITÉ SOCIALE (PASS)
B5: Libellé | C5: Valeur | E5: Source / référence
B6: PASS annuel 2026 (€) | C6: 48060 | E6: Arrêté du 22/12/2025 - JORF du 23/12/2025 (+2,0 % vs 2025)
B7: PMSS (mensuel) (€) | C7: =C6/12 | E7: Calculé : PASS / 12 = 4 005 € en 2026
B9: 2. BARÈME IMPÔT SUR LE REVENU 2026 (revenus 2025)
B10: Tranche | C10: Plafond haut (€) | D10: Taux | E10: Source
B11: Jusqu'à | C11: 11600 | D11: 0 | E11: CGI art. 197 - LF 2025 (revalorisation +1,8 %). Plafonnement quotient familial : 1 791 €/demi-part (CGI art. 197, I-2).
B12: De 11 601 à | C12: 29579 | D12: 0.11
B13: De 29 580 à | C13: 84577 | D13: 0.3
B14: De 84 578 à | C14: 181917 | D14: 0.41
B15: Au-delà de 181 917 | C15: 1000000000000 | D15: 0.45
B17: 3. CSG / CRDS & PRÉLÈVEMENTS SOCIAUX
B18: Libellé | C18: Taux | E18: Source
B19: CSG sur revenus d'activité - part déductible | C19: 0.068 | E19: CSS art. L.136-8, BOI-RSA-BASE-30-30
B20: CSG sur revenus d'activité - part non déductible | C20: 0.024 | E20: CSS art. L.136-8
B21: CRDS sur revenus d'activité (non déductible) | C21: 0.005 | E21: Ordonnance n°96-50 du 24/01/1996
B22: CSG/CRDS revenus d'activité - TOTAL | C22: 0.097 | E22: Calculé
B23: Assiette CSG/CRDS sur salaire (% du brut) | C23: 0.9825 | E23: Abattement de 1,75 % sur ≤4 PASS - CSS art. L.136-2
B24: CSG sur revenus du capital - part déductible 2026 | C24: 0.068 | E24: CSS art. L.136-6 - taux dérog. 9,2 % maintenu sur fonciers, AV
B25: Prélèvements sociaux sur revenus du capital 2026 - TOTAL | C25: 0.186 | E25: LFSS 2026 art. 12 : CSG 10,6 % + CRDS 0,5 % + PS 7,5 % = 18,6 % (vs 17,2 % avant)
B27: 4. COTISATIONS SOCIALES - TAUX MOYENS INDICATIFS
B28: Régime / nature | C28: Taux | E28: Précision / source
B29: Assimilé salarié - cotisations patronales (taux moyen, dirigeant cadre) | C29: 0.42 | E29: Hors réduction Fillon (dirigeant non éligible). Variable selon T1/T2 et conventions.
B30: Assimilé salarié - cotisations salariales hors CSG/CRDS | C30: 0.12 | E30: Retraite, prévoyance, AGIRC-ARRCO. Pas de cotisation chômage pour mandataires.
B31: TNS - taux global de cotisations (sur rémunération nette) | C31: 0.45 | E31: URSSAF (maladie, AF, CSG/CRDS) + retraite (RCI/CIPAV) + invalidité-décès. Variable selon revenu.
B32: Profession libérale BNC - taux global indicatif | C32: 0.45 | E32: URSSAF + caisse de retraite (CIPAV, CARMF, CARPV…). Variable selon profession.
B34: 5. FORFAIT SOCIAL (loi PACTE)
B35: Dispositif × effectif | C35: Taux | E35: Source
B36: Participation - < 50 salariés | C36: 0 | E36: CSS art. L.137-15 - exonéré loi PACTE 2019
B37: Participation - 50 à 249 salariés | C37: 0.2 | E37: CSS art. L.137-16 (taux normal, sauf accord conventionnel)
B38: Participation - ≥ 250 salariés | C38: 0.2 | E38: CSS art. L.137-16
B39: Intéressement - < 250 salariés | C39: 0 | E39: CSS art. L.137-15 - exonéré loi PACTE 2019
B40: Intéressement - ≥ 250 salariés | C40: 0.2 | E40: CSS art. L.137-16
B41: Abondement employeur PEE/PERCO - < 50 sal. | C41: 0 | E41: CSS art. L.137-15
B42: Abondement employeur PEE/PERCO - ≥ 50 sal. | C42: 0.2 | E42: CSS art. L.137-16
B44: 6. PLAFONDS DES DISPOSITIFS
B45: Dispositif | C45: Plafond / formule | E45: Source
B46: Participation - plafond individuel (75 % PASS) | C46: =0.75*PASS_2025 | E46: C. trav. art. L.3324-5
B47: Intéressement - plafond individuel (75 % PASS) | C47: =0.75*PASS_2025 | E47: C. trav. art. L.3314-8
B48: Intéressement - enveloppe globale (% MS brute) | C48: 0.2 | E48: C. trav. art. L.3314-8 (20 % de la masse salariale brute)
B49: Abondement PEE - plafond annuel (8 % PASS) | C49: =0.08*PASS_2025 | E49: C. trav. art. L.3332-11 - triplement contributions salarié
B50: Abondement PER collectif - plafond annuel (16 % PASS) | C50: =0.16*PASS_2025 | E50: C. trav. art. L.3334-6
B51: PER individuel - plafond déduction (10 % rev. pro., min. 10 % PASS, max 8 PASS) | C51: Voir module | E51: CGI art. 163 quatervicies
B52: Avantage en nature véhicule - forfait (% valeur achat) | C52: 0.09 | E52: Arrêté du 25/12/2002 modifié - véhicule < 5 ans achat
B53: Tickets restaurant - exonération part employeur 2025 (€/titre, max 60 %) | C53: 7.26 | E53: BOI-RSA-CHAMP-20-30-10-10 - valeur 2025
B54: CESU préfinancé - exonération annuelle (€/an/salarié) | C54: 2540 | E54: CSS art. L.7233-4 - Loi 2024 (relèvement)
B55: Chèques cadeaux - tolérance URSSAF (% PMSS/événement) | C55: 0.05 | E55: Lettre-circ. ACOSS 2011-024 - 5 % PMSS par événement et bénéficiaire
B56: Chèques vacances - exonération (≤30 % SMIC mensuel/an) | C56: 0.3 | E56: C. tour. art. L.411-1 et s.
B58: 7. FISCALITÉ DES DIVIDENDES & REVENUS DU CAPITAL
B59: Élément | C59: Taux / valeur | E59: Source
B60: PFU - taux global 2026 (IR + PS) | C60: 0.314 | E60: LFSS 2026 - 12,8 % IR + 18,6 % PS (vs 30 % en 2025)
B61: PFU - part IR forfaitaire | C61: 0.128 | E61: CGI art. 200 A - inchangé
B62: Abattement dividendes - option barème IR | C62: 0.4 | E62: CGI art. 158, 3-2°
B63: Seuil cotisations TNS sur dividendes (gérant maj. SARL/SELARL) | C63: 0.1 | E63: CSS art. L.131-6, 3° - > 10 % capital + primes + CC associé
B65: 8. IMPÔT SUR LES SOCIÉTÉS
B66: Tranche / régime | C66: Taux | E66: Source
B67: IS - taux réduit PME (bénéfice ≤ 42 500 €) | C67: 0.15 | E67: CGI art. 219, I-b - PME (CA < 10 M€, capital détenu ≥ 75 % personnes physiques)
B68: IS - taux normal au-delà de 42 500 € | C68: 0.25 | E68: CGI art. 219, I
B69: Plafond IS taux réduit (€) | C69: 42500 | E69: CGI art. 219, I-b
B72: 9. PLAFONNEMENT DU QUOTIENT FAMILIAL
B73: Élément | C73: Valeur | E73: Source
B74: Plafond 1 807 € par demi-part excédentaire (€) | C74: 1807 | E74: CGI art. 197, I-2° - LF 2026, indexation +0,9 % (vs 1 791 € en 2025). Cas général.
B75: Parent isolé (case T) - 1ère personne à charge | C75: 4262 | E75: LF 2026 - BOI-IR-LIQ-20-20-20
B76: Personne seule ayant élevé seule un enfant ≥ 5 ans (case L) | C76: 1079 | E76: LF 2026 - CGI art. 195
B77: Veuf avec enfants à charge - plafond cumulé | C77: 5625 | E77: LF 2026 - CGI art. 197
B78: Ancien combattant > 74 ans ou invalide - demi-part suppl. | C78: 3608 | E78: LF 2026 - CGI art. 195
B81: 10. CONTRIBUTION EXCEPTIONNELLE HAUTS REVENUS (CEHR)
B82: Élément | C82: Valeur | E82: Source
B83: CEHR - taux tranche intermédiaire (%) | C83: 0.03 | E83: CGI art. 223 sexies
B84: CEHR - taux tranche supérieure (%) | C84: 0.04 | E84: CGI art. 223 sexies
B85: CEHR - seuil 1 célibataire/divorcé/veuf (€) | C85: 250000 | E85: CGI art. 223 sexies
B86: CEHR - seuil 2 célibataire/divorcé/veuf (€) | C86: 500000 | E86: CGI art. 223 sexies
B87: CEHR - seuil 1 marié/pacsé (€) | C87: 500000 | E87: CGI art. 223 sexies
B88: CEHR - seuil 2 marié/pacsé (€) | C88: 1000000 | E88: CGI art. 223 sexies
B90: 11. CONTRIBUTION DIFFÉRENTIELLE HAUTS REVENUS (CDHR) - nouveauté 2026
B91: Élément | C91: Valeur | E91: Source
B92: CDHR - taux plancher d'imposition (% RFR) | C92: 0.2 | E92: CGI art. 224 - LF 2025 art. 10, pérennisée LF 2026 art. 2
B93: CDHR - seuil RFR célibataire/divorcé/veuf (€) | C93: 250000 | E93: CGI art. 224
B94: CDHR - seuil RFR marié/pacsé (€) | C94: 500000 | E94: CGI art. 224
B95: CDHR - seuil HAUT lissage célibataire (€) | C95: 330000 | E95: Zone de transition 250-330 k€
B96: CDHR - seuil HAUT lissage marié/pacsé (€) | C96: 660000 | E96: Zone de transition 500-660 k€
B97: ✓ Lissage modélisé (v13) - décote linéaire dans la zone de transition (250-330k célib / 500-660k marié). Limites restantes : pas de retraitement des revenus exceptionnels au 1/4 ; RFR approximé par le revenu net imposable. À affiner par l'expert-comptable pour les déclarations effectives.
B99: 12. HYPOTHÈSES PROJECTION 5 ANS (capitalisation épargne salariale & PER)
B100: Élément | C100: Valeur | E100: Hypothèse / source
B101: Rendement annuel moyen - PEE / PER (%) | C101: 0.04 | E101: Hypothèse cabinet (typ. 3-5 % nets de frais sur fonds diversifiés).
B102: Rendement annuel moyen - Cash dirigeant (%) | C102: 0.02 | E102: Livret A 3 %, fonds euros 2,5 % - placement de défaisance prudent.
B103: Horizon de projection (années) | C103: 5 | E103: 5 ans = horizon court terme, hors fiscalité de sortie PER.
B105: 13. COEFFICIENTS DE RISQUE PAR DISPOSITIF (scoring pondéré)
B106: Dispositif | C106: Coefficient | E106: Justification éditoriale
B107: Salaire / rémunération directe | C107: 1 | E107: Référence - sécurité juridique maximale.
B108: Dividendes (PFU) | C108: 0.95 | E108: Hors cas TNS gérant maj. > 10 % capital.
B109: Participation | C109: 1 | E109: Cadre légal stable (loi PACTE).
B110: Intéressement | C110: 1 | E110: Idem.
B111: Abondement PEE | C111: 1 | E111: Idem.
B112: Abondement PER collectif | C112: 1 | E112: Idem.
B113: PER individuel | C113: 0.95 | E113: Fiscalité de sortie (rente/capital) à anticiper.
B114: Avantages en nature (véhicule, NTIC...) | C114: 0.9 | E114: Évaluation forfait vs réel - risque de redressement si imprécis.
B115: Tickets restaurant | C115: 1 | E115: Plafond 7,26 €/titre, 60 % max.
...

Sheet 5. Profil
A1: 4. Profil client | H1: ↩ Retour sommaire
A2: Saisir le profil du dirigeant / client. Les cellules bleues sont à compléter.
B4: 1. IDENTITÉ DU CLIENT
B5: Nom du client / dénomination sociale | C5: [À renseigner]
B6: Référence dossier | C6: [Réf. cabinet]
B7: Date de la simulation | C7: =TODAY()
B8: Expert-comptable en charge | C8: [Nom collaborateur]
B9: Cabinet | C9: [Nom du cabinet]
B11: 2. STRUCTURE & RÉGIME SOCIAL
B12: Forme juridique | C12: SAS / SASU | E12: Liste déroulante. Choisir la forme du client.
B13: Régime social applicable | C13: =IF(C12="SAS / SASU","Assimilé salarié",IF(C12="SARL (gérance minoritaire)","Assimilé salarié",IF(C12="SARL (gérance majoritaire)","TNS",IF(C12="EURL (gérant associé unique)","TNS",IF(C12="EI (entrepreneur individuel)","TNS",IF(C12="EI à l'IS","TNS",IF(C12="SELARL","TNS (libéral)",IF(C12="SELAS","Assimilé salarié (libéral)",IF(C12="SCP","TNS (libéral)",IF(C12="Salarié (sans structure)","Salarié","À préciser")))))))))) | E13: Déduit automatiquement de la forme juridique.
B14: Effectif de l'entreprise | C14: 11-49 salariés | E14: Seuils légaux : 11 (mutuelle obli.), 50 (participation obli., forfait social), 250 (forfait intéressement). Cf. feuille « 4. Paramètres » §5.
B15: Part de capital détenue par le dirigeant (pour TNS) | C15: 0.5 | E15: Pour TNS : la fraction des dividendes excédant 10 % du (capital social + primes + CC associé) est soumise à cotisations TNS.
B16: Capital social + primes + CCA (€) [TNS uniquement] | C16: 10000 | E16: Base de calcul du seuil 10 %. Au-delà, la fraction de dividendes est requalifiée en rémunération TNS (cotisations ~45 % + IR au barème) au lieu du PFU. Ignoré pour assimilé salarié / salarié. CGI art. L. 131-6 al. 8 CSS, jurisprudence Cass. soc. 2018.
B18: 3. FOYER FISCAL
B19: Situation familiale | C19: Marié / pacsé
B20: Nombre de parts fiscales | C20: 2 | E20: 1 / 2 / 2,5 / 3… selon situation et nombre d'enfants. Plafonnement quotient familial : 1 807 €/demi-part (2026).
B21: Autres revenus imposables du foyer (€/an) | C21: 0 | E21: Salaires conjoint, revenus fonciers, BIC/BNC tiers… au barème. Pour le TMI marginal réel.
B22: Dividendes bruts perçus par le foyer (€/an) | C22: 0 | E22: Distributions effectives au foyer (hors enveloppe arbitrage). Entrent dans le RFR au PFU pour activer correctement la CDHR.
B23: Situation particulière (plafond QF spécifique) | C23: Aucune (cas général) | E23: Sélectionner si applicable : ajuste le plafond du QF (cf. Paramètres §9). Parent isolé : 4 262 € sur 1ère personne à charge. Veuf : plafond cumulé 5 625 €. Invalide : 3 608 €.
B25: 4. ENVELOPPE À ARBITRER
B26: Mode de pilotage | C26: Coût employeur global
B27: Enveloppe (€/an) | C27: 120000 | E27: Coût total annuel pour la société (charges incluses), ou cible nette dirigeant selon mode.
B28: Bénéfice IS de la société (€/an) | C28: 200000 | E28: Bénéfice avant rémunération du dirigeant. Sert au calcul des dividendes distribuables après IS.
B30: 5. ACTIVATION DES DISPOSITIFS
B31: Participation | C31: Oui | E31: Versement en N+1 sur résultat ; PEE/PERECO.
B32: Intéressement | C32: Oui | E32: Accord pluriannuel ; aléatoire et collectif.
B33: Abondement employeur PEE | C33: Oui | E33: Versement complémentaire aux dépôts du salarié.
B34: Abondement employeur PER collectif (PERECO) | C34: Oui | E34: Idem, plafond 16 % PASS.
B35: PER individuel (PERIN) | C35: Oui | E35: Versements déductibles du revenu imposable.
B36: Avantages en nature (véhicule, logement, NTIC) | C36: Oui | E36: Forfait ou réel - cf. arrêté 25/12/2002.
B37: Tickets restaurant | C37: Oui | E37: Exonération part employeur 7,26 €/titre (60 % max).
B38: CESU préfinancé | C38: Oui | E38: Exonéré jusqu'à 2 540 €/an/salarié.
B39: Chèques cadeaux & vacances | C39: Oui | E39: Tolérance URSSAF & exo chèques vacances.
B40: Mutuelle / prévoyance employeur | C40: Oui | E40: Contrat collectif obligatoire - déductible société.
B41: Indemnités kilométriques | C41: Non | E41: Sur la base du barème fiscal ou réelle.
B42: 💸 Cashback (programme partenaire) | C42: Non | E42: 🔴 Niveau de risque optimisé. Cf. note technique en feuille « 13. Sources ».
B44: 6. MONTANTS DES DISPOSITIFS (€/an, par bénéficiaire)
B45: Participation versée | C45: 1500
B46: Intéressement versé | C46: 2500
B47: Abondement PEE | C47: 1500
B48: Abondement PER collectif | C48: 3000
B49: Versement PER individuel (déductible) | C49: 5000
B50: Avantages en nature (valeur) | C50: 3600
B51: Tickets restaurant - part employeur | C51: 1742
B52: CESU préfinancé | C52: 2000
B53: Chèques cadeaux & vacances | C53: 500
B54: Mutuelle / prévoyance employeur | C54: 1200
B55: Indemnités kilométriques | C55: 0
B56: 💸 Cashback annuel | C56: 360
B58: 7. 💸 MODE DE DÉPLOIEMENT DU CASHBACK
B59: Mode de déploiement | C59: Conforme aux recommandations Sources | E59: « Conforme » : souscription nominative hors lien employeur, montants prudents, doc formalisée → coefficient 0,85, badge 🟠 À valider. « Standard » : sans structuration spécifique → coefficient 0,55, badge 🔴 Optimisé.
B60: Coefficient de risque effectif | C60: =IF(C59="Conforme aux recommandations Sources",RISK_CASHBACK_CONFORME,RISK_CASHBACK_STANDARD) | E60: Calculé automatiquement selon le mode de déploiement choisi.
B61: Niveau de risque affiché | C61: =IF(C59="Conforme aux recommandations Sources","🟠 À valider","🔴 Optimisé") | E61: Badge propagé au Dashboard.
B64: ✅ VALIDATION DES INPUTS (vérifications automatiques)
B65: Règle de cohérence | C65: Statut | E65: Action si problème
B66: Régime social libéral compatible avec mode 'Coût employeur' | C66: =IF(IF(AND(REGIME_SOCIAL="TNS (libéral)",INDEX(C:C,MATCH("Mode de pilotage",B:B,0))="Coût employeur global"),FALSE(),TRUE()),"✓","⚠") | E66: =IF(IF(AND(REGIME_SOCIAL="TNS (libéral)",INDEX(C:C,MATCH("Mode de pilotage",B:B,0))="Coût employeur global"),FALSE(),TRUE()),"","Pour un libéral, le concept 'coût employeur' ne s'applique pas - passer en mode 'Rémunération nette dirigeant cible'.")
B67: Enveloppe ≥ 1 SMIC annuel (21 876 €) | C67: =IF(ENVELOPPE>=21876,"✓","⚠") | E67: =IF(ENVELOPPE>=21876,"","L'enveloppe paraît trop faible - vérifier la cohérence (SMIC 2026 : 1 823,03 €/mois).")
B68: Abondement PEE ≤ plafond légal (8 % PASS = 3 845 €) | C68: =IF(IF(AND(TOG_ABO_PEE="Oui",M_ABO_PEE>3845),FALSE(),TRUE()),"✓","⚠") | E68: =IF(IF(AND(TOG_ABO_PEE="Oui",M_ABO_PEE>3845),FALSE(),TRUE()),"","Abondement PEE > 8 % PASS - réduire à 3 845 € max (CSS art. L.3332-11).")
B69: Abondement PER collectif ≤ plafond légal (16 % PASS = 7 690 €) | C69: =IF(IF(AND(TOG_ABO_PER="Oui",M_ABO_PER>7690),FALSE(),TRUE()),"✓","⚠") | E69: =IF(IF(AND(TOG_ABO_PER="Oui",M_ABO_PER>7690),FALSE(),TRUE()),"","Abondement PER collectif > 16 % PASS - réduire à 7 690 € max (CSS art. L.224-20).")
B70: Participation cohérente avec effectif (obligatoire ≥ 50) | C70: =IF(IF(AND(OR(EFFECTIF="Sans salarié",EFFECTIF="1-10 salariés",EFFECTIF="11-49 salariés"),TOG_PARTICIPATION="Oui",M_PARTICIPATION>36045),FALSE(),TRUE()),"✓","⚠") | E70: =IF(IF(AND(OR(EFFECTIF="Sans salarié",EFFECTIF="1-10 salariés",EFFECTIF="11-49 salariés"),TOG_PARTICIPATION="Oui",M_PARTICIPATION>36045),FALSE(),TRUE()),"","Participation facultative sous 50 salariés mais plafond individuel 75 % PASS = 36 045 € s'applique.")
B71: Intéressement individuel ≤ plafond (75 % PASS = 36 045 €) | C71: =IF(IF(AND(TOG_INTERESSEMENT="Oui",M_INTERESSEMENT>36045),FALSE(),TRUE()),"✓","⚠") | E71: =IF(IF(AND(TOG_INTERESSEMENT="Oui",M_INTERESSEMENT>36045),FALSE(),TRUE()),"","Montant intéressement individuel > 75 % PASS - réduire à 36 045 € max.")
B72: Bénéfice IS ≥ enveloppe en mode coût employeur | C72: =IF(IF(INDEX(C:C,MATCH("Mode de pilotage",B:B,0))="Coût employeur global",INDEX(C:C,MATCH("Bénéfice IS de la société (€/an)",B:B,0))>=ENVELOPPE,TRUE()),"✓","⚠") | E72: =IF(IF(INDEX(C:C,MATCH("Mode de pilotage",B:B,0))="Coût employeur global",INDEX(C:C,MATCH("Bénéfice IS de la société (€/an)",B:B,0))>=ENVELOPPE,TRUE()),"","Le bénéfice IS de la société doit couvrir l'enveloppe - vérifier la cohérence.")
B73: Dividendes foyer cohérents (≤ 5 × enveloppe) | C73: =IF(IF(DIVIDENDES_FOYER<=5*ENVELOPPE,TRUE(),FALSE()),"✓","⚠") | E73: =IF(IF(DIVIDENDES_FOYER<=5*ENVELOPPE,TRUE(),FALSE()),"","Dividendes foyer > 5× l'enveloppe - vérifier si ce sont bien des dividendes hors arbitrage ou s'il faut ajuster l'enveloppe.")
B74: Cashback en mode 'Standard' = risque URSSAF assumé | C74: =IF(IF(AND(TOG_CASHBACK="Oui",CASHBACK_MODE="Standard / non documenté"),FALSE(),TRUE()),"✓","⚠") | E74: =IF(IF(AND(TOG_CASHBACK="Oui",CASHBACK_MODE="Standard / non documenté"),FALSE(),TRUE()),"","Mode Standard : provision risque URSSAF calculée en Synthèse. Confirmer avec le client que le risque est assumé.")
A77: Outil indicatif à usage professionnel - ne se substitue pas à un conseil personnalisé. Paramètres fiscaux à mettre à jour annuellement (cf. feuille « 13. Sources »).

Sheet 6. Comparateur
A1: 5. Comparateur de dispositifs | O1: ↩ Retour sommaire
A2: Pour chaque dispositif activé, coût société, net dirigeant après IR et efficacité fiscale-sociale.
B4: A. PARAMÈTRES DÉRIVÉS DU PROFIL CLIENT
B5: Élément | C5: Valeur | D5: Mode de calcul
B6: Revenu imposable estimé par part (€) | C6: =IF(REGIME_SOCIAL="TNS",ENVELOPPE*0.7,IF(REGIME_SOCIAL="TNS (libéral)",ENVELOPPE*0.7,IF(REGIME_SOCIAL="Salarié",ENVELOPPE*0.55,ENVELOPPE*0.55)))/PARTS+AUTRES_REV/PARTS | D6: Estimé : enveloppe × ratio de net imposable (55 % salarié / 70 % TNS) / parts + autres rev./parts.
B7: TMI marginal estimé | C7: =IF(C6<=IR_PLAFOND_T1,0,IF(C6<=IR_PLAFOND_T2,IR_TAUX_T2,IF(C6<=IR_PLAFOND_T3,IR_TAUX_T3,IF(C6<=IR_PLAFOND_T4,IR_TAUX_T4,IR_TAUX_T5)))) | D7: Taux marginal applicable au revenu par part (cf. barème 2025).
B8: Forfait social - Participation (auto) | C8: =IF(OR(EFFECTIF="Sans salarié",EFFECTIF="1-10 salariés",EFFECTIF="11-49 salariés"),FS_PART_LT50,IF(EFFECTIF="50-249 salariés",FS_PART_50_249,IF(EFFECTIF="≥ 250 salariés",FS_PART_GE250,0))) | D8: Calculé selon effectif (cf. feuille « 4. Paramètres »).
B9: Forfait social - Intéressement (auto) | C9: =IF(EFFECTIF="≥ 250 salariés",FS_INT_GE250,FS_INT_LT250) | D9: Idem.
B10: Forfait social - Abondement (auto) | C10: =IF(OR(EFFECTIF="Sans salarié",EFFECTIF="1-10 salariés",EFFECTIF="11-49 salariés"),FS_ABO_LT50,FS_ABO_GE50) | D10: Idem.
B12: B. MATRICE DE RENTABILITÉ DES DISPOSITIFS - incluant scoring pondéré
B13: Dispositif | C13: Activé | D13: Montant input (€) | E13: Coût société (€) | F13: Coût bénéficiaire (€) | G13: Cotisations & PS (€) | H13: Net imposable (€) | I13: IR estimé (€) | J13: Net après IR (€) | K13: Ratio net / coût (%) | L13: Coef. risque | M13: Score ajusté (%) | N13: Top 3
B14: Salaire classique (référence) | C14: Réf. | D14: =ENVELOPPE/(1+TX_PATRONAL) | E14: =ENVELOPPE | F14: =0 | G14: =D14*TX_SALARIAL+D14*ASSIETTE_CSG_SAL*TX_CSG_CRDS_ACT | H14: =D14-D14*TX_SALARIAL-D14*ASSIETTE_CSG_SAL*0.068 | I14: =H14*$C$7 | J14: =D14-G14-I14 | K14: =IFERROR(J14/(E14+F14),0) | L14: =RISK_SALAIRE | M14: =K14*L14 | N14: -
B15: Dividendes - PFU 30 % | C15: Variable | D15: =10000 | E15: =D15/(1-TX_IS_NORMAL) | F15: =0 | G15: =D15*TX_PFU | H15: =0 | I15: =0 | J15: =D15-G15 | K15: =IFERROR(J15/E15,0) | L15: =RISK_DIVIDENDES | M15: =K15*L15 | N15: -
B16: Participation (placée 5 ans en PEE) | C16: =TOG_PARTICIPATION | D16: =M_PARTICIPATION | E16: =IF(C16="Oui",D16*(1+$C$8),0) | F16: =0 | G16: =IF(C16="Oui",D16*TX_CSG_CRDS_ACT,0) | H16: =0 | I16: =0 | J16: =IF(C16="Oui",D16-G16,0) | K16: =IFERROR(J16/E16,0) | L16: =RISK_PARTICIPATION | M16: =K16*L16 | N16: =IF(C16<>"Oui","",IF((SUMPRODUCT(($C$16:$C$27="Oui")*($M$16:$M$27>M16))+SUMPRODUCT(($C$16:$C$27="Oui")*($M$16:$M$27=M16)*(ROW($M$16:$M$27)<16)))=0,"🥇",IF((SUMPRODUCT(($C$16:$C$27="Oui")*($M$16:$M$27>M16))+SUMPRODUCT(($C$16:$C$27="Oui")*($M$16:$M$27=M16)*(ROW($M$16:$M$27)<16)))=1,"🥈",IF((SUMPRODUCT(($C$16:$C$27="Oui")*($M$16:$M$27>M16))+SUMPRODUCT(($C$16:$C$27="Oui")*($M$16:$M$27=M16)*(ROW($M$16:$M$27)<16)))=2,"🥉",""))))
B17: Intéressement (placé 5 ans en PEE) | C17: =TOG_INTERESSEMENT | D17: =M_INTERESSEMENT | E17: =IF(C17="Oui",D17*(1+$C$9),0) | F17: =0 | G17: =IF(C17="Oui",D17*TX_CSG_CRDS_ACT,0) | H17: =0 | I17: =0 | J17: =IF(C17="Oui",D17-G17,0) | K17: =IFERROR(J17/E17,0) | L17: =RISK_INTERESSEMENT | M17: =K17*L17 | N17: =IF(C17<>"Oui","",IF((SUMPRODUCT(($C$16:$C$27="Oui")*($M$16:$M$27>M17))+SUMPRODUCT(($C$16:$C$27="Oui")*($M$16:$M$27=M17)*(ROW($M$16:$M$27)<17)))=0,"🥇",IF((SUMPRODUCT(($C$16:$C$27="Oui")*($M$16:$M$27>M17))+SUMPRODUCT(($C$16:$C$27="Oui")*($M$16:$M$27=M17)*(ROW($M$16:$M$27)<17)))=1,"🥈",IF((SUMPRODUCT(($C$16:$C$27="Oui")*($M$16:$M$27>M17))+SUMPRODUCT(($C$16:$C$27="Oui")*($M$16:$M$27=M17)*(ROW($M$16:$M$27)<17)))=2,"🥉",""))))
B18: Abondement employeur PEE | C18: =TOG_ABO_PEE | D18: =M_ABO_PEE | E18: =IF(C18="Oui",D18*(1+$C$10),0) | F18: =0 | G18: =IF(C18="Oui",D18*TX_CSG_CRDS_ACT,0) | H18: =0 | I18: =0 | J18: =IF(C18="Oui",D18-G18,0) | K18: =IFERROR(J18/E18,0) | L18: =RISK_ABO_PEE | M18: =K18*L18 | N18: =IF(C18<>"Oui","",IF((SUMPRODUCT(($C$16:$C$27="Oui")*($M$16:$M$27>M18))+SUMPRODUCT(($C$16:$C$27="Oui")*($M$16:$M$27=M18)*(ROW($M$16:$M$27)<18)))=0,"🥇",IF((SUMPRODUCT(($C$16:$C$27="Oui")*($M$16:$M$27>M18))+SUMPRODUCT(($C$16:$C$27="Oui")*($M$16:$M$27=M18)*(ROW($M$16:$M$27)<18)))=1,"🥈",IF((SUMPRODUCT(($C$16:$C$27="Oui")*($M$16:$M$27>M18))+SUMPRODUCT(($C$16:$C$27="Oui")*($M$16:$M$27=M18)*(ROW($M$16:$M$27)<18)))=2,"🥉",""))))
B19: Abondement employeur PER collectif | C19: =TOG_ABO_PER | D19: =M_ABO_PER | E19: =IF(C19="Oui",D19*(1+$C$10),0) | F19: =0 | G19: =IF(C19="Oui",D19*TX_CSG_CRDS_ACT,0) | H19: =0 | I19: =0 | J19: =IF(C19="Oui",D19-G19,0) | K19: =IFERROR(J19/E19,0) | L19: =RISK_ABO_PER | M19: =K19*L19 | N19: =IF(C19<>"Oui","",IF((SUMPRODUCT(($C$16:$C$27="Oui")*($M$16:$M$27>M19))+SUMPRODUCT(($C$16:$C$27="Oui")*($M$16:$M$27=M19)*(ROW($M$16:$M$27)<19)))=0,"🥇",IF((SUMPRODUCT(($C$16:$C$27="Oui")*($M$16:$M$27>M19))+SUMPRODUCT(($C$16:$C$27="Oui")*($M$16:$M$27=M19)*(ROW($M$16:$M$27)<19)))=1,"🥈",IF((SUMPRODUCT(($C$16:$C$27="Oui")*($M$16:$M$27>M19))+SUMPRODUCT(($C$16:$C$27="Oui")*($M$16:$M$27=M19)*(ROW($M$16:$M$27)<19)))=2,"🥉",""))))
B20: PER individuel (versement déductible) | C20: =TOG_PERIN | D20: =M_PERIN | E20: =0 | F20: =IF(C20="Oui",D20*(1-$C$7),0) | G20: =0 | H20: =IF(C20="Oui",-D20,0) | I20: =IF(C20="Oui",-D20*$C$7,0) | J20: =IF(C20="Oui",D20-F20,0) | K20: =IFERROR(J20/MAX(F20,1),0) | L20: =RISK_PERIN | M20: =K20*L20 | N20: =IF(C20<>"Oui","",IF((SUMPRODUCT(($C$16:$C$27="Oui")*($M$16:$M$27>M20))+SUMPRODUCT(($C$16:$C$27="Oui")*($M$16:$M$27=M20)*(ROW($M$16:$M$27)<20)))=0,"🥇",IF((SUMPRODUCT(($C$16:$C$27="Oui")*($M$16:$M$27>M20))+SUMPRODUCT(($C$16:$C$27="Oui")*($M$16:$M$27=M20)*(ROW($M$16:$M$27)<20)))=1,"🥈",IF((SUMPRODUCT(($C$16:$C$27="Oui")*($M$16:$M$27>M20))+SUMPRODUCT(($C$16:$C$27="Oui")*($M$16:$M$27=M20)*(ROW($M$16:$M$27)<20)))=2,"🥉",""))))
B21: Avantages en nature (véhicule, NTIC...) | C21: =TOG_AVANTAGES | D21: =M_AVANTAGES | E21: =IF(C21="Oui",D21*(1+TX_PATRONAL),0) | F21: =0 | G21: =IF(C21="Oui",D21*(TX_SALARIAL+ASSIETTE_CSG_SAL*0.068),0) | H21: =IF(C21="Oui",D21*(1-TX_SALARIAL-ASSIETTE_CSG_SAL*0.068),0) | I21: =IF(C21="Oui",H21*$C$7,0) | J21: =IF(C21="Oui",D21-G21-I21,0) | K21: =IFERROR(J21/E21,0) | L21: =RISK_AVANTAGES | M21: =K21*L21 | N21: =IF(C21<>"Oui","",IF((SUMPRODUCT(($C$16:$C$27="Oui")*($M$16:$M$27>M21))+SUMPRODUCT(($C$16:$C$27="Oui")*($M$16:$M$27=M21)*(ROW($M$16:$M$27)<21)))=0,"🥇",IF((SUMPRODUCT(($C$16:$C$27="Oui")*($M$16:$M$27>M21))+SUMPRODUCT(($C$16:$C$27="Oui")*($M$16:$M$27=M21)*(ROW($M$16:$M$27)<21)))=1,"🥈",IF((SUMPRODUCT(($C$16:$C$27="Oui")*($M$16:$M$27>M21))+SUMPRODUCT(($C$16:$C$27="Oui")*($M$16:$M$27=M21)*(ROW($M$16:$M$27)<21)))=2,"🥉",""))))
B22: Tickets restaurant (part employeur exonérée) | C22: =TOG_TR | D22: =M_TR | E22: =IF(C22="Oui",D22,0) | F22: =0 | G22: =0 | H22: =0 | I22: =0 | J22: =IF(C22="Oui",D22,0) | K22: =IFERROR(J22/E22,0) | L22: =RISK_TR | M22: =K22*L22 | N22: =IF(C22<>"Oui","",IF((SUMPRODUCT(($C$16:$C$27="Oui")*($M$16:$M$27>M22))+SUMPRODUCT(($C$16:$C$27="Oui")*($M$16:$M$27=M22)*(ROW($M$16:$M$27)<22)))=0,"🥇",IF((SUMPRODUCT(($C$16:$C$27="Oui")*($M$16:$M$27>M22))+SUMPRODUCT(($C$16:$C$27="Oui")*($M$16:$M$27=M22)*(ROW($M$16:$M$27)<22)))=1,"🥈",IF((SUMPRODUCT(($C$16:$C$27="Oui")*($M$16:$M$27>M22))+SUMPRODUCT(($C$16:$C$27="Oui")*($M$16:$M$27=M22)*(ROW($M$16:$M$27)<22)))=2,"🥉",""))))
B23: CESU préfinancé (exonéré ≤ 2 540 €) | C23: =TOG_CESU | D23: =M_CESU | E23: =IF(C23="Oui",D23,0) | F23: =0 | G23: =0 | H23: =0 | I23: =0 | J23: =IF(C23="Oui",D23,0) | K23: =IFERROR(J23/E23,0) | L23: =RISK_CESU | M23: =K23*L23 | N23: =IF(C23<>"Oui","",IF((SUMPRODUCT(($C$16:$C$27="Oui")*($M$16:$M$27>M23))+SUMPRODUCT(($C$16:$C$27="Oui")*($M$16:$M$27=M23)*(ROW($M$16:$M$27)<23)))=0,"🥇",IF((SUMPRODUCT(($C$16:$C$27="Oui")*($M$16:$M$27>M23))+SUMPRODUCT(($C$16:$C$27="Oui")*($M$16:$M$27=M23)*(ROW($M$16:$M$27)<23)))=1,"🥈",IF((SUMPRODUCT(($C$16:$C$27="Oui")*($M$16:$M$27>M23))+SUMPRODUCT(($C$16:$C$27="Oui")*($M$16:$M$27=M23)*(ROW($M$16:$M$27)<23)))=2,"🥉",""))))
B24: Chèques cadeaux & vacances (tolérance URSSAF) | C24: =TOG_CADO | D24: =M_CADO | E24: =IF(C24="Oui",D24,0) | F24: =0 | G24: =0 | H24: =0 | I24: =0 | J24: =IF(C24="Oui",D24,0) | K24: =IFERROR(J24/E24,0) | L24: =RISK_CADO | M24: =K24*L24 | N24: =IF(C24<>"Oui","",IF((SUMPRODUCT(($C$16:$C$27="Oui")*($M$16:$M$27>M24))+SUMPRODUCT(($C$16:$C$27="Oui")*($M$16:$M$27=M24)*(ROW($M$16:$M$27)<24)))=0,"🥇",IF((SUMPRODUCT(($C$16:$C$27="Oui")*($M$16:$M$27>M24))+SUMPRODUCT(($C$16:$C$27="Oui")*($M$16:$M$27=M24)*(ROW($M$16:$M$27)<24)))=1,"🥈",IF((SUMPRODUCT(($C$16:$C$27="Oui")*($M$16:$M$27>M24))+SUMPRODUCT(($C$16:$C$27="Oui")*($M$16:$M$27=M24)*(ROW($M$16:$M$27)<24)))=2,"🥉",""))))
B25: Mutuelle / prévoyance employeur | C25: =TOG_MUTUELLE | D25: =M_MUTUELLE | E25: =IF(C25="Oui",D25,0) | F25: =0 | G25: =IF(C25="Oui",D25*TX_CSG_CRDS_ACT,0) | H25: =0 | I25: =0 | J25: =IF(C25="Oui",D25-G25,0) | K25: =IFERROR(J25/E25,0) | L25: =RISK_MUTUELLE | M25: =K25*L25 | N25: =IF(C25<>"Oui","",IF((SUMPRODUCT(($C$16:$C$27="Oui")*($M$16:$M$27>M25))+SUMPRODUCT(($C$16:$C$27="Oui")*($M$16:$M$27=M25)*(ROW($M$16:$M$27)<25)))=0,"🥇",IF((SUMPRODUCT(($C$16:$C$27="Oui")*($M$16:$M$27>M25))+SUMPRODUCT(($C$16:$C$27="Oui")*($M$16:$M$27=M25)*(ROW($M$16:$M$27)<25)))=1,"🥈",IF((SUMPRODUCT(($C$16:$C$27="Oui")*($M$16:$M$27>M25))+SUMPRODUCT(($C$16:$C$27="Oui")*($M$16:$M$27=M25)*(ROW($M$16:$M$27)<25)))=2,"🥉",""))))
B26: Indemnités kilométriques (barème fiscal) | C26: =TOG_IK | D26: =M_IK | E26: =IF(C26="Oui",D26,0) | F26: =0 | G26: =0 | H26: =0 | I26: =0 | J26: =IF(C26="Oui",D26,0) | K26: =IFERROR(J26/E26,0) | L26: =RISK_IK | M26: =K26*L26 | N26: =IF(C26<>"Oui","",IF((SUMPRODUCT(($C$16:$C$27="Oui")*($M$16:$M$27>M26))+SUMPRODUCT(($C$16:$C$27="Oui")*($M$16:$M$27=M26)*(ROW($M$16:$M$27)<26)))=0,"🥇",IF((SUMPRODUCT(($C$16:$C$27="Oui")*($M$16:$M$27>M26))+SUMPRODUCT(($C$16:$C$27="Oui")*($M$16:$M$27=M26)*(ROW($M$16:$M$27)<26)))=1,"🥈",IF((SUMPRODUCT(($C$16:$C$27="Oui")*($M$16:$M$27>M26))+SUMPRODUCT(($C$16:$C$27="Oui")*($M$16:$M$27=M26)*(ROW($M$16:$M$27)<26)))=2,"🥉",""))))
B27: 💸 Cashback (programme partenaire) | C27: =TOG_CASHBACK | D27: =M_CASHBACK | E27: =IF(C27="Oui",D27,0) | F27: =0 | G27: =0 | H27: =0 | I27: =0 | J27: =IF(C27="Oui",D27,0) | K27: =IFERROR(J27/MAX(E27,1),0) | L27: =RISK_CASHBACK | M27: =K27*L27 | N27: =IF(C27<>"Oui","",IF((SUMPRODUCT(($C$16:$C$27="Oui")*($M$16:$M$27>M27))+SUMPRODUCT(($C$16:$C$27="Oui")*($M$16:$M$27=M27)*(ROW($M$16:$M$27)<27)))=0,"🥇",IF((SUMPRODUCT(($C$16:$C$27="Oui")*($M$16:$M$27>M27))+SUMPRODUCT(($C$16:$C$27="Oui")*($M$16:$M$27=M27)*(ROW($M$16:$M$27)<27)))=1,"🥈",IF((SUMPRODUCT(($C$16:$C$27="Oui")*($M$16:$M$27>M27))+SUMPRODUCT(($C$16:$C$27="Oui")*($M$16:$M$27=M27)*(ROW($M$16:$M$27)<27)))=2,"🥉",""))))
B28: TOTAL DISPOSITIFS ACTIVÉS (hors salaire & dividendes) | D28: =SUM(D16:D27) | E28: =SUM(E16:E27) | F28: =SUM(F16:F27) | G28: =SUM(G16:G27) | H28: =SUM(H16:H27) | I28: =SUM(I16:I27) | J28: =SUM(J16:J27) | K28: =IFERROR(J28/(E28+F28),0)
B30: Notes & hypothèses simplificatrices
B31: • Participation, intéressement et abondements supposés placés ≥ 5 ans en PEE/PERECO → exonération d'IR (sortie en capital).
B32: • Versement PER individuel : économie IR matérialisée immédiatement au TMI estimé. La fiscalité de sortie (rente/capital) est différée et non modélisée ici.
B33: • Dividendes au PFU 30 % : pas de cotisations sociales sur les sociétés à l'IS, hors cas TNS gérant majoritaire (cf. module dédié).
B34: • Avantages en nature : forfait simplifié - adapter à la valeur réelle (véhicule, logement, NTIC) selon arrêté du 25/12/2002.
B35: • Cashback : assimilé à un transfert net non chargé. Le ratio rapporte le net au coût société effectif (souvent nul ou minime côté employeur).
B36: • Le taux marginal d'imposition (TMI) est estimé sur le seul revenu courant - les modules détaillés affinent par foyer.
A38: Outil indicatif à usage professionnel - ne se substitue pas à un conseil personnalisé. Paramètres fiscaux à mettre à jour annuellement (cf. feuille « 13. Sources »).

Sheet 7. Assimilé salarié
A1: 7. Module - Assimilé salarié | H1: ↩ Retour sommaire
A2: Président SAS/SASU, gérant minoritaire de SARL, président SELAS - régime général sécurité sociale.
B4: 1. INPUTS
B5: Salaire brut annuel (€) | C5: 80000 | E5: Saisir le brut annuel souhaité pour le dirigeant.
B6: Avantages en nature inclus dans le brut (€) | C6: 0 | E6: Véhicule, logement, NTIC… ajoutés au brut social et fiscal.
B7: Brut social total (€) | C7: =C5+C6 | E7: Assiette des cotisations.
B9: 2. COTISATIONS SALARIALES
B10: CSG/CRDS - assiette (98,25 % du brut social) | C10: =C7*ASSIETTE_CSG_SAL | E10: CSS art. L.136-2 - abattement 1,75 % pour ≤ 4 PASS.
B11: CSG déductible (6,80 %) | C11: =C10*0.068 | E11: Déductible du revenu imposable.
B12: CSG non déductible + CRDS (2,90 %) | C12: =C10*0.029 | E12: Non déductibles - réintégrées au revenu imposable.
B13: Cotisations salariales hors CSG/CRDS | C13: =C7*TX_SALARIAL | E13: Retraite, prévoyance - taux moyen paramétrable.
B14: Total prélèvements salariaux | C14: =C11+C12+C13
B15: Net après cotisations sociales | C15: =C7-C14 | E15: Avant impôt sur le revenu.
B17: 3. IMPÔT SUR LE REVENU
B18: Revenu salarial imposable (brut − cotis − CSG déd.) | C18: =C15+C12 | E18: Net après cotisations + CSG non déd. + CRDS (réintégrée fiscalement).
B19: Abattement 10 % frais professionnels (plafonné) | C19: =MIN(C18*0.1,14426) | E19: CGI art. 83 - plancher 504 €, plafond 14 426 € (LF 2026 art. 4).
B20: Revenu imposable net (€) | C20: =MAX(0,C18-C19)
B21: Revenu imposable foyer (avec autres revenus) | C21: =C20+AUTRES_REV
B22: Revenu imposable par part | C22: =C21/PARTS
B23: IR par part (barème) | C23: =IF(C22<=IR_PLAFOND_T1,0,IF(C22<=IR_PLAFOND_T2,(C22-IR_PLAFOND_T1)*IR_TAUX_T2,IF(C22<=IR_PLAFOND_T3,(C22-IR_PLAFOND_T2)*IR_TAUX_T3+(IR_PLAFOND_T2-IR_PLAFOND_T1)*IR_TAUX_T2,IF(C22<=IR_PLAFOND_T4,(C22-IR_PLAFOND_T3)*IR_TAUX_T4+(IR_PLAFOND_T3-IR_PLAFOND_T2)*IR_TAUX_T3+(IR_PLAFOND_T2-IR_PLAFOND_T1)*IR_TAUX_T2,(C22-IR_PLAFOND_T4)*IR_TAUX_T5+(IR_PLAFOND_T4-IR_PLAFOND_T3)*IR_TAUX_T4+(IR_PLAFOND_T3-IR_PLAFOND_T2)*IR_TAUX_T3+(IR_PLAFOND_T2-IR_PLAFOND_T1)*IR_TAUX_T2))))
B24: IR du foyer avec QF (avant plafond) | C24: =C23*PARTS
B25: IR sans QF (référence) | C25: =(IF((C21)/(IF(SITUATION="Marié / pacsé",2,1))<=IR_PLAFOND_T1,0,IF((C21)/(IF(SITUATION="Marié / pacsé",2,1))<=IR_PLAFOND_T2,((C21)/(IF(SITUATION="Marié / pacsé",2,1))-IR_PLAFOND_T1)*IR_TAUX_T2,IF((C21)/(IF(SITUATION="Marié / pacsé",2,1))<=IR_PLAFOND_T3,((C21)/(IF(SITUATION="Marié / pacsé",2,1))-IR_PLAFOND_T2)*IR_TAUX_T3+(IR_PLAFOND_T2-IR_PLAFOND_T1)*IR_TAUX_T2,IF((C21)/(IF(SITUATION="Marié / pacsé",2,1))<=IR_PLAFOND_T4,((C21)/(IF(SITUATION="Marié / pacsé",2,1))-IR_PLAFOND_T3)*IR_TAUX_T4+(IR_PLAFOND_T3-IR_PLAFOND_T2)*IR_TAUX_T3+(IR_PLAFOND_T2-IR_PLAFOND_T1)*IR_TAUX_T2,((C21)/(IF(SITUATION="Marié / pacsé",2,1))-IR_PLAFOND_T4)*IR_TAUX_T5+(IR_PLAFOND_T4-IR_PLAFOND_T3)*IR_TAUX_T4+(IR_PLAFOND_T3-IR_PLAFOND_T2)*IR_TAUX_T3+(IR_PLAFOND_T2-IR_PLAFOND_T1)*IR_TAUX_T2)))))*(IF(SITUATION="Marié / pacsé",2,1)) | E25: Calculé en supposant la situation de base (1 part célib / 2 parts marié).
B26: Plafonnement QF (excédent réintégré) | C26: =MAX(0,((C25)-(C24))-(IFERROR(IF(SITUATION_PART="Parent isolé (case T)",IF(((PARTS)-(IF(SITUATION="Marié / pacsé",2,1)))*2>=1,PLAF_QF_PARENT_ISOLE+MAX(0,((PARTS)-(IF(SITUATION="Marié / pacsé",2,1)))*2-1)*PLAF_QF_DEMI_PART,0),IF(SITUATION_PART="Personne seule ayant élevé un enfant ≥ 5 ans (case L)",IF(((PARTS)-(IF(SITUATION="Marié / pacsé",2,1)))*2>=1,PLAF_QF_PERS_SEULE_L+MAX(0,((PARTS)-(IF(SITUATION="Marié / pacsé",2,1)))*2-1)*PLAF_QF_DEMI_PART,0),IF(SITUATION_PART="Veuf avec enfants à charge",IF(((PARTS)-(IF(SITUATION="Marié / pacsé",2,1)))*2>=1,PLAF_QF_VEUF+MAX(0,((PARTS)-(IF(SITUATION="Marié / pacsé",2,1)))*2-1)*PLAF_QF_DEMI_PART,0),IF(SITUATION_PART="Ancien combattant > 74 ans ou invalide",IF(((PARTS)-(IF(SITUATION="Marié / pacsé",2,1)))*2>=1,PLAF_QF_INVALIDE+MAX(0,((PARTS)-(IF(SITUATION="Marié / pacsé",2,1)))*2-1)*PLAF_QF_DEMI_PART,0),PLAF_QF_DEMI_PART*((PARTS)-(IF(SITUATION="Marié / pacsé",2,1)))*2)))),PLAF_QF_DEMI_PART*((PARTS)-(IF(SITUATION="Marié / pacsé",2,1)))*2))) | E26: Cap 1 791 €/demi-part excédentaire (CGI art. 197, I-2°).
B27: IR du foyer après plafonnement QF | C27: =C24+C26
B28: RFR élargi (revenu imposable + dividendes PFU) | C28: =C21+DIVIDENDES_FOYER | E28: Inclut les dividendes au PFU saisis en Profil §3 - assiette commune CEHR + CDHR (CGI art. 223 sexies et 224).
B29: CEHR (contribution exceptionnelle hauts revenus) | C29: =IF(SITUATION="Marié / pacsé",IF(C28<=CEHR_SEUIL_M1,0,IF(C28<=CEHR_SEUIL_M2,(C28-CEHR_SEUIL_M1)*CEHR_TX_1,(CEHR_SEUIL_M2-CEHR_SEUIL_M1)*CEHR_TX_1+(C28-CEHR_SEUIL_M2)*CEHR_TX_2)),IF(C28<=CEHR_SEUIL_C1,0,IF(C28<=CEHR_SEUIL_C2,(C28-CEHR_SEUIL_C1)*CEHR_TX_1,(CEHR_SEUIL_C2-CEHR_SEUIL_C1)*CEHR_TX_1+(C28-CEHR_SEUIL_C2)*CEHR_TX_2))) | E29: CGI art. 223 sexies - assise sur le RFR élargi (incluant les dividendes au PFU).
B30: IR forfaitaire sur dividendes (PFU 12,8 %) | C30: =DIVIDENDES_FOYER*0.128 | E30: Part IR du PFU. Compte dans le numérateur du plancher 20 % de la CDHR.
B31: CDHR (contribution différentielle hauts revenus) | C31: =IF(C28<=IF(SITUATION="Marié / pacsé",CDHR_SEUIL_M,CDHR_SEUIL_C),0,(MAX(0,CDHR_TAUX_PLANCHER*C28-(((C27+C30))+(C29))))*(MIN(1,MAX(0,(C28-(IF(SITUATION="Marié / pacsé",CDHR_SEUIL_M,CDHR_SEUIL_C)))/((IF(SITUATION="Marié / pacsé",CDHR_SEUIL_M_HAUT,CDHR_SEUIL_C_HAUT))-(IF(SITUATION="Marié / pacsé",CDHR_SEUIL_M,CDHR_SEUIL_C))))))) | E31: CGI art. 224 - LF 2025 art. 10, pérennisée LF 2026 art. 2. Plancher 20 % d'impôt effectif sur RFR > 250 k€ (célib) / 500 k€ (couple). Modélisation simplifiée - sans lissage ni retraitement revenus exceptionnels.
B32: Total impôts foyer (IR + CEHR + CDHR) | C32: =C27+C29+C31 | E32: Hors IR PFU sur dividendes - celui-ci reste imputé au foyer hors enveloppe arbitrage.
B33: Taux moyen IR foyer (IR + CEHR + CDHR) / Revenu imposable | C33: =IFERROR(C32/C21,0) | E33: Taux moyen effectif - réutilisé en Arbitrage pour aligner le calcul du net salarial sur le module sélectionné.
B34: Impôts imputables à la rémunération (prorata) | C34: =C32*IFERROR(C20/C21,0) | E34: IR + CEHR + CDHR imputés à la rémunération du dirigeant au prorata.
B36: 4. NET DIRIGEANT APRÈS IMPÔTS
B37: Net après cotisations sociales | C37: =C15
B38: (–) Impôts imputables (IR + CEHR + CDHR) | C38: =C34
B39: Net dirigeant après impôts (€) | C39: =C15-C34 | E39: Pouvoir d'achat net annuel du dirigeant, après IR (avec QF cappé), CEHR et CDHR.
B41: 5. COÛT EMPLOYEUR
B42: Cotisations patronales | C42: =C7*TX_PATRONAL | E42: Taux moyen paramétrable. Hors réduction Fillon (dirigeant non éligible).
B43: Coût employeur total (€) | C43: =C7+C42
B44: Ratio net dirigeant / coût employeur | C44: =IFERROR(C39/C43,0) | E44: Indicateur clé : combien de € de net pour 100 € de coût total.
B46: 6. ALTERNATIVE - DIVIDENDES (PFU 30 %)
B47: Dividendes bruts envisagés (€) | C47: 50000 | E47: Dividendes distribués (avant PFU).
B48: Bénéfice avant IS nécessaire | C48: =C47/(1-TX_IS_NORMAL) | E48: Coût pour la société : il faut consommer ce bénéfice avant IS pour distribuer.
B49: PFU 30 % (12,8 % IR + 17,2 % PS) | C49: =C47*TX_PFU
B50: Net dividendes après PFU (€) | C50: =C47*(1-TX_PFU)
A52: Outil indicatif à usage professionnel - ne se substitue pas à un conseil personnalisé. Paramètres fiscaux à mettre à jour annuellement (cf. feuille « 13. Sources »).

Sheet 8. TNS
A1: 8. Module - Travailleur non-salarié (TNS) | H1: ↩ Retour sommaire
A2: Gérant majoritaire SARL/EURL, EI, EI à l'IS - régime social des indépendants (URSSAF + RCI/CIPAV).
B4: 1. INPUTS
B5: Rémunération nette annuelle souhaitée (€) | C5: 70000 | E5: Revenu net déclaré (après cotisations TNS, avant IR). Base de calcul des cotisations.
B6: Frais réels professionnels (€) | C6: 0 | E6: Frais déductibles BIC ou rémunération nette. 0 par défaut.
B8: 2. COTISATIONS TNS
B9: Taux global TNS (paramétrable) | C9: =TX_TNS | E9: Taux moyen sur le revenu net - variable selon revenu (cf. feuille « 4. Paramètres »).
B10: Cotisations TNS totales | C10: =C5*C9 | E10: URSSAF (maladie, AF, CSG/CRDS) + retraite + invalidité.
B11: Dont CSG déductible (6,80 % du net + cot.) | C11: =(C5+C10)*0.068 | E11: Déductible BIC mais réintégrée fiscalement pour calcul revenu imposable.
B12: Dont CSG/CRDS non déductible (2,90 %) | C12: =(C5+C10)*0.029
B14: 3. IMPÔT SUR LE REVENU
B15: Revenu net BIC/professionnel | C15: =C5-C6
B16: Revenu imposable (réintégration CSG non déd.) | C16: =C15+C12
B17: Revenu imposable foyer | C17: =C16+AUTRES_REV
B18: Revenu par part | C18: =C17/PARTS
B19: IR par part (barème) | C19: =IF(C18<=IR_PLAFOND_T1,0,IF(C18<=IR_PLAFOND_T2,(C18-IR_PLAFOND_T1)*IR_TAUX_T2,IF(C18<=IR_PLAFOND_T3,(C18-IR_PLAFOND_T2)*IR_TAUX_T3+(IR_PLAFOND_T2-IR_PLAFOND_T1)*IR_TAUX_T2,IF(C18<=IR_PLAFOND_T4,(C18-IR_PLAFOND_T3)*IR_TAUX_T4+(IR_PLAFOND_T3-IR_PLAFOND_T2)*IR_TAUX_T3+(IR_PLAFOND_T2-IR_PLAFOND_T1)*IR_TAUX_T2,(C18-IR_PLAFOND_T4)*IR_TAUX_T5+(IR_PLAFOND_T4-IR_PLAFOND_T3)*IR_TAUX_T4+(IR_PLAFOND_T3-IR_PLAFOND_T2)*IR_TAUX_T3+(IR_PLAFOND_T2-IR_PLAFOND_T1)*IR_TAUX_T2))))
B20: IR du foyer avec QF (avant plafond) | C20: =C19*PARTS
B21: IR sans QF (référence) | C21: =(IF((C17)/(IF(SITUATION="Marié / pacsé",2,1))<=IR_PLAFOND_T1,0,IF((C17)/(IF(SITUATION="Marié / pacsé",2,1))<=IR_PLAFOND_T2,((C17)/(IF(SITUATION="Marié / pacsé",2,1))-IR_PLAFOND_T1)*IR_TAUX_T2,IF((C17)/(IF(SITUATION="Marié / pacsé",2,1))<=IR_PLAFOND_T3,((C17)/(IF(SITUATION="Marié / pacsé",2,1))-IR_PLAFOND_T2)*IR_TAUX_T3+(IR_PLAFOND_T2-IR_PLAFOND_T1)*IR_TAUX_T2,IF((C17)/(IF(SITUATION="Marié / pacsé",2,1))<=IR_PLAFOND_T4,((C17)/(IF(SITUATION="Marié / pacsé",2,1))-IR_PLAFOND_T3)*IR_TAUX_T4+(IR_PLAFOND_T3-IR_PLAFOND_T2)*IR_TAUX_T3+(IR_PLAFOND_T2-IR_PLAFOND_T1)*IR_TAUX_T2,((C17)/(IF(SITUATION="Marié / pacsé",2,1))-IR_PLAFOND_T4)*IR_TAUX_T5+(IR_PLAFOND_T4-IR_PLAFOND_T3)*IR_TAUX_T4+(IR_PLAFOND_T3-IR_PLAFOND_T2)*IR_TAUX_T3+(IR_PLAFOND_T2-IR_PLAFOND_T1)*IR_TAUX_T2)))))*(IF(SITUATION="Marié / pacsé",2,1))
B22: Plafonnement QF (excédent réintégré) | C22: =MAX(0,((C21)-(C20))-(IFERROR(IF(SITUATION_PART="Parent isolé (case T)",IF(((PARTS)-(IF(SITUATION="Marié / pacsé",2,1)))*2>=1,PLAF_QF_PARENT_ISOLE+MAX(0,((PARTS)-(IF(SITUATION="Marié / pacsé",2,1)))*2-1)*PLAF_QF_DEMI_PART,0),IF(SITUATION_PART="Personne seule ayant élevé un enfant ≥ 5 ans (case L)",IF(((PARTS)-(IF(SITUATION="Marié / pacsé",2,1)))*2>=1,PLAF_QF_PERS_SEULE_L+MAX(0,((PARTS)-(IF(SITUATION="Marié / pacsé",2,1)))*2-1)*PLAF_QF_DEMI_PART,0),IF(SITUATION_PART="Veuf avec enfants à charge",IF(((PARTS)-(IF(SITUATION="Marié / pacsé",2,1)))*2>=1,PLAF_QF_VEUF+MAX(0,((PARTS)-(IF(SITUATION="Marié / pacsé",2,1)))*2-1)*PLAF_QF_DEMI_PART,0),IF(SITUATION_PART="Ancien combattant > 74 ans ou invalide",IF(((PARTS)-(IF(SITUATION="Marié / pacsé",2,1)))*2>=1,PLAF_QF_INVALIDE+MAX(0,((PARTS)-(IF(SITUATION="Marié / pacsé",2,1)))*2-1)*PLAF_QF_DEMI_PART,0),PLAF_QF_DEMI_PART*((PARTS)-(IF(SITUATION="Marié / pacsé",2,1)))*2)))),PLAF_QF_DEMI_PART*((PARTS)-(IF(SITUATION="Marié / pacsé",2,1)))*2)))
B23: IR du foyer après plafonnement QF | C23: =C20+C22
B24: RFR élargi (+ dividendes PFU) | C24: =C17+DIVIDENDES_FOYER
B25: CEHR | C25: =IF(SITUATION="Marié / pacsé",IF(C24<=CEHR_SEUIL_M1,0,IF(C24<=CEHR_SEUIL_M2,(C24-CEHR_SEUIL_M1)*CEHR_TX_1,(CEHR_SEUIL_M2-CEHR_SEUIL_M1)*CEHR_TX_1+(C24-CEHR_SEUIL_M2)*CEHR_TX_2)),IF(C24<=CEHR_SEUIL_C1,0,IF(C24<=CEHR_SEUIL_C2,(C24-CEHR_SEUIL_C1)*CEHR_TX_1,(CEHR_SEUIL_C2-CEHR_SEUIL_C1)*CEHR_TX_1+(C24-CEHR_SEUIL_C2)*CEHR_TX_2)))
B26: IR forfaitaire sur dividendes (PFU 12,8 %) | C26: =DIVIDENDES_FOYER*0.128
B27: CDHR (plancher 20 % impôt effectif) | C27: =IF(C24<=IF(SITUATION="Marié / pacsé",CDHR_SEUIL_M,CDHR_SEUIL_C),0,(MAX(0,CDHR_TAUX_PLANCHER*C24-(((C23+C26))+(C25))))*(MIN(1,MAX(0,(C24-(IF(SITUATION="Marié / pacsé",CDHR_SEUIL_M,CDHR_SEUIL_C)))/((IF(SITUATION="Marié / pacsé",CDHR_SEUIL_M_HAUT,CDHR_SEUIL_C_HAUT))-(IF(SITUATION="Marié / pacsé",CDHR_SEUIL_M,CDHR_SEUIL_C))))))) | E27: CGI art. 224 - modélisation simplifiée sans lissage. RFR retraité incluant dividendes PFU.
B28: Total impôts foyer (IR + CEHR + CDHR) | C28: =C23+C25+C27
B29: Taux moyen IR foyer (IR + CEHR + CDHR) / Revenu imposable | C29: =IFERROR(C28/C17,0)
B30: Taux moyen IR foyer (IR + CEHR + CDHR) / Revenu imposable | C30: =IFERROR(C29/C17,0)
B31: Taux moyen IR foyer (IR + CEHR + CDHR) / Revenu imposable | C31: =IFERROR(C30/C17,0)
B32: Impôts imputables à la rémunération (prorata) | C32: =C31*IFERROR(C16/C17,0)
B34: 4. NET TNS APRÈS IR
B35: Net dirigeant après IR (€) | C35: =C5-C32 | E35: Pouvoir d'achat net annuel du TNS.
B37: 5. COÛT POUR LA SOCIÉTÉ
B38: Coût total (rém. + cotisations TNS) (€) | C38: =C5+C10
B39: Ratio net dirigeant / coût total | C39: =IFERROR(C35/C38,0)
B41: 6. DIVIDENDES - SPÉCIFICITÉ TNS GÉRANT MAJORITAIRE
B42: Capital social + primes + CC associé (€) | C42: 100000 | E42: Base de calcul du seuil 10 % au-delà duquel les dividendes sont soumis cotisations TNS.
B43: Seuil 10 % (€) | C43: =C42*SEUIL_DIV_TNS | E43: CSS art. L.131-6, 3°.
B44: Dividendes bruts envisagés (€) | C44: 50000
B45: Fraction soumise cotisations TNS | C45: =MAX(0,C44-C43) | E45: Excédent au-delà du seuil - soumis cotisations TNS.
B46: Cotisations TNS sur dividendes | C46: =C45*C9
B47: Fraction soumise PFU 30 % | C47: =C44-C45
B48: PFU sur fraction PFU | C48: =C47*TX_PFU
B49: IR sur fraction cotisations TNS (TMI estimé) | C49: =C45*IF(C18<=IR_PLAFOND_T1,0,IF(C18<=IR_PLAFOND_T2,IR_TAUX_T2,IF(C18<=IR_PLAFOND_T3,IR_TAUX_T3,IF(C18<=IR_PLAFOND_T4,IR_TAUX_T4,IR_TAUX_T5)))) | E49: La fraction soumise cotisations TNS est imposée à l'IR au barème (et non au PFU).
B50: Net dividendes (€) | C50: =C44-C46-C48-C49
A52: Outil indicatif à usage professionnel - ne se substitue pas à un conseil personnalisé. Paramètres fiscaux à mettre à jour annuellement (cf. feuille « 13. Sources »).

Sheet 9. Libéral
A1: 9. Module - Profession libérale | H1: ↩ Retour sommaire
A2: BNC (médecin, avocat, consultant…) ou SEL (SELARL/SELAS) - régimes spécifiques.
B4: 1. SCÉNARIO BNC (exercice individuel)
B5: Recettes annuelles (€) | C5: 150000
B6: Frais professionnels déductibles (€) | C6: 30000 | E6: Loyer cabinet, secrétariat, matériel, charges sociales déjà payées en N-1, etc.
B7: Bénéfice BNC | C7: =C5-C6
B8: Cotisations URSSAF + caisse de retraite | C8: =C7*TX_LIB | E8: CIPAV / CARMF / CARPV / CARCDSF / CARPIMKO / CNBF selon profession. TX_LIB est supposé inclure CSG/CRDS totales.
B9: Dont CSG/CRDS non déductible (2,90 % du bénéfice) | C9: =C7*0.029 | E9: Réintégrée dans l'assiette IR ci-dessous (CSG non déduc. + CRDS).
B10: Bénéfice net après cotisations | C10: =C7-C8
B11: Revenu imposable libéral (réintégration CSG non déd.) | C11: =C10+C9
B12: Revenu imposable foyer | C12: =C11+AUTRES_REV
B13: Revenu par part | C13: =C12/PARTS
B14: IR par part | C14: =IF(C13<=IR_PLAFOND_T1,0,IF(C13<=IR_PLAFOND_T2,(C13-IR_PLAFOND_T1)*IR_TAUX_T2,IF(C13<=IR_PLAFOND_T3,(C13-IR_PLAFOND_T2)*IR_TAUX_T3+(IR_PLAFOND_T2-IR_PLAFOND_T1)*IR_TAUX_T2,IF(C13<=IR_PLAFOND_T4,(C13-IR_PLAFOND_T3)*IR_TAUX_T4+(IR_PLAFOND_T3-IR_PLAFOND_T2)*IR_TAUX_T3+(IR_PLAFOND_T2-IR_PLAFOND_T1)*IR_TAUX_T2,(C13-IR_PLAFOND_T4)*IR_TAUX_T5+(IR_PLAFOND_T4-IR_PLAFOND_T3)*IR_TAUX_T4+(IR_PLAFOND_T3-IR_PLAFOND_T2)*IR_TAUX_T3+(IR_PLAFOND_T2-IR_PLAFOND_T1)*IR_TAUX_T2))))
B15: IR du foyer avec QF (avant plafond) | C15: =C14*PARTS
B16: IR sans QF (référence) | C16: =(IF((C12)/(IF(SITUATION="Marié / pacsé",2,1))<=IR_PLAFOND_T1,0,IF((C12)/(IF(SITUATION="Marié / pacsé",2,1))<=IR_PLAFOND_T2,((C12)/(IF(SITUATION="Marié / pacsé",2,1))-IR_PLAFOND_T1)*IR_TAUX_T2,IF((C12)/(IF(SITUATION="Marié / pacsé",2,1))<=IR_PLAFOND_T3,((C12)/(IF(SITUATION="Marié / pacsé",2,1))-IR_PLAFOND_T2)*IR_TAUX_T3+(IR_PLAFOND_T2-IR_PLAFOND_T1)*IR_TAUX_T2,IF((C12)/(IF(SITUATION="Marié / pacsé",2,1))<=IR_PLAFOND_T4,((C12)/(IF(SITUATION="Marié / pacsé",2,1))-IR_PLAFOND_T3)*IR_TAUX_T4+(IR_PLAFOND_T3-IR_PLAFOND_T2)*IR_TAUX_T3+(IR_PLAFOND_T2-IR_PLAFOND_T1)*IR_TAUX_T2,((C12)/(IF(SITUATION="Marié / pacsé",2,1))-IR_PLAFOND_T4)*IR_TAUX_T5+(IR_PLAFOND_T4-IR_PLAFOND_T3)*IR_TAUX_T4+(IR_PLAFOND_T3-IR_PLAFOND_T2)*IR_TAUX_T3+(IR_PLAFOND_T2-IR_PLAFOND_T1)*IR_TAUX_T2)))))*(IF(SITUATION="Marié / pacsé",2,1))
B17: Plafonnement QF (excédent réintégré) | C17: =MAX(0,((C16)-(C15))-(IFERROR(IF(SITUATION_PART="Parent isolé (case T)",IF(((PARTS)-(IF(SITUATION="Marié / pacsé",2,1)))*2>=1,PLAF_QF_PARENT_ISOLE+MAX(0,((PARTS)-(IF(SITUATION="Marié / pacsé",2,1)))*2-1)*PLAF_QF_DEMI_PART,0),IF(SITUATION_PART="Personne seule ayant élevé un enfant ≥ 5 ans (case L)",IF(((PARTS)-(IF(SITUATION="Marié / pacsé",2,1)))*2>=1,PLAF_QF_PERS_SEULE_L+MAX(0,((PARTS)-(IF(SITUATION="Marié / pacsé",2,1)))*2-1)*PLAF_QF_DEMI_PART,0),IF(SITUATION_PART="Veuf avec enfants à charge",IF(((PARTS)-(IF(SITUATION="Marié / pacsé",2,1)))*2>=1,PLAF_QF_VEUF+MAX(0,((PARTS)-(IF(SITUATION="Marié / pacsé",2,1)))*2-1)*PLAF_QF_DEMI_PART,0),IF(SITUATION_PART="Ancien combattant > 74 ans ou invalide",IF(((PARTS)-(IF(SITUATION="Marié / pacsé",2,1)))*2>=1,PLAF_QF_INVALIDE+MAX(0,((PARTS)-(IF(SITUATION="Marié / pacsé",2,1)))*2-1)*PLAF_QF_DEMI_PART,0),PLAF_QF_DEMI_PART*((PARTS)-(IF(SITUATION="Marié / pacsé",2,1)))*2)))),PLAF_QF_DEMI_PART*((PARTS)-(IF(SITUATION="Marié / pacsé",2,1)))*2)))
B18: IR du foyer après plafonnement QF | C18: =C15+C17
B19: RFR élargi (+ dividendes PFU) | C19: =C12+DIVIDENDES_FOYER
B20: CEHR | C20: =IF(SITUATION="Marié / pacsé",IF(C19<=CEHR_SEUIL_M1,0,IF(C19<=CEHR_SEUIL_M2,(C19-CEHR_SEUIL_M1)*CEHR_TX_1,(CEHR_SEUIL_M2-CEHR_SEUIL_M1)*CEHR_TX_1+(C19-CEHR_SEUIL_M2)*CEHR_TX_2)),IF(C19<=CEHR_SEUIL_C1,0,IF(C19<=CEHR_SEUIL_C2,(C19-CEHR_SEUIL_C1)*CEHR_TX_1,(CEHR_SEUIL_C2-CEHR_SEUIL_C1)*CEHR_TX_1+(C19-CEHR_SEUIL_C2)*CEHR_TX_2)))
B21: IR forfaitaire sur dividendes (PFU 12,8 %) | C21: =DIVIDENDES_FOYER*0.128
B22: CDHR (plancher 20 % impôt effectif) | C22: =IF(C19<=IF(SITUATION="Marié / pacsé",CDHR_SEUIL_M,CDHR_SEUIL_C),0,(MAX(0,CDHR_TAUX_PLANCHER*C19-(((C18+C21))+(C20))))*(MIN(1,MAX(0,(C19-(IF(SITUATION="Marié / pacsé",CDHR_SEUIL_M,CDHR_SEUIL_C)))/((IF(SITUATION="Marié / pacsé",CDHR_SEUIL_M_HAUT,CDHR_SEUIL_C_HAUT))-(IF(SITUATION="Marié / pacsé",CDHR_SEUIL_M,CDHR_SEUIL_C))))))) | E22: CGI art. 224 - modélisation simplifiée sans lissage. RFR retraité incluant dividendes PFU.
B23: Total impôts foyer (IR + CEHR + CDHR) | C23: =C18+C20+C22
B24: Impôts imputables à l'activité libérale (prorata) | C24: =C23*IFERROR(C11/C12,1)
B25: Net libéral après impôts | C25: =C10-C24 | E25: Pouvoir d'achat net annuel = bénéfice net (cash) − impôts imputables.
B27: 2. SCÉNARIO SEL (SELARL / SELAS) - DOUBLE COUCHE
B28: Bénéfice SEL avant rémunération du dirigeant (€) | C28: 200000 | E28: Avant rémunération du dirigeant et avant IS.
B29: Rémunération versée au dirigeant (€) | C29: 80000
B30: Bénéfice imposable IS | C30: =MAX(0,C28-C29)
B31: IS dû | C31: =MIN(C30,IS_PLAF_REDUIT)*TX_IS_REDUIT+MAX(0,C30-IS_PLAF_REDUIT)*TX_IS_NORMAL | E31: Taux réduit 15 % jusqu'à 42 500 € si éligible PME.
B32: Résultat net distribuable | C32: =C30-C31
B33: Dividendes envisagés (€) | C33: =C32 | E33: Modifiable. Par défaut = totalité du résultat net. Pour gérant maj. SELARL : fraction > 10 % capital → cotisations TNS (cf. module TNS).
B35: 3. NOTES - RÉGIMES SPÉCIFIQUES
B36: • Pour SELARL - gérant majoritaire : régime TNS sur la rémunération + dividendes > 10 % du capital social soumis aux cotisations TNS (cf. module 7).
B37: • Pour SELAS - président : régime assimilé salarié sur la rémunération ; dividendes au PFU sans cotisations sociales.
B38: • Les libéraux peuvent opter pour le régime micro-BNC si recettes ≤ 77 700 € (abattement forfaitaire 34 %).
B39: • Les SEL bénéficient de l'IS taux réduit (15 %) si elles remplissent les critères PME (CGI art. 219, I-b).
A41: Outil indicatif à usage professionnel - ne se substitue pas à un conseil personnalisé. Paramètres fiscaux à mettre à jour annuellement (cf. feuille « 13. Sources »).

Sheet 10. Salarié
A1: 10. Module - Salarié (cadre / non-cadre) | H1: ↩ Retour sommaire
A2: Salarié sans mandat social - accent sur l'optimisation par accessoires (TR, mutuelle, PEE/PER…).
B4: 1. INPUTS
B5: Salaire brut annuel (€) | C5: 60000
B7: 2. COTISATIONS & NET
B8: Cotisations salariales hors CSG/CRDS | C8: =C5*TX_SALARIAL
B9: CSG/CRDS (9,7 % × 98,25 %) | C9: =C5*ASSIETTE_CSG_SAL*TX_CSG_CRDS_ACT
B10: CSG déductible (6,80 % × 98,25 %) | C10: =C5*ASSIETTE_CSG_SAL*0.068
B11: Net avant impôt | C11: =C5-C8-C9
B13: 3. IMPÔT SUR LE REVENU
B14: Revenu salarial imposable (brut − cotis − CSG déd.) | C14: =C11+C9-C10 | E14: Net après cotis + CSG/CRDS non déductible (réintégrée dans l'assiette IR).
B15: Abattement 10 % (plafond 14 426 €) | C15: =MIN(C14*0.1,14426)
B16: Revenu imposable net | C16: =MAX(0,C14-C15)
B17: Revenu imposable foyer | C17: =C16+AUTRES_REV
B18: Revenu par part | C18: =C17/PARTS
B19: IR par part | C19: =IF(C18<=IR_PLAFOND_T1,0,IF(C18<=IR_PLAFOND_T2,(C18-IR_PLAFOND_T1)*IR_TAUX_T2,IF(C18<=IR_PLAFOND_T3,(C18-IR_PLAFOND_T2)*IR_TAUX_T3+(IR_PLAFOND_T2-IR_PLAFOND_T1)*IR_TAUX_T2,IF(C18<=IR_PLAFOND_T4,(C18-IR_PLAFOND_T3)*IR_TAUX_T4+(IR_PLAFOND_T3-IR_PLAFOND_T2)*IR_TAUX_T3+(IR_PLAFOND_T2-IR_PLAFOND_T1)*IR_TAUX_T2,(C18-IR_PLAFOND_T4)*IR_TAUX_T5+(IR_PLAFOND_T4-IR_PLAFOND_T3)*IR_TAUX_T4+(IR_PLAFOND_T3-IR_PLAFOND_T2)*IR_TAUX_T3+(IR_PLAFOND_T2-IR_PLAFOND_T1)*IR_TAUX_T2))))
B20: IR du foyer avec QF (avant plafond) | C20: =C19*PARTS
B21: IR sans QF (référence) | C21: =(IF((C17)/(IF(SITUATION="Marié / pacsé",2,1))<=IR_PLAFOND_T1,0,IF((C17)/(IF(SITUATION="Marié / pacsé",2,1))<=IR_PLAFOND_T2,((C17)/(IF(SITUATION="Marié / pacsé",2,1))-IR_PLAFOND_T1)*IR_TAUX_T2,IF((C17)/(IF(SITUATION="Marié / pacsé",2,1))<=IR_PLAFOND_T3,((C17)/(IF(SITUATION="Marié / pacsé",2,1))-IR_PLAFOND_T2)*IR_TAUX_T3+(IR_PLAFOND_T2-IR_PLAFOND_T1)*IR_TAUX_T2,IF((C17)/(IF(SITUATION="Marié / pacsé",2,1))<=IR_PLAFOND_T4,((C17)/(IF(SITUATION="Marié / pacsé",2,1))-IR_PLAFOND_T3)*IR_TAUX_T4+(IR_PLAFOND_T3-IR_PLAFOND_T2)*IR_TAUX_T3+(IR_PLAFOND_T2-IR_PLAFOND_T1)*IR_TAUX_T2,((C17)/(IF(SITUATION="Marié / pacsé",2,1))-IR_PLAFOND_T4)*IR_TAUX_T5+(IR_PLAFOND_T4-IR_PLAFOND_T3)*IR_TAUX_T4+(IR_PLAFOND_T3-IR_PLAFOND_T2)*IR_TAUX_T3+(IR_PLAFOND_T2-IR_PLAFOND_T1)*IR_TAUX_T2)))))*(IF(SITUATION="Marié / pacsé",2,1))
B22: Plafonnement QF (excédent réintégré) | C22: =MAX(0,((C21)-(C20))-(IFERROR(IF(SITUATION_PART="Parent isolé (case T)",IF(((PARTS)-(IF(SITUATION="Marié / pacsé",2,1)))*2>=1,PLAF_QF_PARENT_ISOLE+MAX(0,((PARTS)-(IF(SITUATION="Marié / pacsé",2,1)))*2-1)*PLAF_QF_DEMI_PART,0),IF(SITUATION_PART="Personne seule ayant élevé un enfant ≥ 5 ans (case L)",IF(((PARTS)-(IF(SITUATION="Marié / pacsé",2,1)))*2>=1,PLAF_QF_PERS_SEULE_L+MAX(0,((PARTS)-(IF(SITUATION="Marié / pacsé",2,1)))*2-1)*PLAF_QF_DEMI_PART,0),IF(SITUATION_PART="Veuf avec enfants à charge",IF(((PARTS)-(IF(SITUATION="Marié / pacsé",2,1)))*2>=1,PLAF_QF_VEUF+MAX(0,((PARTS)-(IF(SITUATION="Marié / pacsé",2,1)))*2-1)*PLAF_QF_DEMI_PART,0),IF(SITUATION_PART="Ancien combattant > 74 ans ou invalide",IF(((PARTS)-(IF(SITUATION="Marié / pacsé",2,1)))*2>=1,PLAF_QF_INVALIDE+MAX(0,((PARTS)-(IF(SITUATION="Marié / pacsé",2,1)))*2-1)*PLAF_QF_DEMI_PART,0),PLAF_QF_DEMI_PART*((PARTS)-(IF(SITUATION="Marié / pacsé",2,1)))*2)))),PLAF_QF_DEMI_PART*((PARTS)-(IF(SITUATION="Marié / pacsé",2,1)))*2)))
B23: IR du foyer après plafonnement QF | C23: =C20+C22
B24: RFR élargi (+ dividendes PFU) | C24: =C17+DIVIDENDES_FOYER
B25: CEHR | C25: =IF(SITUATION="Marié / pacsé",IF(C24<=CEHR_SEUIL_M1,0,IF(C24<=CEHR_SEUIL_M2,(C24-CEHR_SEUIL_M1)*CEHR_TX_1,(CEHR_SEUIL_M2-CEHR_SEUIL_M1)*CEHR_TX_1+(C24-CEHR_SEUIL_M2)*CEHR_TX_2)),IF(C24<=CEHR_SEUIL_C1,0,IF(C24<=CEHR_SEUIL_C2,(C24-CEHR_SEUIL_C1)*CEHR_TX_1,(CEHR_SEUIL_C2-CEHR_SEUIL_C1)*CEHR_TX_1+(C24-CEHR_SEUIL_C2)*CEHR_TX_2)))
B26: IR forfaitaire sur dividendes (PFU 12,8 %) | C26: =DIVIDENDES_FOYER*0.128
B27: CDHR (plancher 20 % impôt effectif) | C27: =IF(C24<=IF(SITUATION="Marié / pacsé",CDHR_SEUIL_M,CDHR_SEUIL_C),0,(MAX(0,CDHR_TAUX_PLANCHER*C24-(((C23+C26))+(C25))))*(MIN(1,MAX(0,(C24-(IF(SITUATION="Marié / pacsé",CDHR_SEUIL_M,CDHR_SEUIL_C)))/((IF(SITUATION="Marié / pacsé",CDHR_SEUIL_M_HAUT,CDHR_SEUIL_C_HAUT))-(IF(SITUATION="Marié / pacsé",CDHR_SEUIL_M,CDHR_SEUIL_C))))))) | E27: CGI art. 224 - modélisation simplifiée sans lissage. RFR retraité incluant dividendes PFU.
B28: Total impôts foyer (IR + CEHR + CDHR) | C28: =C23+C25+C27
B29: Impôts imputables à la rémunération (prorata) | C29: =C28*IFERROR(C16/C17,1)
B30: Net après impôts (IR + CEHR + CDHR) | C30: =C11-C29
B32: 4. PISTES D'OPTIMISATION (SALARIÉ)
B33: • PEE/PER collectif : abondement employeur exo charges sociales (hors CSG/CRDS) jusqu'à 8 % PASS / 16 % PASS.
B34: • PER individuel : versement déductible jusqu'à 10 % des revenus pro de l'année N-1 (plafond mutualisable conjoint).
B35: • Tickets restaurant : part employeur exonérée jusqu'à 7,26 €/titre (60 % max).
B36: • CESU préfinancé : exo jusqu'à 2 540 €/an pour services à la personne.
B37: • Mutuelle / prévoyance employeur : cotisation patronale exo IR (hors part > seuil).
B38: • Forfait mobilité durable : exo jusqu'à 700 €/an (vélo, covoiturage, transports en commun cumulables avec abonnement).
A40: Outil indicatif à usage professionnel - ne se substitue pas à un conseil personnalisé. Paramètres fiscaux à mettre à jour annuellement (cf. feuille « 13. Sources »).

Sheet 11. Arbitrage
A1: 10. Arbitrage global de la rémunération | I1: ↩ Retour sommaire
A2: 4 stratégies comparées à enveloppe constante (cf. cellule « Enveloppe » de la feuille Profil).
B4: MATRICE DES STRATÉGIES
B5: Élément | C5: Stratégie A | D5: Stratégie B | E5: Stratégie C | F5: Stratégie D | H5: Commentaires
C6: 100 % rémunération directe | D6: Salaire optimisé + dividendes | E6: + Épargne salariale & PER | F6: + Périphériques & cashback
B7: Allocation salaire / rémunération (%) | C7: 1 | D7: 0.6 | E7: 0.5 | F7: 0.45 | H7: % de l'enveloppe alloué à la rémunération directe (salaire ou TNS).
B8: Allocation dividendes (%) | C8: 0 | D8: 0.4 | E8: 0.3 | F8: 0.25 | H8: % en dividendes (PFU 30 %).
B9: Allocation épargne salariale & PER (%) | C9: 0 | D9: 0 | E9: 0.2 | F9: 0.2 | H9: Participation, intéressement, abondement, PER - exo IR si placement long.
B10: Allocation périphériques & cashback (%) | C10: 0 | D10: 0 | E10: 0 | F10: 0.1 | H10: TR, CESU, mutuelle, AN, cashback - exonérés ou tolérés.
B11: Total alloué (contrôle) | C11: =C7+C8+C9+C10 | D11: =D7+D8+D9+D10 | E11: =E7+E8+E9+E10 | F11: =F7+F8+F9+F10 | H11: Doit toujours être égal à 100 %. Ajuster les allocations sinon.
B13: MONTANTS PAR POSTE (€)
B14: Coût employeur alloué au salaire (€) | C14: =ENVELOPPE*C7 | D14: =ENVELOPPE*D7 | E14: =ENVELOPPE*E7 | F14: =ENVELOPPE*F7 | H14: Coût total société (charges incluses).
B15: Bénéfice avant IS alloué aux dividendes (€) | C15: =ENVELOPPE*C8 | D15: =ENVELOPPE*D8 | E15: =ENVELOPPE*E8 | F15: =ENVELOPPE*F8 | H15: Bénéfice avant IS consommé pour générer les dividendes.
B16: Coût alloué à l'épargne salariale & PER (€) | C16: =ENVELOPPE*C9 | D16: =ENVELOPPE*D9 | E16: =ENVELOPPE*E9 | F16: =ENVELOPPE*F9
B17: Coût alloué aux périphériques & cashback (€) | C17: =ENVELOPPE*C10 | D17: =ENVELOPPE*D10 | E17: =ENVELOPPE*E10 | F17: =ENVELOPPE*F10
B19: NET DIRIGEANT APRÈS FISCALITÉ (€)
B20: Taux moyen IR appliqué (aligné module sélectionné) | C20: =MAX(IFERROR(IF(REGIME_SOCIAL="TNS",TX_IR_MOY_TNS,IF(REGIME_SOCIAL="TNS (libéral)",TX_IR_MOY_LIB,IF(REGIME_SOCIAL="Salarié",TX_IR_MOY_SAL,TX_IR_MOY_ASS))),0.3),0.05) | D20: =MAX(IFERROR(IF(REGIME_SOCIAL="TNS",TX_IR_MOY_TNS,IF(REGIME_SOCIAL="TNS (libéral)",TX_IR_MOY_LIB,IF(REGIME_SOCIAL="Salarié",TX_IR_MOY_SAL,TX_IR_MOY_ASS))),0.3),0.05) | E20: =MAX(IFERROR(IF(REGIME_SOCIAL="TNS",TX_IR_MOY_TNS,IF(REGIME_SOCIAL="TNS (libéral)",TX_IR_MOY_LIB,IF(REGIME_SOCIAL="Salarié",TX_IR_MOY_SAL,TX_IR_MOY_ASS))),0.3),0.05) | F20: =MAX(IFERROR(IF(REGIME_SOCIAL="TNS",TX_IR_MOY_TNS,IF(REGIME_SOCIAL="TNS (libéral)",TX_IR_MOY_LIB,IF(REGIME_SOCIAL="Salarié",TX_IR_MOY_SAL,TX_IR_MOY_ASS))),0.3),0.05) | H20: Taux moyen IR effectif extrait du module sélectionné (IR + CEHR + CDHR) / Revenu imposable. Plus fin que la TMI marginale forfaitaire - assume une TMI stable across stratégies, biais sur hauts revenus.
B21: Net salaire après IR (€) | C21: =IF(REGIME_SOCIAL="TNS",C14/(1+TX_TNS)*(1-C20),IF(REGIME_SOCIAL="TNS (libéral)",C14/(1+TX_LIB)*(1-C20),C14/(1+TX_PATRONAL)*(1-TX_SALARIAL-ASSIETTE_CSG_SAL*0.097)*(1-C20))) | D21: =IF(REGIME_SOCIAL="TNS",D14/(1+TX_TNS)*(1-D20),IF(REGIME_SOCIAL="TNS (libéral)",D14/(1+TX_LIB)*(1-D20),D14/(1+TX_PATRONAL)*(1-TX_SALARIAL-ASSIETTE_CSG_SAL*0.097)*(1-D20))) | E21: =IF(REGIME_SOCIAL="TNS",E14/(1+TX_TNS)*(1-E20),IF(REGIME_SOCIAL="TNS (libéral)",E14/(1+TX_LIB)*(1-E20),E14/(1+TX_PATRONAL)*(1-TX_SALARIAL-ASSIETTE_CSG_SAL*0.097)*(1-E20))) | F21: =IF(REGIME_SOCIAL="TNS",F14/(1+TX_TNS)*(1-F20),IF(REGIME_SOCIAL="TNS (libéral)",F14/(1+TX_LIB)*(1-F20),F14/(1+TX_PATRONAL)*(1-TX_SALARIAL-ASSIETTE_CSG_SAL*0.097)*(1-F20))) | H21: Net dirigeant après cotisations sociales et IR sur la part rémunération directe.
B22: Net dividendes après IS, cotis. (TNS) et PFU/IR (€) | C22: =IF(OR(REGIME_SOCIAL="TNS",REGIME_SOCIAL="TNS (libéral)"),(MIN((C15-(MIN(C15,IS_PLAF_REDUIT)*TX_IS_REDUIT+MAX(0,C15-IS_PLAF_REDUIT)*TX_IS_NORMAL)),(0.1*CAPITAL_TNS))*(1-TX_PFU)+MAX(0,(C15-(MIN(C15,IS_PLAF_REDUIT)*TX_IS_REDUIT+MAX(0,C15-IS_PLAF_REDUIT)*TX_IS_NORMAL))-(0.1*CAPITAL_TNS))/(1+TX_TNS)*(1-MAX(IFERROR(TX_IR_MOY_TNS,0.3),0.2))),((C15-(MIN(C15,IS_PLAF_REDUIT)*TX_IS_REDUIT+MAX(0,C15-IS_PLAF_REDUIT)*TX_IS_NORMAL))*(1-TX_PFU))) | D22: =IF(OR(REGIME_SOCIAL="TNS",REGIME_SOCIAL="TNS (libéral)"),(MIN((D15-(MIN(D15,IS_PLAF_REDUIT)*TX_IS_REDUIT+MAX(0,D15-IS_PLAF_REDUIT)*TX_IS_NORMAL)),(0.1*CAPITAL_TNS))*(1-TX_PFU)+MAX(0,(D15-(MIN(D15,IS_PLAF_REDUIT)*TX_IS_REDUIT+MAX(0,D15-IS_PLAF_REDUIT)*TX_IS_NORMAL))-(0.1*CAPITAL_TNS))/(1+TX_TNS)*(1-MAX(IFERROR(TX_IR_MOY_TNS,0.3),0.2))),((D15-(MIN(D15,IS_PLAF_REDUIT)*TX_IS_REDUIT+MAX(0,D15-IS_PLAF_REDUIT)*TX_IS_NORMAL))*(1-TX_PFU))) | E22: =IF(OR(REGIME_SOCIAL="TNS",REGIME_SOCIAL="TNS (libéral)"),(MIN((E15-(MIN(E15,IS_PLAF_REDUIT)*TX_IS_REDUIT+MAX(0,E15-IS_PLAF_REDUIT)*TX_IS_NORMAL)),(0.1*CAPITAL_TNS))*(1-TX_PFU)+MAX(0,(E15-(MIN(E15,IS_PLAF_REDUIT)*TX_IS_REDUIT+MAX(0,E15-IS_PLAF_REDUIT)*TX_IS_NORMAL))-(0.1*CAPITAL_TNS))/(1+TX_TNS)*(1-MAX(IFERROR(TX_IR_MOY_TNS,0.3),0.2))),((E15-(MIN(E15,IS_PLAF_REDUIT)*TX_IS_REDUIT+MAX(0,E15-IS_PLAF_REDUIT)*TX_IS_NORMAL))*(1-TX_PFU))) | F22: =IF(OR(REGIME_SOCIAL="TNS",REGIME_SOCIAL="TNS (libéral)"),(MIN((F15-(MIN(F15,IS_PLAF_REDUIT)*TX_IS_REDUIT+MAX(0,F15-IS_PLAF_REDUIT)*TX_IS_NORMAL)),(0.1*CAPITAL_TNS))*(1-TX_PFU)+MAX(0,(F15-(MIN(F15,IS_PLAF_REDUIT)*TX_IS_REDUIT+MAX(0,F15-IS_PLAF_REDUIT)*TX_IS_NORMAL))-(0.1*CAPITAL_TNS))/(1+TX_TNS)*(1-MAX(IFERROR(TX_IR_MOY_TNS,0.3),0.2))),((F15-(MIN(F15,IS_PLAF_REDUIT)*TX_IS_REDUIT+MAX(0,F15-IS_PLAF_REDUIT)*TX_IS_NORMAL))*(1-TX_PFU))) | H22: Pour TNS et TNS (libéral, dont SELARL/SCP) : fraction divs > 10 % capital social requalifiée en rémunération (cotis ~45 % + IR au barème). Sous le seuil : PFU 31,4 %. Pour assimilé salarié / SELAS / salarié : 100 % au PFU.
B23: Net épargne salariale & PER (€) | C23: =C16/(1+IFERROR((IF(TOG_PARTICIPATION="Oui",M_PARTICIPATION,0)*(IF(OR(EFFECTIF="Sans salarié",EFFECTIF="1-10 salariés",EFFECTIF="11-49 salariés"),FS_PART_LT50,IF(EFFECTIF="50-249 salariés",FS_PART_50_249,FS_PART_GE250)))+IF(TOG_INTERESSEMENT="Oui",M_INTERESSEMENT,0)*(IF(OR(EFFECTIF="Sans salarié",EFFECTIF="1-10 salariés",EFFECTIF="11-49 salariés",EFFECTIF="50-249 salariés"),FS_INT_LT250,FS_INT_GE250))+IF(TOG_ABO_PEE="Oui",M_ABO_PEE,0)*(IF(OR(EFFECTIF="Sans salarié",EFFECTIF="1-10 salariés",EFFECTIF="11-49 salariés"),FS_ABO_LT50,FS_ABO_GE50))+IF(TOG_ABO_PER="Oui",M_ABO_PER,0)*(IF(OR(EFFECTIF="Sans salarié",EFFECTIF="1-10 salariés",EFFECTIF="11-49 salariés"),FS_ABO_LT50,FS_ABO_GE50)))/(IF(TOG_PARTICIPATION="Oui",M_PARTICIPATION,0)+IF(TOG_INTERESSEMENT="Oui",M_INTERESSEMENT,0)+IF(TOG_ABO_PEE="Oui",M_ABO_PEE,0)+IF(TOG_ABO_PER="Oui",M_ABO_PER,0)),0))*(1-TX_CSG_CRDS_ACT) | D23: =D16/(1+IFERROR((IF(TOG_PARTICIPATION="Oui",M_PARTICIPATION,0)*(IF(OR(EFFECTIF="Sans salarié",EFFECTIF="1-10 salariés",EFFECTIF="11-49 salariés"),FS_PART_LT50,IF(EFFECTIF="50-249 salariés",FS_PART_50_249,FS_PART_GE250)))+IF(TOG_INTERESSEMENT="Oui",M_INTERESSEMENT,0)*(IF(OR(EFFECTIF="Sans salarié",EFFECTIF="1-10 salariés",EFFECTIF="11-49 salariés",EFFECTIF="50-249 salariés"),FS_INT_LT250,FS_INT_GE250))+IF(TOG_ABO_PEE="Oui",M_ABO_PEE,0)*(IF(OR(EFFECTIF="Sans salarié",EFFECTIF="1-10 salariés",EFFECTIF="11-49 salariés"),FS_ABO_LT50,FS_ABO_GE50))+IF(TOG_ABO_PER="Oui",M_ABO_PER,0)*(IF(OR(EFFECTIF="Sans salarié",EFFECTIF="1-10 salariés",EFFECTIF="11-49 salariés"),FS_ABO_LT50,FS_ABO_GE50)))/(IF(TOG_PARTICIPATION="Oui",M_PARTICIPATION,0)+IF(TOG_INTERESSEMENT="Oui",M_INTERESSEMENT,0)+IF(TOG_ABO_PEE="Oui",M_ABO_PEE,0)+IF(TOG_ABO_PER="Oui",M_ABO_PER,0)),0))*(1-TX_CSG_CRDS_ACT) | E23: =E16/(1+IFERROR((IF(TOG_PARTICIPATION="Oui",M_PARTICIPATION,0)*(IF(OR(EFFECTIF="Sans salarié",EFFECTIF="1-10 salariés",EFFECTIF="11-49 salariés"),FS_PART_LT50,IF(EFFECTIF="50-249 salariés",FS_PART_50_249,FS_PART_GE250)))+IF(TOG_INTERESSEMENT="Oui",M_INTERESSEMENT,0)*(IF(OR(EFFECTIF="Sans salarié",EFFECTIF="1-10 salariés",EFFECTIF="11-49 salariés",EFFECTIF="50-249 salariés"),FS_INT_LT250,FS_INT_GE250))+IF(TOG_ABO_PEE="Oui",M_ABO_PEE,0)*(IF(OR(EFFECTIF="Sans salarié",EFFECTIF="1-10 salariés",EFFECTIF="11-49 salariés"),FS_ABO_LT50,FS_ABO_GE50))+IF(TOG_ABO_PER="Oui",M_ABO_PER,0)*(IF(OR(EFFECTIF="Sans salarié",EFFECTIF="1-10 salariés",EFFECTIF="11-49 salariés"),FS_ABO_LT50,FS_ABO_GE50)))/(IF(TOG_PARTICIPATION="Oui",M_PARTICIPATION,0)+IF(TOG_INTERESSEMENT="Oui",M_INTERESSEMENT,0)+IF(TOG_ABO_PEE="Oui",M_ABO_PEE,0)+IF(TOG_ABO_PER="Oui",M_ABO_PER,0)),0))*(1-TX_CSG_CRDS_ACT) | F23: =F16/(1+IFERROR((IF(TOG_PARTICIPATION="Oui",M_PARTICIPATION,0)*(IF(OR(EFFECTIF="Sans salarié",EFFECTIF="1-10 salariés",EFFECTIF="11-49 salariés"),FS_PART_LT50,IF(EFFECTIF="50-249 salariés",FS_PART_50_249,FS_PART_GE250)))+IF(TOG_INTERESSEMENT="Oui",M_INTERESSEMENT,0)*(IF(OR(EFFECTIF="Sans salarié",EFFECTIF="1-10 salariés",EFFECTIF="11-49 salariés",EFFECTIF="50-249 salariés"),FS_INT_LT250,FS_INT_GE250))+IF(TOG_ABO_PEE="Oui",M_ABO_PEE,0)*(IF(OR(EFFECTIF="Sans salarié",EFFECTIF="1-10 salariés",EFFECTIF="11-49 salariés"),FS_ABO_LT50,FS_ABO_GE50))+IF(TOG_ABO_PER="Oui",M_ABO_PER,0)*(IF(OR(EFFECTIF="Sans salarié",EFFECTIF="1-10 salariés",EFFECTIF="11-49 salariés"),FS_ABO_LT50,FS_ABO_GE50)))/(IF(TOG_PARTICIPATION="Oui",M_PARTICIPATION,0)+IF(TOG_INTERESSEMENT="Oui",M_INTERESSEMENT,0)+IF(TOG_ABO_PEE="Oui",M_ABO_PEE,0)+IF(TOG_ABO_PER="Oui",M_ABO_PER,0)),0))*(1-TX_CSG_CRDS_ACT) | H23: Forfait social granulaire pondéré : 0 % participation/abondement < 50 sal, 20 % au-delà ; 0 % intéressement < 250 sal, 20 % au-delà (loi PACTE 2019).
B24: Net périphériques & cashback (€) | C24: =C17*0.95 | D24: =D17*0.95 | E24: =E17*0.95 | F24: =F17*0.95 | H24: Hypothèse efficacité 95 % - TR/CESU/mutuelle/cashback combinés.
B26: TOTAL NET DIRIGEANT APRÈS FISCALITÉ (€) | C26: =C21+C22+C23+C24 | D26: =D21+D22+D23+D24 | E26: =E21+E22+E23+E24 | F26: =F21+F22+F23+F24 | H26: Pouvoir d'achat net annuel total du dirigeant.
B27: Coût total société (€) | C27: =C14+C15+C16+C17 | D27: =D14+D15+D16+D17 | E27: =E14+E15+E16+E17 | F27: =F14+F15+F16+F17 | H27: Doit être égal à l'enveloppe (cf. ligne contrôle plus haut).
B28: Efficacité fiscale (net / coût) | C28: =IFERROR(C26/C27,0) | D28: =IFERROR(D26/D27,0) | E28: =IFERROR(E26/E27,0) | F28: =IFERROR(F26/F27,0) | H28: % de l'enveloppe qui arrive en net après fiscalité.
B29: Gain vs Stratégie A (€) | C29: - | D29: =D26-C26 | E29: =E26-C26 | F29: =F26-C26 | H29: Différentiel de pouvoir d'achat vs scénario tout-salaire.
B31: Lecture & limites du modèle
B32: • Cet arbitrage est un cadrage stratégique. Les modules détaillés (feuilles 6 à 9) affinent les calculs par population.
B33: • Vérifier que l'enveloppe est cohérente avec le bénéfice IS de la société (cf. feuille « 5. Profil ») pour que les dividendes soient effectivement distribuables.
B34: • Pour TNS gérant majoritaire : la fraction de dividendes > 10 % du capital est soumise à cotisations TNS - non modélisé ici (cf. module 7).
B35: • Les périphériques (TR, CESU, mutuelle…) sont plafonnés individuellement - ne pas dépasser les seuils d'exonération (cf. feuille « 4. Paramètres »).
B36: • Le PER individuel offre un effet immédiat (économie IR au TMI) - son intérêt dépend du différentiel de TMI entre activité et retraite.
A38: Outil indicatif à usage professionnel - ne se substitue pas à un conseil personnalisé. Paramètres fiscaux à mettre à jour annuellement (cf. feuille « 13. Sources »).

Sheet 12. Synthèse
A1: 11. Synthèse dirigeant | I1: ↩ Retour sommaire
A2: Livrable client - résumé exécutif des arbitrages.
B4: DOSSIER
B5: Client | C5: =CLIENT_NAME
B6: Forme juridique | C6: =FORME_JURIDIQUE
B7: Régime social | C7: =REGIME_SOCIAL
B8: Effectif | C8: =EFFECTIF
B9: Foyer fiscal - parts | C9: =PARTS
B10: Enveloppe à arbitrer (€) | C10: =ENVELOPPE
B11: Bénéfice IS de la société | C11: =BENEFICE_IS
B13: COMPARAISON DES STRATÉGIES (cf. feuille « 11. Arbitrage »)
B14: Stratégie | C14: Net dirigeant | E14: Profil et points-clés
B15: A - 100 % rémunération directe | C15: =INDEX('11. Arbitrage'!C:C,MATCH("TOTAL NET DIRIGEANT APRÈS FISCALITÉ (€)",'11. Arbitrage'!B:B,0)) | E15: Référence. Charges sociales et IR maximaux. Pour dirigeants ne pouvant pas distribuer (déficit, CC associé débiteur, etc.).
B16: B - Salaire optimisé + dividendes | C16: =INDEX('11. Arbitrage'!D:D,MATCH("TOTAL NET DIRIGEANT APRÈS FISCALITÉ (€)",'11. Arbitrage'!B:B,0)) | E16: Mix classique. Le salaire sécurise les droits sociaux (retraite, maladie) ; les dividendes complètent à fiscalité allégée (PFU).
B17: C - + Épargne salariale & PER | C17: =INDEX('11. Arbitrage'!E:E,MATCH("TOTAL NET DIRIGEANT APRÈS FISCALITÉ (€)",'11. Arbitrage'!B:B,0)) | E17: Optimum fiscal pour la plupart des PME < 250 sal. (forfait social 0 % loi PACTE). Capitaux différés mais exonérés en sortie.
B18: =IF(TOG_CASHBACK="Oui","D - Stratégie complète + 💸 cashback","D - + Périphériques (sans cashback)") | C18: =INDEX('11. Arbitrage'!F:F,MATCH("TOTAL NET DIRIGEANT APRÈS FISCALITÉ (€)",'11. Arbitrage'!B:B,0)) | E18: =IF(TOG_CASHBACK="Oui","Stratégie complète. Mobilise les enveloppes périphériques exonérées (TR/CESU/mutuelle) ainsi que le 💸 cashback (cf. note technique en feuille « 13. Sources »).","Stratégie complète. Mobilise les enveloppes périphériques exonérées (TR/CESU/mutuelle/AN) - utile pour PME et cadres dirigeants.")
B20: STRATÉGIE RECOMMANDÉE
B21: Net dirigeant le plus élevé | C21: =MAX(INDEX('11. Arbitrage'!C:C,MATCH("TOTAL NET DIRIGEANT APRÈS FISCALITÉ (€)",'11. Arbitrage'!B:B,0)),INDEX('11. Arbitrage'!D:D,MATCH("TOTAL NET DIRIGEANT APRÈS FISCALITÉ (€)",'11. Arbitrage'!B:B,0)),INDEX('11. Arbitrage'!E:E,MATCH("TOTAL NET DIRIGEANT APRÈS FISCALITÉ (€)",'11. Arbitrage'!B:B,0)),INDEX('11. Arbitrage'!F:F,MATCH("TOTAL NET DIRIGEANT APRÈS FISCALITÉ (€)",'11. Arbitrage'!B:B,0))) | E21: Maximum des 4 stratégies modélisées.
B22: Gain vs Stratégie A (référence) | C22: =C21-INDEX('11. Arbitrage'!C:C,MATCH("TOTAL NET DIRIGEANT APRÈS FISCALITÉ (€)",'11. Arbitrage'!B:B,0)) | E22: Différentiel de pouvoir d'achat annuel.
B23: Gain sur 5 ans | C23: =C22*5 | E23: Projection linéaire - paramètres 2025 figés.
B25: POINTS D'ATTENTION
B26: • Validation juridique - accord de participation, règlement PEE/PER : à formaliser avec un cabinet d'avocats si non encore en place.
B27: • Cohérence avec la trésorerie société - vérifier la capacité distributive (réserves disponibles, ratios bancaires, covenants).
B28: • Droits sociaux du dirigeant - un salaire trop faible affaiblit les droits retraite, indemnités journalières, chômage GSC. À calibrer.
B29: • Régularité fiscale - déclaration 2042 (PER, dividendes), 2031 (BIC), 2035 (BNC), DSN, formulaire 2777-D pour PFU.
B30: • Mise à jour annuelle - barème IR, PASS, plafonds dispositifs : actualiser la feuille « 4. Paramètres » chaque année.
B31: • Évolution réglementaire - surveiller les évolutions du forfait social, du PFU, des seuils PME, et de la CSG.
B34: ✅ CHECK-LIST DE CONFORMITÉ (stratégie sélectionnée)
B35: Point de contrôle | C35: Statut | D35: Action requise / commentaire
B36: Effectif compatible avec dispositif participation | C36: =IF(AND('2. Dashboard'!$F$6>="B",TOG_PARTICIPATION="Oui"),IF(OR(EFFECTIF="50-249 salariés",EFFECTIF="≥ 250 salariés"),"✅","⚠"),"-") | D36: =IF(AND('2. Dashboard'!$F$6>="B",TOG_PARTICIPATION="Oui",AND(EFFECTIF<>"50-249 salariés",EFFECTIF<>"≥ 250 salariés")),"Participation obligatoire à 50 salariés - pour < 50, dispositif facultatif via accord. Vérifier la mise en place.","")
B37: Plafond participation individuel (75 % PASS = 36 045 €) | C37: =IF(AND('2. Dashboard'!$F$6>="B",TOG_PARTICIPATION="Oui"),IF(M_PARTICIPATION<=36045,"✅","🔴"),"-") | D37: =IF(AND('2. Dashboard'!$F$6>="B",TOG_PARTICIPATION="Oui",M_PARTICIPATION>36045),"Montant participation dépasse 75 % PASS - réduire à 36 045 € max.","")
B38: Plafond intéressement individuel (75 % PASS) | C38: =IF(AND('2. Dashboard'!$F$6>="B",TOG_INTERESSEMENT="Oui"),IF(M_INTERESSEMENT<=36045,"✅","🔴"),"-") | D38: =IF(AND('2. Dashboard'!$F$6>="B",TOG_INTERESSEMENT="Oui",M_INTERESSEMENT>36045),"Montant intéressement dépasse 75 % PASS - réduire à 36 045 € max.","")
B39: Plafond abondement PEE (8 % PASS = 3 845 €) | C39: =IF(AND('2. Dashboard'!$F$6>="B",TOG_ABO_PEE="Oui"),IF(M_ABO_PEE<=3845,"✅","🔴"),"-") | D39: =IF(AND('2. Dashboard'!$F$6>="B",TOG_ABO_PEE="Oui",M_ABO_PEE>3845),"Abondement PEE dépasse 8 % PASS - réduire à 3 845 € max.","")
B40: Plafond abondement PER collectif (16 % PASS = 7 690 €) | C40: =IF(AND('2. Dashboard'!$F$6>="B",TOG_ABO_PER="Oui"),IF(M_ABO_PER<=7690,"✅","🔴"),"-") | D40: =IF(AND('2. Dashboard'!$F$6>="B",TOG_ABO_PER="Oui",M_ABO_PER>7690),"Abondement PER dépasse 16 % PASS - réduire à 7 690 € max.","")
B41: Accord d'intéressement formalisé (≥ 3 ans) | C41: =IF(AND('2. Dashboard'!$F$6>="B",TOG_INTERESSEMENT="Oui"),"⚠","-") | D41: =IF(AND('2. Dashboard'!$F$6>="B",TOG_INTERESSEMENT="Oui"),"Vérifier l'existence d'un accord triennal déposé à la DDETSPP. À défaut : à mettre en place avant exonération.","")
B42: Règlement PEE déposé et information salariés | C42: =IF(AND('2. Dashboard'!$F$6>="B",OR(TOG_ABO_PEE="Oui",TOG_PARTICIPATION="Oui")),"⚠","-") | D42: =IF(AND('2. Dashboard'!$F$6>="B",OR(TOG_ABO_PEE="Oui",TOG_PARTICIPATION="Oui")),"Vérifier dépôt règlement PEE et livret épargne salariale remis aux salariés.","")
B43: Ratio dividendes / capital social (TNS gérant maj.) | C43: =IF(AND(REGIME_SOCIAL="TNS",DIVIDENDES_FOYER>0),"⚠","-") | D43: =IF(AND(REGIME_SOCIAL="TNS",DIVIDENDES_FOYER>0),"Dividendes > 10 % du capital social + primes d'émission + comptes courants = soumis à cotisations TNS (~45 %). Vérifier sur dossier client.","")
B44: Mode de déploiement cashback documenté | C44: =IF(TOG_CASHBACK="Oui","⚠","-") | D44: =IF(TOG_CASHBACK="Oui","Cf. Profil §7 : mode Conforme suppose souscription nominative hors lien employeur et doc formalisée. Mode Standard = risque URSSAF.","")
B45: RFR foyer > 250 k€ (célib) ou 500 k€ (marié) → CDHR active | C45: =IF(((SITUATION="Célibataire / divorcé / veuf")*((DIVIDENDES_FOYER+AUTRES_REV)>250000))+((SITUATION="Marié / pacsé")*((DIVIDENDES_FOYER+AUTRES_REV)>500000))>0,"⚠","✅") | D45: =IF(((SITUATION="Célibataire / divorcé / veuf")*((DIVIDENDES_FOYER+AUTRES_REV)>250000))+((SITUATION="Marié / pacsé")*((DIVIDENDES_FOYER+AUTRES_REV)>500000))>0,"Foyer potentiellement assujetti à la CDHR (plancher 20 % IR effectif). Vérifier le calcul fin sur impots.gouv.fr.","")
B48: 💰 COÛTS DE MISE EN ŒUVRE ESTIMÉS (1ère année)
B49: Poste | C49: Coût | D49: Commentaire
B50: Mission cabinet - cadrage stratégique | C50: =1200 | D50: Forfait indicatif. Inclut audit du dossier et restitution client.
B51: Mise en place accord d'intéressement | C51: =IF(AND('2. Dashboard'!$F$6>="B",TOG_INTERESSEMENT="Oui"),800,0) | D51: Rédaction de l'accord + dépôt DDETSPP + information salariés.
B52: Mise en place règlement PEE / PER collectif | C52: =IF(AND('2. Dashboard'!$F$6>="B",OR(TOG_ABO_PEE="Oui",TOG_ABO_PER="Oui")),1500,0) | D52: Conventionnement teneur de compte + rédaction règlement + information salariés.
B53: Frais teneur de compte PEE/PER (annuels) | C53: =IF(AND('2. Dashboard'!$F$6>="B",OR(TOG_ABO_PEE="Oui",TOG_ABO_PER="Oui")),IF(OR(EFFECTIF="Sans salarié",EFFECTIF="1-10 salariés",EFFECTIF="11-49 salariés"),500,1200),0) | D53: Frais récurrents (Amundi, BNP, Eres…). Variable selon prestataire et effectif.
B54: Audit conformité périphériques (TR, CESU, AN) | C54: =IF(AND('2. Dashboard'!$F$6>="C",OR(TOG_TR="Oui",TOG_CESU="Oui",TOG_AVANTAGES="Oui")),600,0) | D54: Vérification plafonds, mise en place politique RH, mise à jour bulletins de paie.
B55: Audit conformité cashback - mode Conforme | C55: =IF(AND(TOG_CASHBACK="Oui",CASHBACK_MODE="Conforme aux recommandations Sources"),900,0) | D55: Note méthodologique cabinet, suivi de mise en œuvre, archivage justificatifs.
B56: Provision risque URSSAF cashback - mode Standard | C56: =IF(AND(TOG_CASHBACK="Oui",CASHBACK_MODE="Standard / non documenté"),M_CASHBACK*0.3,0) | D56: Provision 30 % du cashback en cas de requalification - à apprécier en fonction du dossier.
B57: TOTAL coûts de mise en œuvre (1ère année) | C57: =SUM(C50:C56) | D57: À mettre en regard du gain net annuel - ROI typique < 1 an si stratégie ≥ B.
B59: Gain net annuel vs Stratégie A | C59: =(IF('2. Dashboard'!$F$6="A",INDEX('11. Arbitrage'!C:C,MATCH("TOTAL NET DIRIGEANT APRÈS FISCALITÉ (€)",'11. Arbitrage'!B:B,0)),IF('2. Dashboard'!$F$6="B",INDEX('11. Arbitrage'!D:D,MATCH("TOTAL NET DIRIGEANT APRÈS FISCALITÉ (€)",'11. Arbitrage'!B:B,0)),IF('2. Dashboard'!$F$6="C",INDEX('11. Arbitrage'!E:E,MATCH("TOTAL NET DIRIGEANT APRÈS FISCALITÉ (€)",'11. Arbitrage'!B:B,0)),INDEX('11. Arbitrage'!F:F,MATCH("TOTAL NET DIRIGEANT APRÈS FISCALITÉ (€)",'11. Arbitrage'!B:B,0))))))-INDEX('11. Arbitrage'!C:C,MATCH("TOTAL NET DIRIGEANT APRÈS FISCALITÉ (€)",'11. Arbitrage'!B:B,0))
B60: Retour sur investissement (en mois) | C60: =IFERROR(IF(C59>0,C57/C59*12,"-"),"-") | D60: Coûts mise en œuvre ÷ gain annuel × 12. Au-delà de 12 mois, réinterroger l'opportunité.
B62: 📈 PROJECTION 5 ANS - PATRIMOINE NET CONSTITUÉ
B63: Année | C63: Strat. A (réf.) | D63: Stratégie retenue | E63: Écart vs A
B64: Année 1 | C64: =(INDEX('11. Arbitrage'!C:C,MATCH("TOTAL NET DIRIGEANT APRÈS FISCALITÉ (€)",'11. Arbitrage'!B:B,0)))*((1+RDT_CASH)^1-1)/RDT_CASH*(1+RDT_CASH) | D64: =IFERROR((IF('2. Dashboard'!$F$6="A",INDEX('11. Arbitrage'!C:C,MATCH("TOTAL NET DIRIGEANT APRÈS FISCALITÉ (€)",'11. Arbitrage'!B:B,0)),IF('2. Dashboard'!$F$6="B",INDEX('11. Arbitrage'!D:D,MATCH("TOTAL NET DIRIGEANT APRÈS FISCALITÉ (€)",'11. Arbitrage'!B:B,0)),IF('2. Dashboard'!$F$6="C",INDEX('11. Arbitrage'!E:E,MATCH("TOTAL NET DIRIGEANT APRÈS FISCALITÉ (€)",'11. Arbitrage'!B:B,0)),INDEX('11. Arbitrage'!F:F,MATCH("TOTAL NET DIRIGEANT APRÈS FISCALITÉ (€)",'11. Arbitrage'!B:B,0))))))*((1+(IFERROR((IF(TOG_PARTICIPATION="Oui",M_PARTICIPATION,0)+IF(TOG_INTERESSEMENT="Oui",M_INTERESSEMENT,0)+IF(TOG_ABO_PEE="Oui",M_ABO_PEE,0)+IF(TOG_ABO_PER="Oui",M_ABO_PER,0)+IF(TOG_PERIN="Oui",M_PERIN,0))/(IF(TOG_PARTICIPATION="Oui",M_PARTICIPATION,0)+IF(TOG_INTERESSEMENT="Oui",M_INTERESSEMENT,0)+IF(TOG_ABO_PEE="Oui",M_ABO_PEE,0)+IF(TOG_ABO_PER="Oui",M_ABO_PER,0)+IF(TOG_PERIN="Oui",M_PERIN,0)+IF(TOG_TR="Oui",M_TR,0)+IF(TOG_CESU="Oui",M_CESU,0)+IF(TOG_AVANTAGES="Oui",M_AVANTAGES,0)+IF(TOG_MUTUELLE="Oui",M_MUTUELLE,0)+IF(TOG_IK="Oui",M_IK,0)+IF(TOG_CADO="Oui",M_CADO,0)+IF(TOG_CASHBACK="Oui",M_CASHBACK,0)),0)*RDT_EPARGNE+(1-IFERROR((IF(TOG_PARTICIPATION="Oui",M_PARTICIPATION,0)+IF(TOG_INTERESSEMENT="Oui",M_INTERESSEMENT,0)+IF(TOG_ABO_PEE="Oui",M_ABO_PEE,0)+IF(TOG_ABO_PER="Oui",M_ABO_PER,0)+IF(TOG_PERIN="Oui",M_PERIN,0))/(IF(TOG_PARTICIPATION="Oui",M_PARTICIPATION,0)+IF(TOG_INTERESSEMENT="Oui",M_INTERESSEMENT,0)+IF(TOG_ABO_PEE="Oui",M_ABO_PEE,0)+IF(TOG_ABO_PER="Oui",M_ABO_PER,0)+IF(TOG_PERIN="Oui",M_PERIN,0)+IF(TOG_TR="Oui",M_TR,0)+IF(TOG_CESU="Oui",M_CESU,0)+IF(TOG_AVANTAGES="Oui",M_AVANTAGES,0)+IF(TOG_MUTUELLE="Oui",M_MUTUELLE,0)+IF(TOG_IK="Oui",M_IK,0)+IF(TOG_CADO="Oui",M_CADO,0)+IF(TOG_CASHBACK="Oui",M_CASHBACK,0)),0))*RDT_CASH))^1-1)/(IFERROR((IF(TOG_PARTICIPATION="Oui",M_PARTICIPATION,0)+IF(TOG_INTERESSEMENT="Oui",M_INTERESSEMENT,0)+IF(TOG_ABO_PEE="Oui",M_ABO_PEE,0)+IF(TOG_ABO_PER="Oui",M_ABO_PER,0)+IF(TOG_PERIN="Oui",M_PERIN,0))/(IF(TOG_PARTICIPATION="Oui",M_PARTICIPATION,0)+IF(TOG_INTERESSEMENT="Oui",M_INTERESSEMENT,0)+IF(TOG_ABO_PEE="Oui",M_ABO_PEE,0)+IF(TOG_ABO_PER="Oui",M_ABO_PER,0)+IF(TOG_PERIN="Oui",M_PERIN,0)+IF(TOG_TR="Oui",M_TR,0)+IF(TOG_CESU="Oui",M_CESU,0)+IF(TOG_AVANTAGES="Oui",M_AVANTAGES,0)+IF(TOG_MUTUELLE="Oui",M_MUTUELLE,0)+IF(TOG_IK="Oui",M_IK,0)+IF(TOG_CADO="Oui",M_CADO,0)+IF(TOG_CASHBACK="Oui",M_CASHBACK,0)),0)*RDT_EPARGNE+(1-IFERROR((IF(TOG_PARTICIPATION="Oui",M_PARTICIPATION,0)+IF(TOG_INTERESSEMENT="Oui",M_INTERESSEMENT,0)+IF(TOG_ABO_PEE="Oui",M_ABO_PEE,0)+IF(TOG_ABO_PER="Oui",M_ABO_PER,0)+IF(TOG_PERIN="Oui",M_PERIN,0))/(IF(TOG_PARTICIPATION="Oui",M_PARTICIPATION,0)+IF(TOG_INTERESSEMENT="Oui",M_INTERESSEMENT,0)+IF(TOG_ABO_PEE="Oui",M_ABO_PEE,0)+IF(TOG_ABO_PER="Oui",M_ABO_PER,0)+IF(TOG_PERIN="Oui",M_PERIN,0)+IF(TOG_TR="Oui",M_TR,0)+IF(TOG_CESU="Oui",M_CESU,0)+IF(TOG_AVANTAGES="Oui",M_AVANTAGES,0)+IF(TOG_MUTUELLE="Oui",M_MUTUELLE,0)+IF(TOG_IK="Oui",M_IK,0)+IF(TOG_CADO="Oui",M_CADO,0)+IF(TOG_CASHBACK="Oui",M_CASHBACK,0)),0))*RDT_CASH)*(1+(IFERROR((IF(TOG_PARTICIPATION="Oui",M_PARTICIPATION,0)+IF(TOG_INTERESSEMENT="Oui",M_INTERESSEMENT,0)+IF(TOG_ABO_PEE="Oui",M_ABO_PEE,0)+IF(TOG_ABO_PER="Oui",M_ABO_PER,0)+IF(TOG_PERIN="Oui",M_PERIN,0))/(IF(TOG_PARTICIPATION="Oui",M_PARTICIPATION,0)+IF(TOG_INTERESSEMENT="Oui",M_INTERESSEMENT,0)+IF(TOG_ABO_PEE="Oui",M_ABO_PEE,0)+IF(TOG_ABO_PER="Oui",M_ABO_PER,0)+IF(TOG_PERIN="Oui",M_PERIN,0)+IF(TOG_TR="Oui",M_TR,0)+IF(TOG_CESU="Oui",M_CESU,0)+IF(TOG_AVANTAGES="Oui",M_AVANTAGES,0)+IF(TOG_MUTUELLE="Oui",M_MUTUELLE,0)+IF(TOG_IK="Oui",M_IK,0)+IF(TOG_CADO="Oui",M_CADO,0)+IF(TOG_CASHBACK="Oui",M_CASHBACK,0)),0)*RDT_EPARGNE+(1-IFERROR((IF(TOG_PARTICIPATION="Oui",M_PARTICIPATION,0)+IF(TOG_INTERESSEMENT="Oui",M_INTERESSEMENT,0)+IF(TOG_ABO_PEE="Oui",M_ABO_PEE,0)+IF(TOG_ABO_PER="Oui",M_ABO_PER,0)+IF(TOG_PERIN="Oui",M_PERIN,0))/(IF(TOG_PARTICIPATION="Oui",M_PARTICIPATION,0)+IF(TOG_INTERESSEMENT="Oui",M_INTERESSEMENT,0)+IF(TOG_ABO_PEE="Oui",M_ABO_PEE,0)+IF(TOG_ABO_PER="Oui",M_ABO_PER,0)+IF(TOG_PERIN="Oui",M_PERIN,0)+IF(TOG_TR="Oui",M_TR,0)+IF(TOG_CESU="Oui",M_CESU,0)+IF(TOG_AVANTAGES="Oui",M_AVANTAGES,0)+IF(TOG_MUTUELLE="Oui",M_MUTUELLE,0)+IF(TOG_IK="Oui",M_IK,0)+IF(TOG_CADO="Oui",M_CADO,0)+IF(TOG_CASHBACK="Oui",M_CASHBACK,0)),0))*RDT_CASH)),(IF('2. Dashboard'!$F$6="A",INDEX('11. Arbitrage'!C:C,MATCH("TOTAL NET DIRIGEANT APRÈS FISCALITÉ (€)",'11. Arbitrage'!B:B,0)),IF('2. Dashboard'!$F$6="B",INDEX('11. Arbitrage'!D:D,MATCH("TOTAL NET DIRIGEANT APRÈS FISCALITÉ (€)",'11. Arbitrage'!B:B,0)),IF('2. Dashboard'!$F$6="C",INDEX('11. Arbitrage'!E:E,MATCH("TOTAL NET DIRIGEANT APRÈS FISCALITÉ (€)",'11. Arbitrage'!B:B,0)),INDEX('11. Arbitrage'!F:F,MATCH("TOTAL NET DIRIGEANT APRÈS FISCALITÉ (€)",'11. Arbitrage'!B:B,0))))))*1) | E64: =D64-C64
B65: Année 2 | C65: =(INDEX('11. Arbitrage'!C:C,MATCH("TOTAL NET DIRIGEANT APRÈS FISCALITÉ (€)",'11. Arbitrage'!B:B,0)))*((1+RDT_CASH)^2-1)/RDT_CASH*(1+RDT_CASH) | D65: =IFERROR((IF('2. Dashboard'!$F$6="A",INDEX('11. Arbitrage'!C:C,MATCH("TOTAL NET DIRIGEANT APRÈS FISCALITÉ (€)",'11. Arbitrage'!B:B,0)),IF('2. Dashboard'!$F$6="B",INDEX('11. Arbitrage'!D:D,MATCH("TOTAL NET DIRIGEANT APRÈS FISCALITÉ (€)",'11. Arbitrage'!B:B,0)),IF('2. Dashboard'!$F$6="C",INDEX('11. Arbitrage'!E:E,MATCH("TOTAL NET DIRIGEANT APRÈS FISCALITÉ (€)",'11. Arbitrage'!B:B,0)),INDEX('11. Arbitrage'!F:F,MATCH("TOTAL NET DIRIGEANT APRÈS FISCALITÉ (€)",'11. Arbitrage'!B:B,0))))))*((1+(IFERROR((IF(TOG_PARTICIPATION="Oui",M_PARTICIPATION,0)+IF(TOG_INTERESSEMENT="Oui",M_INTERESSEMENT,0)+IF(TOG_ABO_PEE="Oui",M_ABO_PEE,0)+IF(TOG_ABO_PER="Oui",M_ABO_PER,0)+IF(TOG_PERIN="Oui",M_PERIN,0))/(IF(TOG_PARTICIPATION="Oui",M_PARTICIPATION,0)+IF(TOG_INTERESSEMENT="Oui",M_INTERESSEMENT,0)+IF(TOG_ABO_PEE="Oui",M_ABO_PEE,0)+IF(TOG_ABO_PER="Oui",M_ABO_PER,0)+IF(TOG_PERIN="Oui",M_PERIN,0)+IF(TOG_TR="Oui",M_TR,0)+IF(TOG_CESU="Oui",M_CESU,0)+IF(TOG_AVANTAGES="Oui",M_AVANTAGES,0)+IF(TOG_MUTUELLE="Oui",M_MUTUELLE,0)+IF(TOG_IK="Oui",M_IK,0)+IF(TOG_CADO="Oui",M_CADO,0)+IF(TOG_CASHBACK="Oui",M_CASHBACK,0)),0)*RDT_EPARGNE+(1-IFERROR((IF(TOG_PARTICIPATION="Oui",M_PARTICIPATION,0)+IF(TOG_INTERESSEMENT="Oui",M_INTERESSEMENT,0)+IF(TOG_ABO_PEE="Oui",M_ABO_PEE,0)+IF(TOG_ABO_PER="Oui",M_ABO_PER,0)+IF(TOG_PERIN="Oui",M_PERIN,0))/(IF(TOG_PARTICIPATION="Oui",M_PARTICIPATION,0)+IF(TOG_INTERESSEMENT="Oui",M_INTERESSEMENT,0)+IF(TOG_ABO_PEE="Oui",M_ABO_PEE,0)+IF(TOG_ABO_PER="Oui",M_ABO_PER,0)+IF(TOG_PERIN="Oui",M_PERIN,0)+IF(TOG_TR="Oui",M_TR,0)+IF(TOG_CESU="Oui",M_CESU,0)+IF(TOG_AVANTAGES="Oui",M_AVANTAGES,0)+IF(TOG_MUTUELLE="Oui",M_MUTUELLE,0)+IF(TOG_IK="Oui",M_IK,0)+IF(TOG_CADO="Oui",M_CADO,0)+IF(TOG_CASHBACK="Oui",M_CASHBACK,0)),0))*RDT_CASH))^2-1)/(IFERROR((IF(TOG_PARTICIPATION="Oui",M_PARTICIPATION,0)+IF(TOG_INTERESSEMENT="Oui",M_INTERESSEMENT,0)+IF(TOG_ABO_PEE="Oui",M_ABO_PEE,0)+IF(TOG_ABO_PER="Oui",M_ABO_PER,0)+IF(TOG_PERIN="Oui",M_PERIN,0))/(IF(TOG_PARTICIPATION="Oui",M_PARTICIPATION,0)+IF(TOG_INTERESSEMENT="Oui",M_INTERESSEMENT,0)+IF(TOG_ABO_PEE="Oui",M_ABO_PEE,0)+IF(TOG_ABO_PER="Oui",M_ABO_PER,0)+IF(TOG_PERIN="Oui",M_PERIN,0)+IF(TOG_TR="Oui",M_TR,0)+IF(TOG_CESU="Oui",M_CESU,0)+IF(TOG_AVANTAGES="Oui",M_AVANTAGES,0)+IF(TOG_MUTUELLE="Oui",M_MUTUELLE,0)+IF(TOG_IK="Oui",M_IK,0)+IF(TOG_CADO="Oui",M_CADO,0)+IF(TOG_CASHBACK="Oui",M_CASHBACK,0)),0)*RDT_EPARGNE+(1-IFERROR((IF(TOG_PARTICIPATION="Oui",M_PARTICIPATION,0)+IF(TOG_INTERESSEMENT="Oui",M_INTERESSEMENT,0)+IF(TOG_ABO_PEE="Oui",M_ABO_PEE,0)+IF(TOG_ABO_PER="Oui",M_ABO_PER,0)+IF(TOG_PERIN="Oui",M_PERIN,0))/(IF(TOG_PARTICIPATION="Oui",M_PARTICIPATION,0)+IF(TOG_INTERESSEMENT="Oui",M_INTERESSEMENT,0)+IF(TOG_ABO_PEE="Oui",M_ABO_PEE,0)+IF(TOG_ABO_PER="Oui",M_ABO_PER,0)+IF(TOG_PERIN="Oui",M_PERIN,0)+IF(TOG_TR="Oui",M_TR,0)+IF(TOG_CESU="Oui",M_CESU,0)+IF(TOG_AVANTAGES="Oui",M_AVANTAGES,0)+IF(TOG_MUTUELLE="Oui",M_MUTUELLE,0)+IF(TOG_IK="Oui",M_IK,0)+IF(TOG_CADO="Oui",M_CADO,0)+IF(TOG_CASHBACK="Oui",M_CASHBACK,0)),0))*RDT_CASH)*(1+(IFERROR((IF(TOG_PARTICIPATION="Oui",M_PARTICIPATION,0)+IF(TOG_INTERESSEMENT="Oui",M_INTERESSEMENT,0)+IF(TOG_ABO_PEE="Oui",M_ABO_PEE,0)+IF(TOG_ABO_PER="Oui",M_ABO_PER,0)+IF(TOG_PERIN="Oui",M_PERIN,0))/(IF(TOG_PARTICIPATION="Oui",M_PARTICIPATION,0)+IF(TOG_INTERESSEMENT="Oui",M_INTERESSEMENT,0)+IF(TOG_ABO_PEE="Oui",M_ABO_PEE,0)+IF(TOG_ABO_PER="Oui",M_ABO_PER,0)+IF(TOG_PERIN="Oui",M_PERIN,0)+IF(TOG_TR="Oui",M_TR,0)+IF(TOG_CESU="Oui",M_CESU,0)+IF(TOG_AVANTAGES="Oui",M_AVANTAGES,0)+IF(TOG_MUTUELLE="Oui",M_MUTUELLE,0)+IF(TOG_IK="Oui",M_IK,0)+IF(TOG_CADO="Oui",M_CADO,0)+IF(TOG_CASHBACK="Oui",M_CASHBACK,0)),0)*RDT_EPARGNE+(1-IFERROR((IF(TOG_PARTICIPATION="Oui",M_PARTICIPATION,0)+IF(TOG_INTERESSEMENT="Oui",M_INTERESSEMENT,0)+IF(TOG_ABO_PEE="Oui",M_ABO_PEE,0)+IF(TOG_ABO_PER="Oui",M_ABO_PER,0)+IF(TOG_PERIN="Oui",M_PERIN,0))/(IF(TOG_PARTICIPATION="Oui",M_PARTICIPATION,0)+IF(TOG_INTERESSEMENT="Oui",M_INTERESSEMENT,0)+IF(TOG_ABO_PEE="Oui",M_ABO_PEE,0)+IF(TOG_ABO_PER="Oui",M_ABO_PER,0)+IF(TOG_PERIN="Oui",M_PERIN,0)+IF(TOG_TR="Oui",M_TR,0)+IF(TOG_CESU="Oui",M_CESU,0)+IF(TOG_AVANTAGES="Oui",M_AVANTAGES,0)+IF(TOG_MUTUELLE="Oui",M_MUTUELLE,0)+IF(TOG_IK="Oui",M_IK,0)+IF(TOG_CADO="Oui",M_CADO,0)+IF(TOG_CASHBACK="Oui",M_CASHBACK,0)),0))*RDT_CASH)),(IF('2. Dashboard'!$F$6="A",INDEX('11. Arbitrage'!C:C,MATCH("TOTAL NET DIRIGEANT APRÈS FISCALITÉ (€)",'11. Arbitrage'!B:B,0)),IF('2. Dashboard'!$F$6="B",INDEX('11. Arbitrage'!D:D,MATCH("TOTAL NET DIRIGEANT APRÈS FISCALITÉ (€)",'11. Arbitrage'!B:B,0)),IF('2. Dashboard'!$F$6="C",INDEX('11. Arbitrage'!E:E,MATCH("TOTAL NET DIRIGEANT APRÈS FISCALITÉ (€)",'11. Arbitrage'!B:B,0)),INDEX('11. Arbitrage'!F:F,MATCH("TOTAL NET DIRIGEANT APRÈS FISCALITÉ (€)",'11. Arbitrage'!B:B,0))))))*2) | E65: =D65-C65
B66: Année 3 | C66: =(INDEX('11. Arbitrage'!C:C,MATCH("TOTAL NET DIRIGEANT APRÈS FISCALITÉ (€)",'11. Arbitrage'!B:B,0)))*((1+RDT_CASH)^3-1)/RDT_CASH*(1+RDT_CASH) | D66: =IFERROR((IF('2. Dashboard'!$F$6="A",INDEX('11. Arbitrage'!C:C,MATCH("TOTAL NET DIRIGEANT APRÈS FISCALITÉ (€)",'11. Arbitrage'!B:B,0)),IF('2. Dashboard'!$F$6="B",INDEX('11. Arbitrage'!D:D,MATCH("TOTAL NET DIRIGEANT APRÈS FISCALITÉ (€)",'11. Arbitrage'!B:B,0)),IF('2. Dashboard'!$F$6="C",INDEX('11. Arbitrage'!E:E,MATCH("TOTAL NET DIRIGEANT APRÈS FISCALITÉ (€)",'11. Arbitrage'!B:B,0)),INDEX('11. Arbitrage'!F:F,MATCH("TOTAL NET DIRIGEANT APRÈS FISCALITÉ (€)",'11. Arbitrage'!B:B,0))))))*((1+(IFERROR((IF(TOG_PARTICIPATION="Oui",M_PARTICIPATION,0)+IF(TOG_INTERESSEMENT="Oui",M_INTERESSEMENT,0)+IF(TOG_ABO_PEE="Oui",M_ABO_PEE,0)+IF(TOG_ABO_PER="Oui",M_ABO_PER,0)+IF(TOG_PERIN="Oui",M_PERIN,0))/(IF(TOG_PARTICIPATION="Oui",M_PARTICIPATION,0)+IF(TOG_INTERESSEMENT="Oui",M_INTERESSEMENT,0)+IF(TOG_ABO_PEE="Oui",M_ABO_PEE,0)+IF(TOG_ABO_PER="Oui",M_ABO_PER,0)+IF(TOG_PERIN="Oui",M_PERIN,0)+IF(TOG_TR="Oui",M_TR,0)+IF(TOG_CESU="Oui",M_CESU,0)+IF(TOG_AVANTAGES="Oui",M_AVANTAGES,0)+IF(TOG_MUTUELLE="Oui",M_MUTUELLE,0)+IF(TOG_IK="Oui",M_IK,0)+IF(TOG_CADO="Oui",M_CADO,0)+IF(TOG_CASHBACK="Oui",M_CASHBACK,0)),0)*RDT_EPARGNE+(1-IFERROR((IF(TOG_PARTICIPATION="Oui",M_PARTICIPATION,0)+IF(TOG_INTERESSEMENT="Oui",M_INTERESSEMENT,0)+IF(TOG_ABO_PEE="Oui",M_ABO_PEE,0)+IF(TOG_ABO_PER="Oui",M_ABO_PER,0)+IF(TOG_PERIN="Oui",M_PERIN,0))/(IF(TOG_PARTICIPATION="Oui",M_PARTICIPATION,0)+IF(TOG_INTERESSEMENT="Oui",M_INTERESSEMENT,0)+IF(TOG_ABO_PEE="Oui",M_ABO_PEE,0)+IF(TOG_ABO_PER="Oui",M_ABO_PER,0)+IF(TOG_PERIN="Oui",M_PERIN,0)+IF(TOG_TR="Oui",M_TR,0)+IF(TOG_CESU="Oui",M_CESU,0)+IF(TOG_AVANTAGES="Oui",M_AVANTAGES,0)+IF(TOG_MUTUELLE="Oui",M_MUTUELLE,0)+IF(TOG_IK="Oui",M_IK,0)+IF(TOG_CADO="Oui",M_CADO,0)+IF(TOG_CASHBACK="Oui",M_CASHBACK,0)),0))*RDT_CASH))^3-1)/(IFERROR((IF(TOG_PARTICIPATION="Oui",M_PARTICIPATION,0)+IF(TOG_INTERESSEMENT="Oui",M_INTERESSEMENT,0)+IF(TOG_ABO_PEE="Oui",M_ABO_PEE,0)+IF(TOG_ABO_PER="Oui",M_ABO_PER,0)+IF(TOG_PERIN="Oui",M_PERIN,0))/(IF(TOG_PARTICIPATION="Oui",M_PARTICIPATION,0)+IF(TOG_INTERESSEMENT="Oui",M_INTERESSEMENT,0)+IF(TOG_ABO_PEE="Oui",M_ABO_PEE,0)+IF(TOG_ABO_PER="Oui",M_ABO_PER,0)+IF(TOG_PERIN="Oui",M_PERIN,0)+IF(TOG_TR="Oui",M_TR,0)+IF(TOG_CESU="Oui",M_CESU,0)+IF(TOG_AVANTAGES="Oui",M_AVANTAGES,0)+IF(TOG_MUTUELLE="Oui",M_MUTUELLE,0)+IF(TOG_IK="Oui",M_IK,0)+IF(TOG_CADO="Oui",M_CADO,0)+IF(TOG_CASHBACK="Oui",M_CASHBACK,0)),0)*RDT_EPARGNE+(1-IFERROR((IF(TOG_PARTICIPATION="Oui",M_PARTICIPATION,0)+IF(TOG_INTERESSEMENT="Oui",M_INTERESSEMENT,0)+IF(TOG_ABO_PEE="Oui",M_ABO_PEE,0)+IF(TOG_ABO_PER="Oui",M_ABO_PER,0)+IF(TOG_PERIN="Oui",M_PERIN,0))/(IF(TOG_PARTICIPATION="Oui",M_PARTICIPATION,0)+IF(TOG_INTERESSEMENT="Oui",M_INTERESSEMENT,0)+IF(TOG_ABO_PEE="Oui",M_ABO_PEE,0)+IF(TOG_ABO_PER="Oui",M_ABO_PER,0)+IF(TOG_PERIN="Oui",M_PERIN,0)+IF(TOG_TR="Oui",M_TR,0)+IF(TOG_CESU="Oui",M_CESU,0)+IF(TOG_AVANTAGES="Oui",M_AVANTAGES,0)+IF(TOG_MUTUELLE="Oui",M_MUTUELLE,0)+IF(TOG_IK="Oui",M_IK,0)+IF(TOG_CADO="Oui",M_CADO,0)+IF(TOG_CASHBACK="Oui",M_CASHBACK,0)),0))*RDT_CASH)*(1+(IFERROR((IF(TOG_PARTICIPATION="Oui",M_PARTICIPATION,0)+IF(TOG_INTERESSEMENT="Oui",M_INTERESSEMENT,0)+IF(TOG_ABO_PEE="Oui",M_ABO_PEE,0)+IF(TOG_ABO_PER="Oui",M_ABO_PER,0)+IF(TOG_PERIN="Oui",M_PERIN,0))/(IF(TOG_PARTICIPATION="Oui",M_PARTICIPATION,0)+IF(TOG_INTERESSEMENT="Oui",M_INTERESSEMENT,0)+IF(TOG_ABO_PEE="Oui",M_ABO_PEE,0)+IF(TOG_ABO_PER="Oui",M_ABO_PER,0)+IF(TOG_PERIN="Oui",M_PERIN,0)+IF(TOG_TR="Oui",M_TR,0)+IF(TOG_CESU="Oui",M_CESU,0)+IF(TOG_AVANTAGES="Oui",M_AVANTAGES,0)+IF(TOG_MUTUELLE="Oui",M_MUTUELLE,0)+IF(TOG_IK="Oui",M_IK,0)+IF(TOG_CADO="Oui",M_CADO,0)+IF(TOG_CASHBACK="Oui",M_CASHBACK,0)),0)*RDT_EPARGNE+(1-IFERROR((IF(TOG_PARTICIPATION="Oui",M_PARTICIPATION,0)+IF(TOG_INTERESSEMENT="Oui",M_INTERESSEMENT,0)+IF(TOG_ABO_PEE="Oui",M_ABO_PEE,0)+IF(TOG_ABO_PER="Oui",M_ABO_PER,0)+IF(TOG_PERIN="Oui",M_PERIN,0))/(IF(TOG_PARTICIPATION="Oui",M_PARTICIPATION,0)+IF(TOG_INTERESSEMENT="Oui",M_INTERESSEMENT,0)+IF(TOG_ABO_PEE="Oui",M_ABO_PEE,0)+IF(TOG_ABO_PER="Oui",M_ABO_PER,0)+IF(TOG_PERIN="Oui",M_PERIN,0)+IF(TOG_TR="Oui",M_TR,0)+IF(TOG_CESU="Oui",M_CESU,0)+IF(TOG_AVANTAGES="Oui",M_AVANTAGES,0)+IF(TOG_MUTUELLE="Oui",M_MUTUELLE,0)+IF(TOG_IK="Oui",M_IK,0)+IF(TOG_CADO="Oui",M_CADO,0)+IF(TOG_CASHBACK="Oui",M_CASHBACK,0)),0))*RDT_CASH)),(IF('2. Dashboard'!$F$6="A",INDEX('11. Arbitrage'!C:C,MATCH("TOTAL NET DIRIGEANT APRÈS FISCALITÉ (€)",'11. Arbitrage'!B:B,0)),IF('2. Dashboard'!$F$6="B",INDEX('11. Arbitrage'!D:D,MATCH("TOTAL NET DIRIGEANT APRÈS FISCALITÉ (€)",'11. Arbitrage'!B:B,0)),IF('2. Dashboard'!$F$6="C",INDEX('11. Arbitrage'!E:E,MATCH("TOTAL NET DIRIGEANT APRÈS FISCALITÉ (€)",'11. Arbitrage'!B:B,0)),INDEX('11. Arbitrage'!F:F,MATCH("TOTAL NET DIRIGEANT APRÈS FISCALITÉ (€)",'11. Arbitrage'!B:B,0))))))*3) | E66: =D66-C66
B67: Année 4 | C67: =(INDEX('11. Arbitrage'!C:C,MATCH("TOTAL NET DIRIGEANT APRÈS FISCALITÉ (€)",'11. Arbitrage'!B:B,0)))*((1+RDT_CASH)^4-1)/RDT_CASH*(1+RDT_CASH) | D67: =IFERROR((IF('2. Dashboard'!$F$6="A",INDEX('11. Arbitrage'!C:C,MATCH("TOTAL NET DIRIGEANT APRÈS FISCALITÉ (€)",'11. Arbitrage'!B:B,0)),IF('2. Dashboard'!$F$6="B",INDEX('11. Arbitrage'!D:D,MATCH("TOTAL NET DIRIGEANT APRÈS FISCALITÉ (€)",'11. Arbitrage'!B:B,0)),IF('2. Dashboard'!$F$6="C",INDEX('11. Arbitrage'!E:E,MATCH("TOTAL NET DIRIGEANT APRÈS FISCALITÉ (€)",'11. Arbitrage'!B:B,0)),INDEX('11. Arbitrage'!F:F,MATCH("TOTAL NET DIRIGEANT APRÈS FISCALITÉ (€)",'11. Arbitrage'!B:B,0))))))*((1+(IFERROR((IF(TOG_PARTICIPATION="Oui",M_PARTICIPATION,0)+IF(TOG_INTERESSEMENT="Oui",M_INTERESSEMENT,0)+IF(TOG_ABO_PEE="Oui",M_ABO_PEE,0)+IF(TOG_ABO_PER="Oui",M_ABO_PER,0)+IF(TOG_PERIN="Oui",M_PERIN,0))/(IF(TOG_PARTICIPATION="Oui",M_PARTICIPATION,0)+IF(TOG_INTERESSEMENT="Oui",M_INTERESSEMENT,0)+IF(TOG_ABO_PEE="Oui",M_ABO_PEE,0)+IF(TOG_ABO_PER="Oui",M_ABO_PER,0)+IF(TOG_PERIN="Oui",M_PERIN,0)+IF(TOG_TR="Oui",M_TR,0)+IF(TOG_CESU="Oui",M_CESU,0)+IF(TOG_AVANTAGES="Oui",M_AVANTAGES,0)+IF(TOG_MUTUELLE="Oui",M_MUTUELLE,0)+IF(TOG_IK="Oui",M_IK,0)+IF(TOG_CADO="Oui",M_CADO,0)+IF(TOG_CASHBACK="Oui",M_CASHBACK,0)),0)*RDT_EPARGNE+(1-IFERROR((IF(TOG_PARTICIPATION="Oui",M_PARTICIPATION,0)+IF(TOG_INTERESSEMENT="Oui",M_INTERESSEMENT,0)+IF(TOG_ABO_PEE="Oui",M_ABO_PEE,0)+IF(TOG_ABO_PER="Oui",M_ABO_PER,0)+IF(TOG_PERIN="Oui",M_PERIN,0))/(IF(TOG_PARTICIPATION="Oui",M_PARTICIPATION,0)+IF(TOG_INTERESSEMENT="Oui",M_INTERESSEMENT,0)+IF(TOG_ABO_PEE="Oui",M_ABO_PEE,0)+IF(TOG_ABO_PER="Oui",M_ABO_PER,0)+IF(TOG_PERIN="Oui",M_PERIN,0)+IF(TOG_TR="Oui",M_TR,0)+IF(TOG_CESU="Oui",M_CESU,0)+IF(TOG_AVANTAGES="Oui",M_AVANTAGES,0)+IF(TOG_MUTUELLE="Oui",M_MUTUELLE,0)+IF(TOG_IK="Oui",M_IK,0)+IF(TOG_CADO="Oui",M_CADO,0)+IF(TOG_CASHBACK="Oui",M_CASHBACK,0)),0))*RDT_CASH))^4-1)/(IFERROR((IF(TOG_PARTICIPATION="Oui",M_PARTICIPATION,0)+IF(TOG_INTERESSEMENT="Oui",M_INTERESSEMENT,0)+IF(TOG_ABO_PEE="Oui",M_ABO_PEE,0)+IF(TOG_ABO_PER="Oui",M_ABO_PER,0)+IF(TOG_PERIN="Oui",M_PERIN,0))/(IF(TOG_PARTICIPATION="Oui",M_PARTICIPATION,0)+IF(TOG_INTERESSEMENT="Oui",M_INTERESSEMENT,0)+IF(TOG_ABO_PEE="Oui",M_ABO_PEE,0)+IF(TOG_ABO_PER="Oui",M_ABO_PER,0)+IF(TOG_PERIN="Oui",M_PERIN,0)+IF(TOG_TR="Oui",M_TR,0)+IF(TOG_CESU="Oui",M_CESU,0)+IF(TOG_AVANTAGES="Oui",M_AVANTAGES,0)+IF(TOG_MUTUELLE="Oui",M_MUTUELLE,0)+IF(TOG_IK="Oui",M_IK,0)+IF(TOG_CADO="Oui",M_CADO,0)+IF(TOG_CASHBACK="Oui",M_CASHBACK,0)),0)*RDT_EPARGNE+(1-IFERROR((IF(TOG_PARTICIPATION="Oui",M_PARTICIPATION,0)+IF(TOG_INTERESSEMENT="Oui",M_INTERESSEMENT,0)+IF(TOG_ABO_PEE="Oui",M_ABO_PEE,0)+IF(TOG_ABO_PER="Oui",M_ABO_PER,0)+IF(TOG_PERIN="Oui",M_PERIN,0))/(IF(TOG_PARTICIPATION="Oui",M_PARTICIPATION,0)+IF(TOG_INTERESSEMENT="Oui",M_INTERESSEMENT,0)+IF(TOG_ABO_PEE="Oui",M_ABO_PEE,0)+IF(TOG_ABO_PER="Oui",M_ABO_PER,0)+IF(TOG_PERIN="Oui",M_PERIN,0)+IF(TOG_TR="Oui",M_TR,0)+IF(TOG_CESU="Oui",M_CESU,0)+IF(TOG_AVANTAGES="Oui",M_AVANTAGES,0)+IF(TOG_MUTUELLE="Oui",M_MUTUELLE,0)+IF(TOG_IK="Oui",M_IK,0)+IF(TOG_CADO="Oui",M_CADO,0)+IF(TOG_CASHBACK="Oui",M_CASHBACK,0)),0))*RDT_CASH)*(1+(IFERROR((IF(TOG_PARTICIPATION="Oui",M_PARTICIPATION,0)+IF(TOG_INTERESSEMENT="Oui",M_INTERESSEMENT,0)+IF(TOG_ABO_PEE="Oui",M_ABO_PEE,0)+IF(TOG_ABO_PER="Oui",M_ABO_PER,0)+IF(TOG_PERIN="Oui",M_PERIN,0))/(IF(TOG_PARTICIPATION="Oui",M_PARTICIPATION,0)+IF(TOG_INTERESSEMENT="Oui",M_INTERESSEMENT,0)+IF(TOG_ABO_PEE="Oui",M_ABO_PEE,0)+IF(TOG_ABO_PER="Oui",M_ABO_PER,0)+IF(TOG_PERIN="Oui",M_PERIN,0)+IF(TOG_TR="Oui",M_TR,0)+IF(TOG_CESU="Oui",M_CESU,0)+IF(TOG_AVANTAGES="Oui",M_AVANTAGES,0)+IF(TOG_MUTUELLE="Oui",M_MUTUELLE,0)+IF(TOG_IK="Oui",M_IK,0)+IF(TOG_CADO="Oui",M_CADO,0)+IF(TOG_CASHBACK="Oui",M_CASHBACK,0)),0)*RDT_EPARGNE+(1-IFERROR((IF(TOG_PARTICIPATION="Oui",M_PARTICIPATION,0)+IF(TOG_INTERESSEMENT="Oui",M_INTERESSEMENT,0)+IF(TOG_ABO_PEE="Oui",M_ABO_PEE,0)+IF(TOG_ABO_PER="Oui",M_ABO_PER,0)+IF(TOG_PERIN="Oui",M_PERIN,0))/(IF(TOG_PARTICIPATION="Oui",M_PARTICIPATION,0)+IF(TOG_INTERESSEMENT="Oui",M_INTERESSEMENT,0)+IF(TOG_ABO_PEE="Oui",M_ABO_PEE,0)+IF(TOG_ABO_PER="Oui",M_ABO_PER,0)+IF(TOG_PERIN="Oui",M_PERIN,0)+IF(TOG_TR="Oui",M_TR,0)+IF(TOG_CESU="Oui",M_CESU,0)+IF(TOG_AVANTAGES="Oui",M_AVANTAGES,0)+IF(TOG_MUTUELLE="Oui",M_MUTUELLE,0)+IF(TOG_IK="Oui",M_IK,0)+IF(TOG_CADO="Oui",M_CADO,0)+IF(TOG_CASHBACK="Oui",M_CASHBACK,0)),0))*RDT_CASH)),(IF('2. Dashboard'!$F$6="A",INDEX('11. Arbitrage'!C:C,MATCH("TOTAL NET DIRIGEANT APRÈS FISCALITÉ (€)",'11. Arbitrage'!B:B,0)),IF('2. Dashboard'!$F$6="B",INDEX('11. Arbitrage'!D:D,MATCH("TOTAL NET DIRIGEANT APRÈS FISCALITÉ (€)",'11. Arbitrage'!B:B,0)),IF('2. Dashboard'!$F$6="C",INDEX('11. Arbitrage'!E:E,MATCH("TOTAL NET DIRIGEANT APRÈS FISCALITÉ (€)",'11. Arbitrage'!B:B,0)),INDEX('11. Arbitrage'!F:F,MATCH("TOTAL NET DIRIGEANT APRÈS FISCALITÉ (€)",'11. Arbitrage'!B:B,0))))))*4) | E67: =D67-C67
B68: Année 5 | C68: =(INDEX('11. Arbitrage'!C:C,MATCH("TOTAL NET DIRIGEANT APRÈS FISCALITÉ (€)",'11. Arbitrage'!B:B,0)))*((1+RDT_CASH)^5-1)/RDT_CASH*(1+RDT_CASH) | D68: =IFERROR((IF('2. Dashboard'!$F$6="A",INDEX('11. Arbitrage'!C:C,MATCH("TOTAL NET DIRIGEANT APRÈS FISCALITÉ (€)",'11. Arbitrage'!B:B,0)),IF('2. Dashboard'!$F$6="B",INDEX('11. Arbitrage'!D:D,MATCH("TOTAL NET DIRIGEANT APRÈS FISCALITÉ (€)",'11. Arbitrage'!B:B,0)),IF('2. Dashboard'!$F$6="C",INDEX('11. Arbitrage'!E:E,MATCH("TOTAL NET DIRIGEANT APRÈS FISCALITÉ (€)",'11. Arbitrage'!B:B,0)),INDEX('11. Arbitrage'!F:F,MATCH("TOTAL NET DIRIGEANT APRÈS FISCALITÉ (€)",'11. Arbitrage'!B:B,0))))))*((1+(IFERROR((IF(TOG_PARTICIPATION="Oui",M_PARTICIPATION,0)+IF(TOG_INTERESSEMENT="Oui",M_INTERESSEMENT,0)+IF(TOG_ABO_PEE="Oui",M_ABO_PEE,0)+IF(TOG_ABO_PER="Oui",M_ABO_PER,0)+IF(TOG_PERIN="Oui",M_PERIN,0))/(IF(TOG_PARTICIPATION="Oui",M_PARTICIPATION,0)+IF(TOG_INTERESSEMENT="Oui",M_INTERESSEMENT,0)+IF(TOG_ABO_PEE="Oui",M_ABO_PEE,0)+IF(TOG_ABO_PER="Oui",M_ABO_PER,0)+IF(TOG_PERIN="Oui",M_PERIN,0)+IF(TOG_TR="Oui",M_TR,0)+IF(TOG_CESU="Oui",M_CESU,0)+IF(TOG_AVANTAGES="Oui",M_AVANTAGES,0)+IF(TOG_MUTUELLE="Oui",M_MUTUELLE,0)+IF(TOG_IK="Oui",M_IK,0)+IF(TOG_CADO="Oui",M_CADO,0)+IF(TOG_CASHBACK="Oui",M_CASHBACK,0)),0)*RDT_EPARGNE+(1-IFERROR((IF(TOG_PARTICIPATION="Oui",M_PARTICIPATION,0)+IF(TOG_INTERESSEMENT="Oui",M_INTERESSEMENT,0)+IF(TOG_ABO_PEE="Oui",M_ABO_PEE,0)+IF(TOG_ABO_PER="Oui",M_ABO_PER,0)+IF(TOG_PERIN="Oui",M_PERIN,0))/(IF(TOG_PARTICIPATION="Oui",M_PARTICIPATION,0)+IF(TOG_INTERESSEMENT="Oui",M_INTERESSEMENT,0)+IF(TOG_ABO_PEE="Oui",M_ABO_PEE,0)+IF(TOG_ABO_PER="Oui",M_ABO_PER,0)+IF(TOG_PERIN="Oui",M_PERIN,0)+IF(TOG_TR="Oui",M_TR,0)+IF(TOG_CESU="Oui",M_CESU,0)+IF(TOG_AVANTAGES="Oui",M_AVANTAGES,0)+IF(TOG_MUTUELLE="Oui",M_MUTUELLE,0)+IF(TOG_IK="Oui",M_IK,0)+IF(TOG_CADO="Oui",M_CADO,0)+IF(TOG_CASHBACK="Oui",M_CASHBACK,0)),0))*RDT_CASH))^5-1)/(IFERROR((IF(TOG_PARTICIPATION="Oui",M_PARTICIPATION,0)+IF(TOG_INTERESSEMENT="Oui",M_INTERESSEMENT,0)+IF(TOG_ABO_PEE="Oui",M_ABO_PEE,0)+IF(TOG_ABO_PER="Oui",M_ABO_PER,0)+IF(TOG_PERIN="Oui",M_PERIN,0))/(IF(TOG_PARTICIPATION="Oui",M_PARTICIPATION,0)+IF(TOG_INTERESSEMENT="Oui",M_INTERESSEMENT,0)+IF(TOG_ABO_PEE="Oui",M_ABO_PEE,0)+IF(TOG_ABO_PER="Oui",M_ABO_PER,0)+IF(TOG_PERIN="Oui",M_PERIN,0)+IF(TOG_TR="Oui",M_TR,0)+IF(TOG_CESU="Oui",M_CESU,0)+IF(TOG_AVANTAGES="Oui",M_AVANTAGES,0)+IF(TOG_MUTUELLE="Oui",M_MUTUELLE,0)+IF(TOG_IK="Oui",M_IK,0)+IF(TOG_CADO="Oui",M_CADO,0)+IF(TOG_CASHBACK="Oui",M_CASHBACK,0)),0)*RDT_EPARGNE+(1-IFERROR((IF(TOG_PARTICIPATION="Oui",M_PARTICIPATION,0)+IF(TOG_INTERESSEMENT="Oui",M_INTERESSEMENT,0)+IF(TOG_ABO_PEE="Oui",M_ABO_PEE,0)+IF(TOG_ABO_PER="Oui",M_ABO_PER,0)+IF(TOG_PERIN="Oui",M_PERIN,0))/(IF(TOG_PARTICIPATION="Oui",M_PARTICIPATION,0)+IF(TOG_INTERESSEMENT="Oui",M_INTERESSEMENT,0)+IF(TOG_ABO_PEE="Oui",M_ABO_PEE,0)+IF(TOG_ABO_PER="Oui",M_ABO_PER,0)+IF(TOG_PERIN="Oui",M_PERIN,0)+IF(TOG_TR="Oui",M_TR,0)+IF(TOG_CESU="Oui",M_CESU,0)+IF(TOG_AVANTAGES="Oui",M_AVANTAGES,0)+IF(TOG_MUTUELLE="Oui",M_MUTUELLE,0)+IF(TOG_IK="Oui",M_IK,0)+IF(TOG_CADO="Oui",M_CADO,0)+IF(TOG_CASHBACK="Oui",M_CASHBACK,0)),0))*RDT_CASH)*(1+(IFERROR((IF(TOG_PARTICIPATION="Oui",M_PARTICIPATION,0)+IF(TOG_INTERESSEMENT="Oui",M_INTERESSEMENT,0)+IF(TOG_ABO_PEE="Oui",M_ABO_PEE,0)+IF(TOG_ABO_PER="Oui",M_ABO_PER,0)+IF(TOG_PERIN="Oui",M_PERIN,0))/(IF(TOG_PARTICIPATION="Oui",M_PARTICIPATION,0)+IF(TOG_INTERESSEMENT="Oui",M_INTERESSEMENT,0)+IF(TOG_ABO_PEE="Oui",M_ABO_PEE,0)+IF(TOG_ABO_PER="Oui",M_ABO_PER,0)+IF(TOG_PERIN="Oui",M_PERIN,0)+IF(TOG_TR="Oui",M_TR,0)+IF(TOG_CESU="Oui",M_CESU,0)+IF(TOG_AVANTAGES="Oui",M_AVANTAGES,0)+IF(TOG_MUTUELLE="Oui",M_MUTUELLE,0)+IF(TOG_IK="Oui",M_IK,0)+IF(TOG_CADO="Oui",M_CADO,0)+IF(TOG_CASHBACK="Oui",M_CASHBACK,0)),0)*RDT_EPARGNE+(1-IFERROR((IF(TOG_PARTICIPATION="Oui",M_PARTICIPATION,0)+IF(TOG_INTERESSEMENT="Oui",M_INTERESSEMENT,0)+IF(TOG_ABO_PEE="Oui",M_ABO_PEE,0)+IF(TOG_ABO_PER="Oui",M_ABO_PER,0)+IF(TOG_PERIN="Oui",M_PERIN,0))/(IF(TOG_PARTICIPATION="Oui",M_PARTICIPATION,0)+IF(TOG_INTERESSEMENT="Oui",M_INTERESSEMENT,0)+IF(TOG_ABO_PEE="Oui",M_ABO_PEE,0)+IF(TOG_ABO_PER="Oui",M_ABO_PER,0)+IF(TOG_PERIN="Oui",M_PERIN,0)+IF(TOG_TR="Oui",M_TR,0)+IF(TOG_CESU="Oui",M_CESU,0)+IF(TOG_AVANTAGES="Oui",M_AVANTAGES,0)+IF(TOG_MUTUELLE="Oui",M_MUTUELLE,0)+IF(TOG_IK="Oui",M_IK,0)+IF(TOG_CADO="Oui",M_CADO,0)+IF(TOG_CASHBACK="Oui",M_CASHBACK,0)),0))*RDT_CASH)),(IF('2. Dashboard'!$F$6="A",INDEX('11. Arbitrage'!C:C,MATCH("TOTAL NET DIRIGEANT APRÈS FISCALITÉ (€)",'11. Arbitrage'!B:B,0)),IF('2. Dashboard'!$F$6="B",INDEX('11. Arbitrage'!D:D,MATCH("TOTAL NET DIRIGEANT APRÈS FISCALITÉ (€)",'11. Arbitrage'!B:B,0)),IF('2. Dashboard'!$F$6="C",INDEX('11. Arbitrage'!E:E,MATCH("TOTAL NET DIRIGEANT APRÈS FISCALITÉ (€)",'11. Arbitrage'!B:B,0)),INDEX('11. Arbitrage'!F:F,MATCH("TOTAL NET DIRIGEANT APRÈS FISCALITÉ (€)",'11. Arbitrage'!B:B,0))))))*5) | E68: =D68-C68
B69: Fraction capitalisable du gain (info) | C69: =IFERROR((IF(TOG_PARTICIPATION="Oui",M_PARTICIPATION,0)+IF(TOG_INTERESSEMENT="Oui",M_INTERESSEMENT,0)+IF(TOG_ABO_PEE="Oui",M_ABO_PEE,0)+IF(TOG_ABO_PER="Oui",M_ABO_PER,0)+IF(TOG_PERIN="Oui",M_PERIN,0))/(IF(TOG_PARTICIPATION="Oui",M_PARTICIPATION,0)+IF(TOG_INTERESSEMENT="Oui",M_INTERESSEMENT,0)+IF(TOG_ABO_PEE="Oui",M_ABO_PEE,0)+IF(TOG_ABO_PER="Oui",M_ABO_PER,0)+IF(TOG_PERIN="Oui",M_PERIN,0)+IF(TOG_TR="Oui",M_TR,0)+IF(TOG_CESU="Oui",M_CESU,0)+IF(TOG_AVANTAGES="Oui",M_AVANTAGES,0)+IF(TOG_MUTUELLE="Oui",M_MUTUELLE,0)+IF(TOG_IK="Oui",M_IK,0)+IF(TOG_CADO="Oui",M_CADO,0)+IF(TOG_CASHBACK="Oui",M_CASHBACK,0)),0) | D69: Calculé dynamiquement à partir des dispositifs activés en Profil §5.
B70: Hypothèse : capital placé en début d'année, capitalisation annuelle composée. Stratégie A : rendement cash défensif (RDT_CASH, ~2 %). Stratégie retenue : rendement épargne salariale & PER (RDT_EPARGNE, ~4 %). Hors fiscalité de sortie PER (différée, dépend du choix rente/capital).
B84: 📊 DÉCOMPOSITION DU GAIN vs STRATÉGIE A
B85: Étape | C85: Net dirigeant | D85: Contribution | E85: Cumul
B86: Stratégie A - référence salaire | C86: =INDEX('11. Arbitrage'!C:C,MATCH("TOTAL NET DIRIGEANT APRÈS FISCALITÉ (€)",'11. Arbitrage'!B:B,0)) | D86: - | E86: =C86-INDEX('11. Arbitrage'!C:C,MATCH("TOTAL NET DIRIGEANT APRÈS FISCALITÉ (€)",'11. Arbitrage'!B:B,0))
B87: + Dividendes optimisés (B) | C87: =INDEX('11. Arbitrage'!D:D,MATCH("TOTAL NET DIRIGEANT APRÈS FISCALITÉ (€)",'11. Arbitrage'!B:B,0)) | D87: =INDEX('11. Arbitrage'!D:D,MATCH("TOTAL NET DIRIGEANT APRÈS FISCALITÉ (€)",'11. Arbitrage'!B:B,0))-INDEX('11. Arbitrage'!C:C,MATCH("TOTAL NET DIRIGEANT APRÈS FISCALITÉ (€)",'11. Arbitrage'!B:B,0)) | E87: =C87-INDEX('11. Arbitrage'!C:C,MATCH("TOTAL NET DIRIGEANT APRÈS FISCALITÉ (€)",'11. Arbitrage'!B:B,0))
B88: + Épargne salariale & PER (C) | C88: =INDEX('11. Arbitrage'!E:E,MATCH("TOTAL NET DIRIGEANT APRÈS FISCALITÉ (€)",'11. Arbitrage'!B:B,0)) | D88: =INDEX('11. Arbitrage'!E:E,MATCH("TOTAL NET DIRIGEANT APRÈS FISCALITÉ (€)",'11. Arbitrage'!B:B,0))-INDEX('11. Arbitrage'!D:D,MATCH("TOTAL NET DIRIGEANT APRÈS FISCALITÉ (€)",'11. Arbitrage'!B:B,0)) | E88: =C88-INDEX('11. Arbitrage'!C:C,MATCH("TOTAL NET DIRIGEANT APRÈS FISCALITÉ (€)",'11. Arbitrage'!B:B,0))
B89: + Périphériques & cashback (D) | C89: =INDEX('11. Arbitrage'!F:F,MATCH("TOTAL NET DIRIGEANT APRÈS FISCALITÉ (€)",'11. Arbitrage'!B:B,0)) | D89: =INDEX('11. Arbitrage'!F:F,MATCH("TOTAL NET DIRIGEANT APRÈS FISCALITÉ (€)",'11. Arbitrage'!B:B,0))-INDEX('11. Arbitrage'!E:E,MATCH("TOTAL NET DIRIGEANT APRÈS FISCALITÉ (€)",'11. Arbitrage'!B:B,0)) | E89: =C89-INDEX('11. Arbitrage'!C:C,MATCH("TOTAL NET DIRIGEANT APRÈS FISCALITÉ (€)",'11. Arbitrage'!B:B,0))
B103: Document préparé par : | C103: =INDEX('5. Profil'!C:C,MATCH("Expert-comptable en charge",'5. Profil'!B:B,0))
B104: Cabinet : | C104: =INDEX('5. Profil'!C:C,MATCH("Cabinet",'5. Profil'!B:B,0))
B105: Date : | C105: =INDEX('5. Profil'!C:C,MATCH("Date de la simulation",'5. Profil'!B:B,0))
B107: 💼 PLACEMENT DU NET DIRIGEANT - COMPARAISON ENVELOPPES À 5 ANS
B108: Une fois la rémunération brute optimisée, où placer le net dirigeant disponible ? Comparaison de 4 enveloppes patrimoniales sur 5 ans, montant placé = 10 000 € (paramétrable).
B109: Montant placé (€) | C109: 10000
B110: Horizon (années) | C110: 5
B111: Rendement annuel brut hypothèse (%) | C111: 0.04
B113: Enveloppe | C113: Versement (€) | D113: Valeur brute (€) | E113: Fiscalité de sortie | F113: Net disponible (€)
B114: CTO - Compte-titres ordinaire | C114: =C109 | D114: =(C109*(1+C111)^C110) | E114: PFU 31,4 % sur les gains | F114: =C109+((C109*(1+C111)^C110)-C109)*(1-TX_PFU)
B115: PEA - après 5 ans | C115: =C109 | D115: =(C109*(1+C111)^C110) | E115: Exonération IR sur PV, prélèvements sociaux 17,2 % | F115: =IF(C110>=5,C109+((C109*(1+C111)^C110)-C109)*(1-0.172),C109+((C109*(1+C111)^C110)-C109)*(1-TX_PFU))
B116: Assurance-vie - après 8 ans | C116: =C109 | D116: =(C109*(1+C111)^C110) | E116: Abattement 4 600 € (célib) / 9 200 € (couple) + PFU réduit 7,5 % + PS 17,2 % | F116: =IF(C110>=8,C109+((C109*(1+C111)^C110)-C109)*(1-0.172)-MAX(0,((C109*(1+C111)^C110)-C109)-IF(SITUATION="Marié / pacsé",9200,4600))*0.075,C109+((C109*(1+C111)^C110)-C109)*(1-TX_PFU))
B117: PER individuel - sortie en capital | C117: =C109 | D117: =(C109*(1+C111)^C110) | E117: Déduction à l'entrée + IR barème sortie sur capital + PS 17,2 % sur gains | F117: =(C109*(1+C111)^C110)*(1-MAX(IFERROR(TX_IR_MOY_ASS,0.3),0.2))-((C109*(1+C111)^C110)-C109)*0.172
B119: Meilleure enveloppe selon hypothèses ci-dessus | C119: =INDEX(B114:B117,MATCH(MAX(F114:F117),F114:F117,0))
B121: 💡 Pour interpréter ce tableau :
B122: • Hypothèse simplificatrice : rendement constant identique pour les 4 enveloppes.
B123: • CTO subit une taxation annuelle implicite ; modélisé ici comme taxation finale, qui sur-estime le net (effet capitalisation).
B124: • Assurance-vie : l'abattement 4 600/9 200 € est annuel - étalé sur plusieurs sorties, l'avantage est cumulable.
B125: • PER : l'économie d'IR à l'entrée n'est PAS double-comptée - elle est censée avoir déjà été récupérée à l'année du versement.
B126: • Le choix dépend aussi de : succession (assurance-vie 152 500 € par bénéficiaire), liquidité, allocation cible.
B129: 📊 COMPOSITION DU NET DIRIGEANT PAR STRATÉGIE
B130: Composante | C130: Stratégie A | D130: Stratégie B | E130: Stratégie C | F130: Stratégie D
B131: Net salaire après IR | C131: =IFERROR(INDEX('11. Arbitrage'!C:C,MATCH("Net salaire après IR (€)",'11. Arbitrage'!B:B,0)),0) | D131: =IFERROR(INDEX('11. Arbitrage'!D:D,MATCH("Net salaire après IR (€)",'11. Arbitrage'!B:B,0)),0) | E131: =IFERROR(INDEX('11. Arbitrage'!E:E,MATCH("Net salaire après IR (€)",'11. Arbitrage'!B:B,0)),0) | F131: =IFERROR(INDEX('11. Arbitrage'!F:F,MATCH("Net salaire après IR (€)",'11. Arbitrage'!B:B,0)),0)
B132: Net dividendes | C132: =IFERROR(INDEX('11. Arbitrage'!C:C,MATCH("Net dividendes après IS, cotis. (TNS) et PFU/IR (€)",'11. Arbitrage'!B:B,0)),0) | D132: =IFERROR(INDEX('11. Arbitrage'!D:D,MATCH("Net dividendes après IS, cotis. (TNS) et PFU/IR (€)",'11. Arbitrage'!B:B,0)),0) | E132: =IFERROR(INDEX('11. Arbitrage'!E:E,MATCH("Net dividendes après IS, cotis. (TNS) et PFU/IR (€)",'11. Arbitrage'!B:B,0)),0) | F132: =IFERROR(INDEX('11. Arbitrage'!F:F,MATCH("Net dividendes après IS, cotis. (TNS) et PFU/IR (€)",'11. Arbitrage'!B:B,0)),0)
B133: Net épargne salariale | C133: =IFERROR(INDEX('11. Arbitrage'!C:C,MATCH("Net épargne salariale & PER (€)",'11. Arbitrage'!B:B,0)),0) | D133: =IFERROR(INDEX('11. Arbitrage'!D:D,MATCH("Net épargne salariale & PER (€)",'11. Arbitrage'!B:B,0)),0) | E133: =IFERROR(INDEX('11. Arbitrage'!E:E,MATCH("Net épargne salariale & PER (€)",'11. Arbitrage'!B:B,0)),0) | F133: =IFERROR(INDEX('11. Arbitrage'!F:F,MATCH("Net épargne salariale & PER (€)",'11. Arbitrage'!B:B,0)),0)
B134: Net périphériques | C134: =IFERROR(INDEX('11. Arbitrage'!C:C,MATCH("Net périphériques & cashback (€)",'11. Arbitrage'!B:B,0)),0) | D134: =IFERROR(INDEX('11. Arbitrage'!D:D,MATCH("Net périphériques & cashback (€)",'11. Arbitrage'!B:B,0)),0) | E134: =IFERROR(INDEX('11. Arbitrage'!E:E,MATCH("Net périphériques & cashback (€)",'11. Arbitrage'!B:B,0)),0) | F134: =IFERROR(INDEX('11. Arbitrage'!F:F,MATCH("Net périphériques & cashback (€)",'11. Arbitrage'!B:B,0)),0)
B135: TOTAL | C135: =SUM(C131:C134) | D135: =SUM(D131:D134) | E135: =SUM(E131:E134) | F135: =SUM(F131:F134)
B161: 🎯 PROFIL COMPARÉ DES 4 STRATÉGIES - RADAR 6 DIMENSIONS
B162: Dimension | C162: Strat. A | D162: Strat. B | E162: Strat. C | F162: Strat. D
B163: Net dirigeant immédiat | C163: =IFERROR(C135/MAX(C135:F135)*100,0) | D163: =IFERROR(D135/MAX(C135:F135)*100,0) | E163: =IFERROR(E135/MAX(C135:F135)*100,0) | F163: =IFERROR(F135/MAX(C135:F135)*100,0)
B164: Protection sociale | C164: =IFERROR(C131/C135*100,0) | D164: =IFERROR(D131/D135*100,0) | E164: =IFERROR(E131/E135*100,0) | F164: =IFERROR(F131/F135*100,0)
B165: Capitalisation 5 ans | C165: =IFERROR((C133+C132)/C135*100,0) | D165: =IFERROR((D133+D132)/D135*100,0) | E165: =IFERROR((E133+E132)/E135*100,0) | F165: =IFERROR((F133+F132)/F135*100,0)
B166: Robustesse fiscale | C166: =IFERROR(100-C132/C135*100,0) | D166: =IFERROR(100-D132/D135*100,0) | E166: =IFERROR(100-E132/E135*100,0) | F166: =IFERROR(100-F132/F135*100,0)
B167: Simplicité administrative | C167: 100 | D167: 70 | E167: 50 | F167: 30
...

Sheet Scénarios A vs B
A1: S. Comparateur 2 scénarios | H1: ↩ Retour sommaire
A2: Saisir deux jeux d'inputs côte à côte pour analyser un arbitrage, une sensibilité ou comparer deux dirigeants.
B4: 1. INPUTS DES DEUX SCÉNARIOS
B5: Paramètre | C5: Scénario A | D5: Scénario B | F5: Commentaire
B6: Libellé du scénario | C6: Enveloppe 100k | D6: Enveloppe 150k | F6: Ex : 'Dirigeant 1' / 'Dirigeant 2', 'Avant participation' / 'Après participation', 'Enveloppe 120k' / 'Enveloppe 150k'.
B7: Situation familiale | C7: Marié / pacsé | D7: Marié / pacsé
B8: Parts fiscales | C8: 2 | D8: 2
B9: Régime social | C9: Assimilé salarié | D9: Assimilé salarié
B10: Salaire brut annuel (€) | C10: 100000 | D10: 150000
B11: Dividendes bruts distribués (€) | C11: 10000 | D11: 10000
B12: Épargne salariale & PER (capitalisable, €) | C12: 5000 | D12: 5000 | F12: Total : Participation + Intéressement + Abondement PEE/PER coll + PER indiv.
B13: Périphériques consommés (TR/CESU/AN, €) | C13: 2000 | D13: 2000
B15: 2. RÉSULTATS PAR SCÉNARIO (modèle simplifié)
B16: Élément | C16: Scénario A | D16: Scénario B | E16: Écart | F16: Méthodologie
B17: Net salaire après cotisations | C17: =IF(C9="TNS",C10*(1-TX_TNS/(1+TX_TNS)),IF(C9="TNS (libéral)",C10*(1-TX_LIB/(1+TX_LIB)),C10*(1-TX_SALARIAL-ASSIETTE_CSG_SAL*TX_CSG_CRDS_ACT))) | D17: =IF(D9="TNS",D10*(1-TX_TNS/(1+TX_TNS)),IF(D9="TNS (libéral)",D10*(1-TX_LIB/(1+TX_LIB)),D10*(1-TX_SALARIAL-ASSIETTE_CSG_SAL*TX_CSG_CRDS_ACT))) | E17: =D17-C17 | F17: Brut × (1 − taux cotisations social moyen selon régime).
B18: Revenu imposable approximé | C18: =IF(C9="TNS",C10*(1-TX_TNS/(1+TX_TNS)),IF(C9="TNS (libéral)",C10*(1-TX_LIB/(1+TX_LIB)),C10*(1-TX_SALARIAL-ASSIETTE_CSG_SAL*TX_CSG_CRDS_ACT)))*0.9 | D18: =IF(D9="TNS",D10*(1-TX_TNS/(1+TX_TNS)),IF(D9="TNS (libéral)",D10*(1-TX_LIB/(1+TX_LIB)),D10*(1-TX_SALARIAL-ASSIETTE_CSG_SAL*TX_CSG_CRDS_ACT)))*0.9 | E18: =D18-C18 | F18: Net après cotis × 0,9 (abattement 10 % approximé sans plafond).
B19: IR au barème (sans plafonnement QF) | C19: =(C8)*(IF((C18/C8)<=IR_PLAFOND_T1,0,IF((C18/C8)<=IR_PLAFOND_T2,((C18/C8)-IR_PLAFOND_T1)*IR_TAUX_T2,IF((C18/C8)<=IR_PLAFOND_T3,(IR_PLAFOND_T2-IR_PLAFOND_T1)*IR_TAUX_T2+((C18/C8)-IR_PLAFOND_T2)*IR_TAUX_T3,IF((C18/C8)<=IR_PLAFOND_T4,(IR_PLAFOND_T2-IR_PLAFOND_T1)*IR_TAUX_T2+(IR_PLAFOND_T3-IR_PLAFOND_T2)*IR_TAUX_T3+((C18/C8)-IR_PLAFOND_T3)*IR_TAUX_T4,(IR_PLAFOND_T2-IR_PLAFOND_T1)*IR_TAUX_T2+(IR_PLAFOND_T3-IR_PLAFOND_T2)*IR_TAUX_T3+(IR_PLAFOND_T4-IR_PLAFOND_T3)*IR_TAUX_T4+((C18/C8)-IR_PLAFOND_T4)*IR_TAUX_T5))))) | D19: =(D8)*(IF((D18/D8)<=IR_PLAFOND_T1,0,IF((D18/D8)<=IR_PLAFOND_T2,((D18/D8)-IR_PLAFOND_T1)*IR_TAUX_T2,IF((D18/D8)<=IR_PLAFOND_T3,(IR_PLAFOND_T2-IR_PLAFOND_T1)*IR_TAUX_T2+((D18/D8)-IR_PLAFOND_T2)*IR_TAUX_T3,IF((D18/D8)<=IR_PLAFOND_T4,(IR_PLAFOND_T2-IR_PLAFOND_T1)*IR_TAUX_T2+(IR_PLAFOND_T3-IR_PLAFOND_T2)*IR_TAUX_T3+((D18/D8)-IR_PLAFOND_T3)*IR_TAUX_T4,(IR_PLAFOND_T2-IR_PLAFOND_T1)*IR_TAUX_T2+(IR_PLAFOND_T3-IR_PLAFOND_T2)*IR_TAUX_T3+(IR_PLAFOND_T4-IR_PLAFOND_T3)*IR_TAUX_T4+((D18/D8)-IR_PLAFOND_T4)*IR_TAUX_T5))))) | E19: =D19-C19 | F19: Barème 2026 indexé +0,9 %. Plafonnement QF non modélisé ici.
B20: Net salaire après IR | C20: =C17-C19 | D20: =D17-D19 | E20: =D20-C20 | F20: Net après cotis − IR foyer.
B21: Net dividendes (IS + PFU) | C21: =IF(C11>0,(C11-MIN(C11,IS_PLAF_REDUIT)*TX_IS_REDUIT-MAX(0,C11-IS_PLAF_REDUIT)*TX_IS_NORMAL)*(1-TX_PFU),0) | D21: =IF(D11>0,(D11-MIN(D11,IS_PLAF_REDUIT)*TX_IS_REDUIT-MAX(0,D11-IS_PLAF_REDUIT)*TX_IS_NORMAL)*(1-TX_PFU),0) | E21: =D21-C21 | F21: Bénéfice → IS 15 % jusqu'à 42 500 €, 25 % au-delà → distribution × (1 − PFU 31,4 %).
B22: Net épargne salariale & PER | C22: =C12/1.05*(1-TX_CSG_CRDS_ACT) | D22: =D12/1.05*(1-TX_CSG_CRDS_ACT) | E22: =D22-C22 | F22: Forfait social 5 % moyen + CSG/CRDS 9,7 %.
B23: Net périphériques (TR/CESU/AN) | C23: =C13*0.95 | D23: =D13*0.95 | E23: =D23-C23 | F23: Efficacité 95 % (peu de CSG/IR sur ces dispositifs).
B25: TOTAL NET DIRIGEANT | C25: =C20+C21+C22+C23 | D25: =D20+D21+D22+D23 | E25: =D25-C25
B26: Écart relatif (%) | E26: =IFERROR((D25-C25)/C25,0)
B27: Scénario gagnant | C27: =IF(D25>C25,"→ "&D6,IF(D25<C25,"← "&C6,"= équivalent"))
B29: 3. PROJECTION 5 ANS - PATRIMOINE CUMULÉ
B30: Année | C30: Scénario A | D30: Scénario B | E30: Écart
B31: Année 1 | C31: =IFERROR(C25*((1+(IFERROR(C12/(C12+C13),0)*RDT_EPARGNE+(1-IFERROR(C12/(C12+C13),0))*RDT_CASH))^1-1)/(IFERROR(C12/(C12+C13),0)*RDT_EPARGNE+(1-IFERROR(C12/(C12+C13),0))*RDT_CASH)*(1+(IFERROR(C12/(C12+C13),0)*RDT_EPARGNE+(1-IFERROR(C12/(C12+C13),0))*RDT_CASH)),C25*1) | D31: =IFERROR(D25*((1+(IFERROR(D12/(D12+D13),0)*RDT_EPARGNE+(1-IFERROR(D12/(D12+D13),0))*RDT_CASH))^1-1)/(IFERROR(D12/(D12+D13),0)*RDT_EPARGNE+(1-IFERROR(D12/(D12+D13),0))*RDT_CASH)*(1+(IFERROR(D12/(D12+D13),0)*RDT_EPARGNE+(1-IFERROR(D12/(D12+D13),0))*RDT_CASH)),D25*1) | E31: =D31-C31
B32: Année 2 | C32: =IFERROR(C25*((1+(IFERROR(C12/(C12+C13),0)*RDT_EPARGNE+(1-IFERROR(C12/(C12+C13),0))*RDT_CASH))^2-1)/(IFERROR(C12/(C12+C13),0)*RDT_EPARGNE+(1-IFERROR(C12/(C12+C13),0))*RDT_CASH)*(1+(IFERROR(C12/(C12+C13),0)*RDT_EPARGNE+(1-IFERROR(C12/(C12+C13),0))*RDT_CASH)),C25*2) | D32: =IFERROR(D25*((1+(IFERROR(D12/(D12+D13),0)*RDT_EPARGNE+(1-IFERROR(D12/(D12+D13),0))*RDT_CASH))^2-1)/(IFERROR(D12/(D12+D13),0)*RDT_EPARGNE+(1-IFERROR(D12/(D12+D13),0))*RDT_CASH)*(1+(IFERROR(D12/(D12+D13),0)*RDT_EPARGNE+(1-IFERROR(D12/(D12+D13),0))*RDT_CASH)),D25*2) | E32: =D32-C32
B33: Année 3 | C33: =IFERROR(C25*((1+(IFERROR(C12/(C12+C13),0)*RDT_EPARGNE+(1-IFERROR(C12/(C12+C13),0))*RDT_CASH))^3-1)/(IFERROR(C12/(C12+C13),0)*RDT_EPARGNE+(1-IFERROR(C12/(C12+C13),0))*RDT_CASH)*(1+(IFERROR(C12/(C12+C13),0)*RDT_EPARGNE+(1-IFERROR(C12/(C12+C13),0))*RDT_CASH)),C25*3) | D33: =IFERROR(D25*((1+(IFERROR(D12/(D12+D13),0)*RDT_EPARGNE+(1-IFERROR(D12/(D12+D13),0))*RDT_CASH))^3-1)/(IFERROR(D12/(D12+D13),0)*RDT_EPARGNE+(1-IFERROR(D12/(D12+D13),0))*RDT_CASH)*(1+(IFERROR(D12/(D12+D13),0)*RDT_EPARGNE+(1-IFERROR(D12/(D12+D13),0))*RDT_CASH)),D25*3) | E33: =D33-C33
B34: Année 4 | C34: =IFERROR(C25*((1+(IFERROR(C12/(C12+C13),0)*RDT_EPARGNE+(1-IFERROR(C12/(C12+C13),0))*RDT_CASH))^4-1)/(IFERROR(C12/(C12+C13),0)*RDT_EPARGNE+(1-IFERROR(C12/(C12+C13),0))*RDT_CASH)*(1+(IFERROR(C12/(C12+C13),0)*RDT_EPARGNE+(1-IFERROR(C12/(C12+C13),0))*RDT_CASH)),C25*4) | D34: =IFERROR(D25*((1+(IFERROR(D12/(D12+D13),0)*RDT_EPARGNE+(1-IFERROR(D12/(D12+D13),0))*RDT_CASH))^4-1)/(IFERROR(D12/(D12+D13),0)*RDT_EPARGNE+(1-IFERROR(D12/(D12+D13),0))*RDT_CASH)*(1+(IFERROR(D12/(D12+D13),0)*RDT_EPARGNE+(1-IFERROR(D12/(D12+D13),0))*RDT_CASH)),D25*4) | E34: =D34-C34
B35: Année 5 | C35: =IFERROR(C25*((1+(IFERROR(C12/(C12+C13),0)*RDT_EPARGNE+(1-IFERROR(C12/(C12+C13),0))*RDT_CASH))^5-1)/(IFERROR(C12/(C12+C13),0)*RDT_EPARGNE+(1-IFERROR(C12/(C12+C13),0))*RDT_CASH)*(1+(IFERROR(C12/(C12+C13),0)*RDT_EPARGNE+(1-IFERROR(C12/(C12+C13),0))*RDT_CASH)),C25*5) | D35: =IFERROR(D25*((1+(IFERROR(D12/(D12+D13),0)*RDT_EPARGNE+(1-IFERROR(D12/(D12+D13),0))*RDT_CASH))^5-1)/(IFERROR(D12/(D12+D13),0)*RDT_EPARGNE+(1-IFERROR(D12/(D12+D13),0))*RDT_CASH)*(1+(IFERROR(D12/(D12+D13),0)*RDT_EPARGNE+(1-IFERROR(D12/(D12+D13),0))*RDT_CASH)),D25*5) | E35: =D35-C35
B47: 4. INTERPRÉTATION & USAGE
B48: 💡 Cas d'usage typiques :
B49: • Couple à 2 dirigeants : Scénario A = dirigeant principal, B = conjoint dirigeant.
B50: • Sensibilité enveloppe : A = enveloppe basse, B = enveloppe haute → mesurer l'effet marginal.
B51: • Avant/après dispositif : A = sans participation, B = avec participation 8 000 €.
B52: • Comparaison régime : A = Assimilé salarié, B = TNS → coût social vs IR.
B54: ⚠ Précisions méthodologiques :
B55: • Modèle simplifié autonome - pas de CEHR/CDHR/QF plafonné (vs modules détaillés).
B56: • Convient pour cadrage stratégique ; pour chiffrage déclaratif, repasser par les modules 7-10.
B57: • IR au barème pur, plafonnement QF négligé (impact < 2 % pour les revenus < 200k).
A60: Outil indicatif à usage professionnel - ne se substitue pas à un conseil personnalisé. Paramètres fiscaux à mettre à jour annuellement (cf. feuille « 13. Sources »).

Sheet Détail calcul fiscal
A1: 📚. Détail du calcul fiscal - pédagogie | H1: ↩ Retour sommaire
A2: Décomposition complète du calcul d'impôt sur le revenu, tranche par tranche, pour le cas saisi en Profil. Permet à l'expert-comptable d'expliquer chaque ligne au client.
B4: 📋 CAS EN COURS (lien Profil)
B5: Situation familiale | C5: =SITUATION
B6: Parts fiscales | C6: =PARTS
B7: Situation particulière | C7: =IFERROR(SITUATION_PART,"Aucune (cas général)")
B8: Régime social | C8: =REGIME_SOCIAL
B9: Autres revenus du foyer | C9: =AUTRES_REV
B10: Dividendes foyer (au PFU) | C10: =DIVIDENDES_FOYER
B11: Rémunération brute annuelle (module actif) | C11: =IFERROR(INDEX(INDIRECT("'"&IF(REGIME_SOCIAL="TNS","8. TNS",IF(REGIME_SOCIAL="TNS (libéral)","9. Libéral",IF(REGIME_SOCIAL="Salarié","10. Salarié","7. Assimilé salarié")))&"'!C:C"),MATCH("Rémunération brute annuelle (€)",INDIRECT("'"&IF(REGIME_SOCIAL="TNS","8. TNS",IF(REGIME_SOCIAL="TNS (libéral)","9. Libéral",IF(REGIME_SOCIAL="Salarié","10. Salarié","7. Assimilé salarié")))&"'!B:B"),0)),IFERROR(INDEX(INDIRECT("'"&IF(REGIME_SOCIAL="TNS","8. TNS",IF(REGIME_SOCIAL="TNS (libéral)","9. Libéral",IF(REGIME_SOCIAL="Salarié","10. Salarié","7. Assimilé salarié")))&"'!C:C"),MATCH("Salaire brut annuel (€)",INDIRECT("'"&IF(REGIME_SOCIAL="TNS","8. TNS",IF(REGIME_SOCIAL="TNS (libéral)","9. Libéral",IF(REGIME_SOCIAL="Salarié","10. Salarié","7. Assimilé salarié")))&"'!B:B"),0)),0))
B13: 1. PASSAGE BRUT → NET IMPOSABLE
B14: Élément | C14: Montant (€) | D14: Taux | H14: Explication
B15: Brut (rémunération annuelle) | C15: =C11 | H15: Saisi en Profil §1 ou dans le module actif.
B16: (–) Cotisations sociales | C16: =-C15*IF(REGIME_SOCIAL="TNS",TX_TNS/(1+TX_TNS),IF(REGIME_SOCIAL="TNS (libéral)",TX_LIB/(1+TX_LIB),TX_SALARIAL+ASSIETTE_CSG_SAL*TX_CSG_CRDS_ACT)) | D16: =IF(REGIME_SOCIAL="TNS",TX_TNS/(1+TX_TNS),IF(REGIME_SOCIAL="TNS (libéral)",TX_LIB/(1+TX_LIB),TX_SALARIAL+ASSIETTE_CSG_SAL*TX_CSG_CRDS_ACT)) | H16: Assimilé salarié : ~22 % (URSSAF, retraite ARRCO/AGIRC, prévoyance, chômage cadre). TNS : ~45 % du revenu net (assiette différente). Libéral : ~45 % (caisses CIPAV/CARMF/CARCDSF…).
B17: → Net après cotisations sociales | C17: =C15+C16
B18: (+) CSG non déductible + CRDS réintégrée (assimilé/salarié) | C18: =IF(OR(REGIME_SOCIAL="Assimilé salarié",REGIME_SOCIAL="Salarié",REGIME_SOCIAL="Assimilé salarié (libéral)"),C15*ASSIETTE_CSG_SAL*(0.024+0.005),0) | H18: Pour les salariés et assimilés salariés : la CSG non déductible (2,4 %) et la CRDS (0,5 %) sont réintégrées au revenu imposable (CGI art. 1417). Pour les TNS, ces prélèvements n'existent pas sous cette forme.
B19: → Revenu salarial imposable | C19: =C17+C18
B20: (–) Abattement 10 % (frais professionnels, plafonné 14 426 €) | C20: =-MIN(C19*0.1,14426) | D20: 10 % | H20: Abattement forfaitaire pour frais professionnels. Plafonné à 14 426 € en 2026 (LF 2026 art. 4). Option pour les frais réels si > 10 % (cas chauffeurs longs trajets, etc.).
B21: → Revenu imposable (catégorie traitements et salaires) | C21: =C19+C20
B22: (+) Autres revenus du foyer | C22: =AUTRES_REV | H22: Saisis en Profil §3 - typiquement conjoint, BIC, BNC complémentaire.
B23: → Revenu net imposable global du foyer | C23: =C21+C22
B25: 2. IR TRANCHE PAR TRANCHE (barème 2026, revenus 2025)
B26: Quotient familial (revenu / parts) = revenu net imposable / nombre de parts
B27: Quotient familial (par part) | C27: =C23/PARTS
B29: Tranche | C29: Borne basse (€) | D29: Borne haute (€) | E29: Taux | F29: Montant dans tranche (€) | G29: IR de la tranche (€)
B30: Tranche 1 - non imposable | C30: 0 | D30: =IR_PLAFOND_T1 | E30: 0 | F30: =MAX(0,MIN(C27,(IR_PLAFOND_T1))-0) | G30: =F30*E30
B31: Tranche 2 - 11 % | C31: =IR_PLAFOND_T1 | D31: =IR_PLAFOND_T2 | E31: =IR_TAUX_T2 | F31: =MAX(0,MIN(C27,(IR_PLAFOND_T2))-(IR_PLAFOND_T1)) | G31: =F31*E31
B32: Tranche 3 - 30 % | C32: =IR_PLAFOND_T2 | D32: =IR_PLAFOND_T3 | E32: =IR_TAUX_T3 | F32: =MAX(0,MIN(C27,(IR_PLAFOND_T3))-(IR_PLAFOND_T2)) | G32: =F32*E32
B33: Tranche 4 - 41 % | C33: =IR_PLAFOND_T3 | D33: =IR_PLAFOND_T4 | E33: =IR_TAUX_T4 | F33: =MAX(0,MIN(C27,(IR_PLAFOND_T4))-(IR_PLAFOND_T3)) | G33: =F33*E33
B34: Tranche 5 - 45 % | C34: =IR_PLAFOND_T4 | D34: ∞ | E34: =IR_TAUX_T5 | F34: =MAX(0,MIN(C27,(99999999))-(IR_PLAFOND_T4)) | G34: =F34*E34
B35: IR par part fiscale (somme tranches) | G35: =SUM(G30:G34)
B36: IR foyer brut (× nb de parts) | G36: =G35*PARTS
B58: 3. QUOTIENT FAMILIAL - AVANTAGE & PLAFONNEMENT
B59: IR théorique SANS quotient familial (parts de base) | C59: =(IF((C23/(IF(SITUATION="Marié / pacsé",2,1)))<=IR_PLAFOND_T1,0,IF((C23/(IF(SITUATION="Marié / pacsé",2,1)))<=IR_PLAFOND_T2,((C23/(IF(SITUATION="Marié / pacsé",2,1)))-IR_PLAFOND_T1)*IR_TAUX_T2,IF((C23/(IF(SITUATION="Marié / pacsé",2,1)))<=IR_PLAFOND_T3,(IR_PLAFOND_T2-IR_PLAFOND_T1)*IR_TAUX_T2+((C23/(IF(SITUATION="Marié / pacsé",2,1)))-IR_PLAFOND_T2)*IR_TAUX_T3,IF((C23/(IF(SITUATION="Marié / pacsé",2,1)))<=IR_PLAFOND_T4,(IR_PLAFOND_T2-IR_PLAFOND_T1)*IR_TAUX_T2+(IR_PLAFOND_T3-IR_PLAFOND_T2)*IR_TAUX_T3+((C23/(IF(SITUATION="Marié / pacsé",2,1)))-IR_PLAFOND_T3)*IR_TAUX_T4,(IR_PLAFOND_T2-IR_PLAFOND_T1)*IR_TAUX_T2+(IR_PLAFOND_T3-IR_PLAFOND_T2)*IR_TAUX_T3+(IR_PLAFOND_T4-IR_PLAFOND_T3)*IR_TAUX_T4+((C23/(IF(SITUATION="Marié / pacsé",2,1)))-IR_PLAFOND_T4)*IR_TAUX_T5)))))*(IF(SITUATION="Marié / pacsé",2,1)) | H59: Calcul IR avec parts = {1 célibataire, 2 marié}, ignorant les enfants.
B60: IR théorique AVEC quotient familial (toutes les parts) | C60: =G36 | H60: Calcul avec toutes les parts du foyer (incluant enfants).
B61: Économie brute du QF (avant plafonnement) | C61: =C59-C60
B62: Plafond de l'avantage QF (selon situation particulière) | C62: =IFERROR(IF(SITUATION_PART="Parent isolé (case T)",IF((PARTS-(IF(SITUATION="Marié / pacsé",2,1)))*2>=1,PLAF_QF_PARENT_ISOLE+MAX(0,(PARTS-(IF(SITUATION="Marié / pacsé",2,1)))*2-1)*PLAF_QF_DEMI_PART,0),IF(SITUATION_PART="Personne seule ayant élevé un enfant ≥ 5 ans (case L)",IF((PARTS-(IF(SITUATION="Marié / pacsé",2,1)))*2>=1,PLAF_QF_PERS_SEULE_L+MAX(0,(PARTS-(IF(SITUATION="Marié / pacsé",2,1)))*2-1)*PLAF_QF_DEMI_PART,0),IF(SITUATION_PART="Veuf avec enfants à charge",IF((PARTS-(IF(SITUATION="Marié / pacsé",2,1)))*2>=1,PLAF_QF_VEUF+MAX(0,(PARTS-(IF(SITUATION="Marié / pacsé",2,1)))*2-1)*PLAF_QF_DEMI_PART,0),IF(SITUATION_PART="Ancien combattant > 74 ans ou invalide",IF((PARTS-(IF(SITUATION="Marié / pacsé",2,1)))*2>=1,PLAF_QF_INVALIDE+MAX(0,(PARTS-(IF(SITUATION="Marié / pacsé",2,1)))*2-1)*PLAF_QF_DEMI_PART,0),PLAF_QF_DEMI_PART*(PARTS-(IF(SITUATION="Marié / pacsé",2,1)))*2)))),PLAF_QF_DEMI_PART*(PARTS-(IF(SITUATION="Marié / pacsé",2,1)))*2) | H62: Cas général : 1 807 € par demi-part excédentaire. Parent isolé : 4 262 € sur la 1ère demi-part + 1 807 € au-delà. Veuf avec enfants : 5 625 € + 1 807 € au-delà. Invalide / ancien combattant : 3 608 € + 1 807 € au-delà.
B63: Perte d'avantage (excédent réintégré à l'IR) | C63: =MAX(0,C61-C62)
B64: → IR foyer après plafonnement QF | C64: =C60+C63
B66: 4. CEHR - CONTRIBUTION EXCEPTIONNELLE HAUTS REVENUS
B67: RFR de référence (revenu net imposable + dividendes au PFU) | C67: =C23+DIVIDENDES_FOYER
B68: Tranche CEHR | C68: Seuil bas (€) | D68: Seuil haut (€) | E68: Taux | F68: CEHR (€)
B69: Tranche 3 % | C69: =IF(SITUATION="Marié / pacsé",CEHR_SEUIL_M1,CEHR_SEUIL_C1) | D69: =IF(SITUATION="Marié / pacsé",CEHR_SEUIL_M2,CEHR_SEUIL_C2) | E69: =CEHR_TX_1 | F69: =MAX(0,MIN(C67,IF(SITUATION="Marié / pacsé",CEHR_SEUIL_M2,CEHR_SEUIL_C2))-IF(SITUATION="Marié / pacsé",CEHR_SEUIL_M1,CEHR_SEUIL_C1))*CEHR_TX_1
B70: Tranche 4 % | C70: =IF(SITUATION="Marié / pacsé",CEHR_SEUIL_M2,CEHR_SEUIL_C2) | D70: ∞ | E70: =CEHR_TX_2 | F70: =MAX(0,C67-IF(SITUATION="Marié / pacsé",CEHR_SEUIL_M2,CEHR_SEUIL_C2))*CEHR_TX_2
B71: CEHR totale | F71: =SUM(F69:F70)
B73: 5. CDHR - CONTRIBUTION DIFFÉRENTIELLE HAUTS REVENUS (LF 2026)
B74: IR au PFU sur les dividendes (12,8 %) | C74: =DIVIDENDES_FOYER*0.128 | H74: Part IR du PFU 31,4 % (le reste = 18,6 % prélèvements sociaux). S'ajoute à l'IR foyer pour le calcul du dénominateur de la CDHR.
B75: Imposition effective totale (IR foyer + CEHR + IR PFU) | C75: =C64+F71+C74
B76: Plancher 20 % du RFR (imposition minimum) | C76: =C67*CDHR_TAUX_PLANCHER
B77: CDHR théorique (avant lissage) = MAX(0, plancher – imposition) | C77: =MAX(0,C76-C75)
B78: Ratio de lissage (zone 250-330k célib / 500-660k marié) | C78: =IF(C67<=IF(SITUATION="Marié / pacsé",CDHR_SEUIL_M,CDHR_SEUIL_C),0,MIN(1,MAX(0,(C67-IF(SITUATION="Marié / pacsé",CDHR_SEUIL_M,CDHR_SEUIL_C))/(IF(SITUATION="Marié / pacsé",CDHR_SEUIL_M_HAUT,CDHR_SEUIL_C_HAUT)-IF(SITUATION="Marié / pacsé",CDHR_SEUIL_M,CDHR_SEUIL_C)))))
B79: CDHR finale (théorique × ratio lissage) | C79: =C77*C78
B81: 6. RÉCAP IMPOSITION TOTALE DU FOYER
B82: IR foyer (après plafonnement QF) | C82: =C64
B83: (+) CEHR | C83: =F71
B84: (+) CDHR | C84: =C79
B85: (+) IR sur dividendes PFU | C85: =C74
B86: → IMPOSITION TOTALE FOYER | C86: =SUM(C82:C85)
B87: Taux moyen effectif d'imposition (impôt / RFR) | C87: =IFERROR(C86/C67,0)
B89: 💡 Comment lire cette feuille :
B90: • Toutes les valeurs réagissent automatiquement aux changements en Profil §1-3.
B91: • Section 2 : la pyramide visualise quelle tranche du barème porte le plus de poids.
B92: • Section 3 : si la « perte d'avantage QF » est non nulle, le QF est plafonné - l'avantage des enfants est limité.
B93: • Section 5 : si la CDHR est positive, vous êtes dans la zone des hauts revenus ; le ratio de lissage évite l'effet de seuil brutal.
B94: • Le taux moyen effectif d'imposition est l'indicateur clé à communiquer au client : « votre foyer est imposé à X % en moyenne ».
A97: Outil indicatif à usage professionnel - ne se substitue pas à un conseil personnalisé. Paramètres fiscaux à mettre à jour annuellement (cf. feuille « 13. Sources »).

Sheet 13. Sources
A1: 13. Sources & disclaimer | H1: ↩ Retour sommaire
A2: Références légales et limites du modèle.
B4: SOURCES LÉGALES PAR PARAMÈTRE
B5: PASS 2026 (48 060 €) | C5: Arrêté du 22/12/2025 - JORF du 23/12/2025
B6: Barème IR 2026 (revenus 2025) | C6: CGI art. 197 - LF 2026 art. 4 (revalorisation +0,9 %)
B7: Plafonnement quotient familial | C7: CGI art. 197, I-2° (1 807 €/demi-part 2026)
B8: CSG/CRDS sur revenus d'activité | C8: CSS art. L.136-2 et L.136-8 ; ordonnance n°96-50 du 24/01/1996
B9: Abattement 1,75 % CSG/CRDS (≤ 4 PASS) | C9: CSS art. L.136-2
B10: PFU dividendes (12,8 % + 17,2 %) | C10: CGI art. 200 A
B11: Abattement 40 % dividendes (option barème) | C11: CGI art. 158, 3-2°
B12: Cotisations TNS sur dividendes > 10 % | C12: CSS art. L.131-6, 3°
B13: Régime fiscal SEL - dividendes | C13: BOI-RPPM-RCM-10-20-20-20
B14: IS - taux réduit 15 % PME | C14: CGI art. 219, I-b (CA < 10 M€, capital ≥ 75 % personnes physiques)
B15: Forfait social - exonération PACTE | C15: CSS art. L.137-15 et L.137-16 - loi PACTE n°2019-486
B16: Participation - plafond individuel | C16: C. trav. art. L.3324-5 (75 % PASS)
... B27: Abattement 10 % salariés | C27: CGI art. 83 (plancher 504 €, plafond 14 426 €)
B29: HYPOTHÈSES SIMPLIFICATRICES DU MODÈLE
B30: Cotisations sociales | C30: Taux moyens (42 % patronales / 12 % salariales / 45 % TNS / 45 % libéral). Les taux réels varient selon T1/T2, conventions, code APE, profession et niveau de revenu. L'expert-comptable affine selon la fiche de paie réelle ou la déclaration 2042-C-PRO.
B31: Épargne salariale | C31: Hypothèse de placement ≥ 5 ans en PEE/PERECO → exonération d'IR à la sortie en capital. Versement direct (rare en pratique) entraîne fiscalisation IR au barème.
B32: PER individuel | C32: Économie IR matérialisée immédiatement au TMI estimé. La fiscalité de sortie (rente / capital) est différée et non modélisée. Différentiel de TMI activité/retraite généralement favorable.
B33: Dividendes - TNS | C33: La fraction des dividendes excédant 10 % du capital social + primes d'émission + comptes courants d'associés est soumise à cotisations TNS (gérant majoritaire SARL / associé EURL / SELARL). À paramétrer au cas par cas.
B34: Quotient familial | C34: Le plafonnement du quotient familial (1 807 €/demi-part 2026, hors cas spécifiques) n'est pas modélisé - à vérifier manuellement si le foyer dispose de plus de 2 parts.
B35: Décote, CIMR, CEHR | C35: Les mécanismes de décote IR, contribution exceptionnelle sur les hauts revenus (CEHR) et plafond IFI ne sont pas modélisés. À vérifier sur les dossiers à fort revenu.
B36: Dispositifs non modélisés | C36: Stock-options, AGA, BSPCE, plus-values de cession de titres, intérêts CC associé, indemnités de cessation, pacte Dutreil - non modélisés.
B37: Périmètre géographique | C37: Modèle calibré pour le régime fiscal et social français de droit commun. Non applicable aux non-résidents, expatriés, travailleurs frontaliers, DOM-TOM (régimes spécifiques).
B39: 💸 NOTE TECHNIQUE - CASHBACK
B40: Le cashback est traité dans cet outil comme un flux externe au lien de subordination employeur/salarié - c'est-à-dire un pouvoir d'achat net obtenu via un programme partenaire (souscription individuelle ou collective) et non un complément de rémunération chargé. Cette qualification est juridiquement défendue mais elle n'est ni garantie par un texte fiscal exprès, ni opposable de droit à l'URSSAF. Risques identifiés : 1. Requalification en avantage en nature (CSS art. L.242-1) si le cabinet est l'instigateur direct du programme et que les bénéficiaires sont les salariés / dirigeants. Conséquence : assujettissement aux cotisations sociales et IR. 2. Requalification en complément de salaire si le programme constitue un usage habituel et systématique de l'entreprise (jurisprudence Cass. soc. sur usage d'entreprise). 3. Risque de redressement URSSAF avec rappel de cotisations sur 3 ans + majorations (jusqu'à 25 %). Recommandations : • Souscription du programme au nom du bénéficiaire personnel, hors lien employeur, et financement neutre côté société (paiement de l'abonnement par le salarié, remboursé via une enveloppe non chargée comme un titre-cadeau dans la limite de la tolérance ACOSS). • Documenter formellement la nature externe et facultative du programme. • Limiter les montants en deçà de seuils significatifs (typiquement < 5 % de la rémunération). • Faire valider le montage par un avocat fiscaliste ou un cabinet spécialisé URSSAF avant déploiement. À ce titre, le cashback est positionné en niveau de risque « 🔴 Optimisé » dans le tableau de bord - il s'agit d'une optimisation à fort potentiel d'efficacité fiscale-sociale (≈100 % du brut conservé) mais à sécurisation juridique encore non stabilisée.
B64: NOTE TECHNIQUE - CDHR (Contribution Différentielle Hauts Revenus, art. 224 CGI)
B65: Cadre légal - La CDHR a été instaurée par la loi de finances pour 2025 (art. 10) puis pérennisée par la loi de finances pour 2026 (art. 2), jusqu'à ce que le déficit public repasse sous 3 % du PIB. Elle garantit une imposition minimale de 20 % du revenu fiscal de référence pour les foyers dont le RFR dépasse 250 000 € (célibataire) ou 500 000 € (couple). Le mécanisme : si (IR + CEHR + prélèvements libératoires) / RFR < 20 %, le foyer paie la différence pour atteindre 20 %. Approche retenue dans l'outil - Le calcul est intégré aux 4 modules par population avec une formule simplifiée : CDHR = MAX(0, 20 % × RFR − (IR + CEHR)) dès lors que le RFR dépasse le seuil. Trois simplifications sont assumées par rapport au texte légal complet : 1. Pas de lissage entre 250-330 k€ (célib) / 500-660 k€ (marié). Conséquence : effet de seuil plus brutal dans l'outil que dans la réalité, mais sécurise un cadrage conservateur. 2. Pas de retraitement des revenus exceptionnels au 1/4 (CGI art. 224 prévoit que les revenus exceptionnels comptent pour le quart de leur montant dans le RFR retraité). 3. RFR approximé par le revenu net imposable foyer + autres revenus. En réalité le RFR contient aussi les revenus au PFU (dividendes, plus-values), exonérations diverses et abattements spécifiques. Limite d'usage - Pour les dirigeants rémunérés à 100 % en salaire, l'IR au barème progressif dépasse vite 20 % du RFR, donc la CDHR mord rarement. Là où elle mord vraiment, c'est sur les profils à dividendes importants au PFU (taux moyen plus faible) - situation gérée plus finement dans la feuille Arbitrage qui combine salaire + dividendes. Pour un chiffrage déclaratif final sur un dossier haut revenu, utiliser le simulateur officiel impots.gouv.fr.
B82: ⚖ NOTE TECHNIQUE - SOCIÉTÉS D'EXERCICE LIBÉRAL (SEL, SELARL, SELAS, SCP)
B83: Cadre - Les SEL permettent aux professions libérales réglementées (avocats, médecins, dentistes, experts-comptables, vétérinaires, kinésithérapeutes…) d'exercer en société à l'IS. Le statut social et fiscal des associés diffère selon la forme : • SELARL / SCP → associé gérant majoritaire = TNS (libéral). Régime CIPAV, CARMF, CARCDSF, CNBF selon la profession. Imposition à l'IR en BNC pour la part rémunération. • SELAS / SELAFA → associés actifs = assimilés salariés (régime général SS). Imposition à l'IR en traitements et salaires. Régime ARRCO-AGIRC pour la retraite complémentaire. Points spécifiques modélisés : • Cotisations TNS sur dividendes > 10 % capital social : appliquées aux SELARL/SCP en gérance majoritaire (jurisprudence Cass. soc. 23 oct. 2014 et confirmation 2018), via la même logique que les SARL gérance majoritaire. Cf. Profil §2 « Capital social + primes + CCA ». • SELAS : pas de requalification dividendes (régime PFU intégral, comme assimilé salarié). Points NON modélisés (à traiter au cas par cas) : • Caisse de retraite spécifique selon profession (CIPAV pour BNC non réglementé, CARMF pour médecins libéraux, etc.) - l'outil utilise le taux moyen TNS libéral de 45 %. • Frais professionnels réels en SEL TNS (déduction du BNC vs abattement 10 % salarié). • Cotisations CNBF spécifiques avocats (taux dégressif, plafonds particuliers). • Régime fiscal de la cession ou liquidation de parts SEL. Pour un dossier SEL complexe, repasser par le module « 9. Libéral » et compléter manuellement avec les paramètres caisse spécifique.
B103: GLOSSAIRE DES SIGLES
B104: AN | C104: Avantage en Nature (véhicule, logement, NTIC, etc.) - évalué au forfait ou au réel.
B105: BIC | C105: Bénéfices Industriels et Commerciaux - catégorie fiscale des artisans, commerçants, industriels.
B106: BNC | C106: Bénéfices Non Commerciaux - catégorie fiscale des professions libérales et titulaires de charges/offices.
B107: CARCDSF | C107: Caisse Autonome de Retraite des Chirurgiens-Dentistes et des Sages-Femmes.
B108: CARMF | C108: Caisse Autonome de Retraite des Médecins de France.
B109: CARPIMKO | C109: Caisse de retraite des Infirmiers, Masseurs-Kinésithérapeutes, Pédicures-Podologues, Orthophonistes et Orthoptistes.
B110: CARPV | C110: Caisse Autonome de Retraite et de Prévoyance des Vétérinaires.
B111: CDHR | C111: Contribution Différentielle sur les Hauts Revenus - CGI art. 224. Instaurée par LF 2025, pérennisée par LF 2026. Garantit un plancher de 20 % d'imposition effective sur RFR > 250 k€ (célib) ou 500 k€ (marié).
B112: CEHR | C112: Contribution Exceptionnelle sur les Hauts Revenus - CGI art. 223 sexies. 3 % à 4 % au-delà de 250/500 k€ (célib./marié).
B113: CESU | C113: Chèque Emploi Service Universel préfinancé - exo charges/IR jusqu'à 2 540 €/an/salarié.
B114: CFA | C114: Contribution Financière pour l'Autonomie - créée par LFSS 2026, intégrée à la CSG (+1,4 pt sur revenus du capital, portant la CSG à 10,6 %).
B115: CIMR | C115: Crédit d'Impôt pour la Modernisation du Recouvrement - mécanisme de transition lors du passage au prélèvement à la source en 2019.
... B141: URSSAF | C141: Union de Recouvrement des cotisations de Sécurité Sociale et d'Allocations Familiales - collecte les cotisations sociales.
B143: DISCLAIMER JURIDIQUE
B144: 1. Le présent outil constitue une aide à la simulation et au cadrage stratégique, à usage exclusif des professionnels du chiffre et du droit (experts-comptables, avocats fiscalistes, conseils en gestion de patrimoine). 2. Il ne saurait se substituer à un conseil personnalisé délivré après examen complet de la situation individuelle du client (situation patrimoniale, familiale, projets de cession ou de transmission, etc.). 3. Les calculs reposent sur le référentiel fiscal et social 2025 (revenus 2024) en vigueur à la date de mise à jour de la feuille « 4. Paramètres ». Toute évolution législative ou réglementaire postérieure doit faire l'objet d'une mise à jour. 4. Les hypothèses simplificatrices détaillées ci-dessus peuvent conduire à des écarts avec les calculs définitifs réalisés par le cabinet. Les chiffres produits par cet outil sont indicatifs et ne valent pas engagement. 5. Le cabinet utilisateur conserve l'entière responsabilité du conseil délivré au client final, ainsi que de la mise à jour annuelle des paramètres et des éventuels ajustements liés aux spécificités du dossier. 6. La présente version (v1.0) est un outil de cabinet sous licence - toute reproduction, diffusion ou commercialisation à des tiers non autorisés est interdite.

Sheet Tests
A1: Tests régressifs intégrés - feuille de validation
A2: Cas-tests calibrés sur le barème IR 2026 (revenus 2025), plafonds 2026 (PASS 48 060 €, QF 1 807 €), CEHR/CDHR pérennisées LF 2026. Si un cas-test passe au ✗, cela indique qu'une modification a cassé une formule.
A4: Indicateur global | B4: =IF(COUNTIF(H8:H80,"✗")=0,"✅ Tous les cas-tests passent ("&COUNTIF(H8:H80,"✓")&" verts / "&COUNTIF(H8:H80,"✗")&" rouges)","🔴 "&COUNTIF(H8:H80,"✗")&" test(s) en échec sur "&(COUNTIF(H8:H80,"✓")+COUNTIF(H8:H80,"✗"))&" total")
A7: N° | B7: Description | C7: Situation | D7: Parts | E7: Rev. imp. (€) | F7: Attendu (€) | G7: Calculé (€) | H7: Statut
A8: T1 | B8: Célib 1p, 30k → IR ≈ 2 104 € (cf. simu officielle) | C8: Célibataire / divorcé / veuf | D8: 1 | E8: 30000 | F8: 2104 | G8: =ROUND((IF(E8/D8<=IR_PLAFOND_T1,0,IF(E8/D8<=IR_PLAFOND_T2,(E8/D8-IR_PLAFOND_T1)*IR_TAUX_T2,IF(E8/D8<=IR_PLAFOND_T3,(IR_PLAFOND_T2-IR_PLAFOND_T1)*IR_TAUX_T2+(E8/D8-IR_PLAFOND_T2)*IR_TAUX_T3,IF(E8/D8<=IR_PLAFOND_T4,(IR_PLAFOND_T2-IR_PLAFOND_T1)*IR_TAUX_T2+(IR_PLAFOND_T3-IR_PLAFOND_T2)*IR_TAUX_T3+(E8/D8-IR_PLAFOND_T3)*IR_TAUX_T4,(IR_PLAFOND_T2-IR_PLAFOND_T1)*IR_TAUX_T2+(IR_PLAFOND_T3-IR_PLAFOND_T2)*IR_TAUX_T3+(IR_PLAFOND_T4-IR_PLAFOND_T3)*IR_TAUX_T4+(E8/D8-IR_PLAFOND_T4)*IR_TAUX_T5)))))*D8,0) | H8: =IF(ABS(F8-G8)<=5,"✓","✗")
A9: T2 | B9: Marié 2p, 60k → IR ≈ 4 208 € (cf. simu officielle) | C9: Marié / pacsé | D9: 2 | E9: 60000 | F9: 4208 | G9: =ROUND((IF(E9/D9<=IR_PLAFOND_T1,0,IF(E9/D9<=IR_PLAFOND_T2,(E9/D9-IR_PLAFOND_T1)*IR_TAUX_T2,IF(E9/D9<=IR_PLAFOND_T3,(IR_PLAFOND_T2-IR_PLAFOND_T1)*IR_TAUX_T2+(E9/D9-IR_PLAFOND_T2)*IR_TAUX_T3,IF(E9/D9<=IR_PLAFOND_T4,(IR_PLAFOND_T2-IR_PLAFOND_T1)*IR_TAUX_T2+(IR_PLAFOND_T3-IR_PLAFOND_T2)*IR_TAUX_T3+(E9/D9-IR_PLAFOND_T3)*IR_TAUX_T4,(IR_PLAFOND_T2-IR_PLAFOND_T1)*IR_TAUX_T2+(IR_PLAFOND_T3-IR_PLAFOND_T2)*IR_TAUX_T3+(IR_PLAFOND_T4-IR_PLAFOND_T3)*IR_TAUX_T4+(E9/D9-IR_PLAFOND_T4)*IR_TAUX_T5)))))*D9,0) | H9: =IF(ABS(F9-G9)<=5,"✓","✗")
A10: T3 | B10: Marié 2p, 80k → IR ≈ 10 208 € | C10: Marié / pacsé | D10: 2 | E10: 80000 | F10: 10208 | G10: =ROUND((IF(E10/D10<=IR_PLAFOND_T1,0,IF(E10/D10<=IR_PLAFOND_T2,(E10/D10-IR_PLAFOND_T1)*IR_TAUX_T2,IF(E10/D10<=IR_PLAFOND_T3,(IR_PLAFOND_T2-IR_PLAFOND_T1)*IR_TAUX_T2+(E10/D10-IR_PLAFOND_T2)*IR_TAUX_T3,IF(E10/D10<=IR_PLAFOND_T4,(IR_PLAFOND_T2-IR_PLAFOND_T1)*IR_TAUX_T2+(IR_PLAFOND_T3-IR_PLAFOND_T2)*IR_TAUX_T3+(E10/D10-IR_PLAFOND_T3)*IR_TAUX_T4,(IR_PLAFOND_T2-IR_PLAFOND_T1)*IR_TAUX_T2+(IR_PLAFOND_T3-IR_PLAFOND_T2)*IR_TAUX_T3+(IR_PLAFOND_T4-IR_PLAFOND_T3)*IR_TAUX_T4+(E10/D10-IR_PLAFOND_T4)*IR_TAUX_T5)))))*D10,0) | H10: =IF(ABS(F10-G10)<=5,"✓","✗")
A11: T4 | B11: Célib 1p, 100k → IR ≈ 24 800 € (TMI 41 %) | C11: Célibataire / divorcé / veuf | D11: 1 | E11: 100000 | F11: 24800 | G11: =ROUND((IF(E11/D11<=IR_PLAFOND_T1,0,IF(E11/D11<=IR_PLAFOND_T2,(E11/D11-IR_PLAFOND_T1)*IR_TAUX_T2,IF(E11/D11<=IR_PLAFOND_T3,(IR_PLAFOND_T2-IR_PLAFOND_T1)*IR_TAUX_T2+(E11/D11-IR_PLAFOND_T2)*IR_TAUX_T3,IF(E11/D11<=IR_PLAFOND_T4,(IR_PLAFOND_T2-IR_PLAFOND_T1)*IR_TAUX_T2+(IR_PLAFOND_T3-IR_PLAFOND_T2)*IR_TAUX_T3+(E11/D11-IR_PLAFOND_T3)*IR_TAUX_T4,(IR_PLAFOND_T2-IR_PLAFOND_T1)*IR_TAUX_T2+(IR_PLAFOND_T3-IR_PLAFOND_T2)*IR_TAUX_T3+(IR_PLAFOND_T4-IR_PLAFOND_T3)*IR_TAUX_T4+(E11/D11-IR_PLAFOND_T4)*IR_TAUX_T5)))))*D11,0) | H11: =IF(ABS(F11-G11)<=5,"✓","✗")
A12: T5 | B12: Marié 2p, 200k → IR ≈ 49 600 € (TMI 41 %) | C12: Marié / pacsé | D12: 2 | E12: 200000 | F12: 49600 | G12: =ROUND((IF(E12/D12<=IR_PLAFOND_T1,0,IF(E12/D12<=IR_PLAFOND_T2,(E12/D12-IR_PLAFOND_T1)*IR_TAUX_T2,IF(E12/D12<=IR_PLAFOND_T3,(IR_PLAFOND_T2-IR_PLAFOND_T1)*IR_TAUX_T2+(E12/D12-IR_PLAFOND_T2)*IR_TAUX_T3,IF(E12/D12<=IR_PLAFOND_T4,(IR_PLAFOND_T2-IR_PLAFOND_T1)*IR_TAUX_T2+(IR_PLAFOND_T3-IR_PLAFOND_T2)*IR_TAUX_T3+(E12/D12-IR_PLAFOND_T3)*IR_TAUX_T4,(IR_PLAFOND_T2-IR_PLAFOND_T1)*IR_TAUX_T2+(IR_PLAFOND_T3-IR_PLAFOND_T2)*IR_TAUX_T3+(IR_PLAFOND_T4-IR_PLAFOND_T3)*IR_TAUX_T4+(E12/D12-IR_PLAFOND_T4)*IR_TAUX_T5)))))*D12,0) | H12: =IF(ABS(F12-G12)<=5,"✓","✗")
A13: T11 | B13: Célib 1p, 11 600 € (limite T1/T2) → IR = 0 | C13: Célibataire / divorcé / veuf | D13: 1 | E13: 11600 | F13: 0 | G13: =ROUND((IF(E13/D13<=IR_PLAFOND_T1,0,IF(E13/D13<=IR_PLAFOND_T2,(E13/D13-IR_PLAFOND_T1)*IR_TAUX_T2,IF(E13/D13<=IR_PLAFOND_T3,(IR_PLAFOND_T2-IR_PLAFOND_T1)*IR_TAUX_T2+(E13/D13-IR_PLAFOND_T2)*IR_TAUX_T3,IF(E13/D13<=IR_PLAFOND_T4,(IR_PLAFOND_T2-IR_PLAFOND_T1)*IR_TAUX_T2+(IR_PLAFOND_T3-IR_PLAFOND_T2)*IR_TAUX_T3+(E13/D13-IR_PLAFOND_T3)*IR_TAUX_T4,(IR_PLAFOND_T2-IR_PLAFOND_T1)*IR_TAUX_T2+(IR_PLAFOND_T3-IR_PLAFOND_T2)*IR_TAUX_T3+(IR_PLAFOND_T4-IR_PLAFOND_T3)*IR_TAUX_T4+(E13/D13-IR_PLAFOND_T4)*IR_TAUX_T5)))))*D13,0) | H13: =IF(ABS(F13-G13)<=5,"✓","✗")
A14: T12 | B14: Célib 1p, 29 579 € (limite T2/T3) → IR ≈ 1 978 € | C14: Célibataire / divorcé / veuf | D14: 1 | E14: 29579 | F14: 1978 | G14: =ROUND((IF(E14/D14<=IR_PLAFOND_T1,0,IF(E14/D14<=IR_PLAFOND_T2,(E14/D14-IR_PLAFOND_T1)*IR_TAUX_T2,IF(E14/D14<=IR_PLAFOND_T3,(IR_PLAFOND_T2-IR_PLAFOND_T1)*IR_TAUX_T2+(E14/D14-IR_PLAFOND_T2)*IR_TAUX_T3,IF(E14/D14<=IR_PLAFOND_T4,(IR_PLAFOND_T2-IR_PLAFOND_T1)*IR_TAUX_T2+(IR_PLAFOND_T3-IR_PLAFOND_T2)*IR_TAUX_T3+(E14/D14-IR_PLAFOND_T3)*IR_TAUX_T4,(IR_PLAFOND_T2-IR_PLAFOND_T1)*IR_TAUX_T2+(IR_PLAFOND_T3-IR_PLAFOND_T2)*IR_TAUX_T3+(IR_PLAFOND_T4-IR_PLAFOND_T3)*IR_TAUX_T4+(E14/D14-IR_PLAFOND_T4)*IR_TAUX_T5)))))*D14,0) | H14: =IF(ABS(F14-G14)<=5,"✓","✗")
A15: T13 | B15: Célib 1p, 250k → IR ≈ 89 024 € (T5 active, calcul direct) | C15: Célibataire / divorcé / veuf | D15: 1 | E15: 250000 | F15: 89024 | G15: =ROUND((IF(E15/D15<=IR_PLAFOND_T1,0,IF(E15/D15<=IR_PLAFOND_T2,(E15/D15-IR_PLAFOND_T1)*IR_TAUX_T2,IF(E15/D15<=IR_PLAFOND_T3,(IR_PLAFOND_T2-IR_PLAFOND_T1)*IR_TAUX_T2+(E15/D15-IR_PLAFOND_T2)*IR_TAUX_T3,IF(E15/D15<=IR_PLAFOND_T4,(IR_PLAFOND_T2-IR_PLAFOND_T1)*IR_TAUX_T2+(IR_PLAFOND_T3-IR_PLAFOND_T2)*IR_TAUX_T3+(E15/D15-IR_PLAFOND_T3)*IR_TAUX_T4,(IR_PLAFOND_T2-IR_PLAFOND_T1)*IR_TAUX_T2+(IR_PLAFOND_T3-IR_PLAFOND_T2)*IR_TAUX_T3+(IR_PLAFOND_T4-IR_PLAFOND_T3)*IR_TAUX_T4+(E15/D15-IR_PLAFOND_T4)*IR_TAUX_T5)))))*D15,0) | H15: =IF(ABS(F15-G15)<=5,"✓","✗")
A16: T14 | B16: Marié 3p, 100k → IR brut ≈ 9 312 € (sans plafonnement QF) | C16: Marié / pacsé | D16: 3 | E16: 100000 | F16: 9312 | G16: =ROUND((IF(E16/D16<=IR_PLAFOND_T1,0,IF(E16/D16<=IR_PLAFOND_T2,(E16/D16-IR_PLAFOND_T1)*IR_TAUX_T2,IF(E16/D16<=IR_PLAFOND_T3,(IR_PLAFOND_T2-IR_PLAFOND_T1)*IR_TAUX_T2+(E16/D16-IR_PLAFOND_T2)*IR_TAUX_T3,IF(E16/D16<=IR_PLAFOND_T4,(IR_PLAFOND_T2-IR_PLAFOND_T1)*IR_TAUX_T2+(IR_PLAFOND_T3-IR_PLAFOND_T2)*IR_TAUX_T3+(E16/D16-IR_PLAFOND_T3)*IR_TAUX_T4,(IR_PLAFOND_T2-IR_PLAFOND_T1)*IR_TAUX_T2+(IR_PLAFOND_T3-IR_PLAFOND_T2)*IR_TAUX_T3+(IR_PLAFOND_T4-IR_PLAFOND_T3)*IR_TAUX_T4+(E16/D16-IR_PLAFOND_T4)*IR_TAUX_T5)))))*D16,0) | H16: =IF(ABS(F16-G16)<=5,"✓","✗")
A17: T15 | B17: Marié 2,5p, 100k → IR brut ≈ 12 760 € (sans plafonnement QF) | C17: Marié / pacsé | D17: 2.5 | E17: 100000 | F17: 12760 | G17: =ROUND((IF(E17/D17<=IR_PLAFOND_T1,0,IF(E17/D17<=IR_PLAFOND_T2,(E17/D17-IR_PLAFOND_T1)*IR_TAUX_T2,IF(E17/D17<=IR_PLAFOND_T3,(IR_PLAFOND_T2-IR_PLAFOND_T1)*IR_TAUX_T2+(E17/D17-IR_PLAFOND_T2)*IR_TAUX_T3,IF(E17/D17<=IR_PLAFOND_T4,(IR_PLAFOND_T2-IR_PLAFOND_T1)*IR_TAUX_T2+(IR_PLAFOND_T3-IR_PLAFOND_T2)*IR_TAUX_T3+(E17/D17-IR_PLAFOND_T3)*IR_TAUX_T4,(IR_PLAFOND_T2-IR_PLAFOND_T1)*IR_TAUX_T2+(IR_PLAFOND_T3-IR_PLAFOND_T2)*IR_TAUX_T3+(IR_PLAFOND_T4-IR_PLAFOND_T3)*IR_TAUX_T4+(E17/D17-IR_PLAFOND_T4)*IR_TAUX_T5)))))*D17,0) | H17: =IF(ABS(F17-G17)<=5,"✓","✗")
A18: T6 | B18: Célib 1p, RFR 400k → CEHR = 4 500 € (3 %) | C18: Célibataire / divorcé / veuf | D18: 1 | E18: 400000 | F18: 4500 | G18: =ROUND(IF(C18="Marié / pacsé",IF(E18<=CEHR_SEUIL_M1,0,IF(E18<=CEHR_SEUIL_M2,(E18-CEHR_SEUIL_M1)*CEHR_TX_1,(CEHR_SEUIL_M2-CEHR_SEUIL_M1)*CEHR_TX_1+(E18-CEHR_SEUIL_M2)*CEHR_TX_2)),IF(E18<=CEHR_SEUIL_C1,0,IF(E18<=CEHR_SEUIL_C2,(E18-CEHR_SEUIL_C1)*CEHR_TX_1,(CEHR_SEUIL_C2-CEHR_SEUIL_C1)*CEHR_TX_1+(E18-CEHR_SEUIL_C2)*CEHR_TX_2))),0) | H18: =IF(ABS(F18-G18)<=5,"✓","✗")
A19: T7 | B19: Marié 2p, RFR 700k → CEHR = 6 000 € (3 % sur tranche 500-700k) | C19: Marié / pacsé | D19: 2 | E19: 700000 | F19: 6000 | G19: =ROUND(IF(C19="Marié / pacsé",IF(E19<=CEHR_SEUIL_M1,0,IF(E19<=CEHR_SEUIL_M2,(E19-CEHR_SEUIL_M1)*CEHR_TX_1,(CEHR_SEUIL_M2-CEHR_SEUIL_M1)*CEHR_TX_1+(E19-CEHR_SEUIL_M2)*CEHR_TX_2)),IF(E19<=CEHR_SEUIL_C1,0,IF(E19<=CEHR_SEUIL_C2,(E19-CEHR_SEUIL_C1)*CEHR_TX_1,(CEHR_SEUIL_C2-CEHR_SEUIL_C1)*CEHR_TX_1+(E19-CEHR_SEUIL_C2)*CEHR_TX_2))),0) | H19: =IF(ABS(F19-G19)<=5,"✓","✗")
A20: T8 | B20: Célib 1p, RFR 600k → CEHR = 11 500 € (3 % puis 4 %) | C20: Célibataire / divorcé / veuf | D20: 1 | E20: 600000 | F20: 11500 | G20: =ROUND(IF(C20="Marié / pacsé",IF(E20<=CEHR_SEUIL_M1,0,IF(E20<=CEHR_SEUIL_M2,(E20-CEHR_SEUIL_M1)*CEHR_TX_1,(CEHR_SEUIL_M2-CEHR_SEUIL_M1)*CEHR_TX_1+(E20-CEHR_SEUIL_M2)*CEHR_TX_2)),IF(E20<=CEHR_SEUIL_C1,0,IF(E20<=CEHR_SEUIL_C2,(E20-CEHR_SEUIL_C1)*CEHR_TX_1,(CEHR_SEUIL_C2-CEHR_SEUIL_C1)*CEHR_TX_1+(E20-CEHR_SEUIL_C2)*CEHR_TX_2))),0) | H20: =IF(ABS(F20-G20)<=5,"✓","✗")
A21: T16 | B21: Célib 1p, RFR 250k (limite seuil C1) → CEHR = 0 | C21: Célibataire / divorcé / veuf | D21: 1 | E21: 250000 | F21: 0 | G21: =ROUND(IF(C21="Marié / pacsé",IF(E21<=CEHR_SEUIL_M1,0,IF(E21<=CEHR_SEUIL_M2,(E21-CEHR_SEUIL_M1)*CEHR_TX_1,(CEHR_SEUIL_M2-CEHR_SEUIL_M1)*CEHR_TX_1+(E21-CEHR_SEUIL_M2)*CEHR_TX_2)),IF(E21<=CEHR_SEUIL_C1,0,IF(E21<=CEHR_SEUIL_C2,(E21-CEHR_SEUIL_C1)*CEHR_TX_1,(CEHR_SEUIL_C2-CEHR_SEUIL_C1)*CEHR_TX_1+(E21-CEHR_SEUIL_C2)*CEHR_TX_2))),0) | H21: =IF(ABS(F21-G21)<=5,"✓","✗")
A22: T17 | B22: Marié 2p, RFR 500k (limite seuil M1) → CEHR = 0 | C22: Marié / pacsé | D22: 2 | E22: 500000 | F22: 0 | G22: =ROUND(IF(C22="Marié / pacsé",IF(E22<=CEHR_SEUIL_M1,0,IF(E22<=CEHR_SEUIL_M2,(E22-CEHR_SEUIL_M1)*CEHR_TX_1,(CEHR_SEUIL_M2-CEHR_SEUIL_M1)*CEHR_TX_1+(E22-CEHR_SEUIL_M2)*CEHR_TX_2)),IF(E22<=CEHR_SEUIL_C1,0,IF(E22<=CEHR_SEUIL_C2,(E22-CEHR_SEUIL_C1)*CEHR_TX_1,(CEHR_SEUIL_C2-CEHR_SEUIL_C1)*CEHR_TX_1+(E22-CEHR_SEUIL_C2)*CEHR_TX_2))),0) | H22: =IF(ABS(F22-G22)<=5,"✓","✗")
A23: T18 | B23: Marié 2p, RFR 1 200k → CEHR = 23 000 € (3 % puis 4 %) | C23: Marié / pacsé | D23: 2 | E23: 1200000 | F23: 23000 | G23: =ROUND(IF(C23="Marié / pacsé",IF(E23<=CEHR_SEUIL_M1,0,IF(E23<=CEHR_SEUIL_M2,(E23-CEHR_SEUIL_M1)*CEHR_TX_1,(CEHR_SEUIL_M2-CEHR_SEUIL_M1)*CEHR_TX_1+(E23-CEHR_SEUIL_M2)*CEHR_TX_2)),IF(E23<=CEHR_SEUIL_C1,0,IF(E23<=CEHR_SEUIL_C2,(E23-CEHR_SEUIL_C1)*CEHR_TX_1,(CEHR_SEUIL_C2-CEHR_SEUIL_C1)*CEHR_TX_1+(E23-CEHR_SEUIL_C2)*CEHR_TX_2))),0) | H23: =IF(ABS(F23-G23)<=5,"✓","✗")
A24: T9 | B24: Célib 1p, RFR 300k pur salaire → CDHR = 0 (IR > 20 % RFR) | C24: Célibataire / divorcé / veuf | D24: 1 | E24: 300000 | F24: 0 | G24: =ROUND(IF(E24<=IF(C24="Marié / pacsé",CDHR_SEUIL_M,CDHR_SEUIL_C),0,MAX(0,CDHR_TAUX_PLANCHER*E24-((IF(E24/D24<=IR_PLAFOND_T1,0,IF(E24/D24<=IR_PLAFOND_T2,(E24/D24-IR_PLAFOND_T1)*IR_TAUX_T2,IF(E24/D24<=IR_PLAFOND_T3,(IR_PLAFOND_T2-IR_PLAFOND_T1)*IR_TAUX_T2+(E24/D24-IR_PLAFOND_T2)*IR_TAUX_T3,IF(E24/D24<=IR_PLAFOND_T4,(IR_PLAFOND_T2-IR_PLAFOND_T1)*IR_TAUX_T2+(IR_PLAFOND_T3-IR_PLAFOND_T2)*IR_TAUX_T3+(E24/D24-IR_PLAFOND_T3)*IR_TAUX_T4,(IR_PLAFOND_T2-IR_PLAFOND_T1)*IR_TAUX_T2+(IR_PLAFOND_T3-IR_PLAFOND_T2)*IR_TAUX_T3+(IR_PLAFOND_T4-IR_PLAFOND_T3)*IR_TAUX_T4+(E24/D24-IR_PLAFOND_T4)*IR_TAUX_T5)))))*D24+IF(C24="Marié / pacsé",IF(E24<=CEHR_SEUIL_M1,0,IF(E24<=CEHR_SEUIL_M2,(E24-CEHR_SEUIL_M1)*CEHR_TX_1,(CEHR_SEUIL_M2-CEHR_SEUIL_M1)*CEHR_TX_1+(E24-CEHR_SEUIL_M2)*CEHR_TX_2)),IF(E24<=CEHR_SEUIL_C1,0,IF(E24<=CEHR_SEUIL_C2,(E24-CEHR_SEUIL_C1)*CEHR_TX_1,(CEHR_SEUIL_C2-CEHR_SEUIL_C1)*CEHR_TX_1+(E24-CEHR_SEUIL_C2)*CEHR_TX_2)))))),0) | H24: =IF(ABS(F24-G24)<=5,"✓","✗")
A25: T10 | B25: Marié 2p, RFR 400k pur salaire → sous seuil 500k → CDHR = 0 | C25: Marié / pacsé | D25: 2 | E25: 400000 | F25: 0 | G25: =ROUND(IF(E25<=IF(C25="Marié / pacsé",CDHR_SEUIL_M,CDHR_SEUIL_C),0,MAX(0,CDHR_TAUX_PLANCHER*E25-((IF(E25/D25<=IR_PLAFOND_T1,0,IF(E25/D25<=IR_PLAFOND_T2,(E25/D25-IR_PLAFOND_T1)*IR_TAUX_T2,IF(E25/D25<=IR_PLAFOND_T3,(IR_PLAFOND_T2-IR_PLAFOND_T1)*IR_TAUX_T2+(E25/D25-IR_PLAFOND_T2)*IR_TAUX_T3,IF(E25/D25<=IR_PLAFOND_T4,(IR_PLAFOND_T2-IR_PLAFOND_T1)*IR_TAUX_T2+(IR_PLAFOND_T3-IR_PLAFOND_T2)*IR_TAUX_T3+(E25/D25-IR_PLAFOND_T3)*IR_TAUX_T4,(IR_PLAFOND_T2-IR_PLAFOND_T1)*IR_TAUX_T2+(IR_PLAFOND_T3-IR_PLAFOND_T2)*IR_TAUX_T3+(IR_PLAFOND_T4-IR_PLAFOND_T3)*IR_TAUX_T4+(E25/D25-IR_PLAFOND_T4)*IR_TAUX_T5)))))*D25+IF(C25="Marié / pacsé",IF(E25<=CEHR_SEUIL_M1,0,IF(E25<=CEHR_SEUIL_M2,(E25-CEHR_SEUIL_M1)*CEHR_TX_1,(CEHR_SEUIL_M2-CEHR_SEUIL_M1)*CEHR_TX_1+(E25-CEHR_SEUIL_M2)*CEHR_TX_2)),IF(E25<=CEHR_SEUIL_C1,0,IF(E25<=CEHR_SEUIL_C2,(E25-CEHR_SEUIL_C1)*CEHR_TX_1,(CEHR_SEUIL_C2-CEHR_SEUIL_C1)*CEHR_TX_1+(E25-CEHR_SEUIL_C2)*CEHR_TX_2)))))),0) | H25: =IF(ABS(F25-G25)<=5,"✓","✗")
A26: T19 | B26: Célib 1p, RFR 250k (limite basse) → CDHR = 0 | C26: Célibataire / divorcé / veuf | D26: 1 | E26: 250000 | F26: 0 | G26: =ROUND(IF(E26<=IF(C26="Marié / pacsé",CDHR_SEUIL_M,CDHR_SEUIL_C),0,MAX(0,CDHR_TAUX_PLANCHER*E26-((IF(E26/D26<=IR_PLAFOND_T1,0,IF(E26/D26<=IR_PLAFOND_T2,(E26/D26-IR_PLAFOND_T1)*IR_TAUX_T2,IF(E26/D26<=IR_PLAFOND_T3,(IR_PLAFOND_T2-IR_PLAFOND_T1)*IR_TAUX_T2+(E26/D26-IR_PLAFOND_T2)*IR_TAUX_T3,IF(E26/D26<=IR_PLAFOND_T4,(IR_PLAFOND_T2-IR_PLAFOND_T1)*IR_TAUX_T2+(IR_PLAFOND_T3-IR_PLAFOND_T2)*IR_TAUX_T3+(E26/D26-IR_PLAFOND_T3)*IR_TAUX_T4,(IR_PLAFOND_T2-IR_PLAFOND_T1)*IR_TAUX_T2+(IR_PLAFOND_T3-IR_PLAFOND_T2)*IR_TAUX_T3+(IR_PLAFOND_T4-IR_PLAFOND_T3)*IR_TAUX_T4+(E26/D26-IR_PLAFOND_T4)*IR_TAUX_T5)))))*D26+IF(C26="Marié / pacsé",IF(E26<=CEHR_SEUIL_M1,0,IF(E26<=CEHR_SEUIL_M2,(E26-CEHR_SEUIL_M1)*CEHR_TX_1,(CEHR_SEUIL_M2-CEHR_SEUIL_M1)*CEHR_TX_1+(E26-CEHR_SEUIL_M2)*CEHR_TX_2)),IF(E26<=CEHR_SEUIL_C1,0,IF(E26<=CEHR_SEUIL_C2,(E26-CEHR_SEUIL_C1)*CEHR_TX_1,(CEHR_SEUIL_C2-CEHR_SEUIL_C1)*CEHR_TX_1+(E26-CEHR_SEUIL_C2)*CEHR_TX_2)))))),0) | H26: =IF(ABS(F26-G26)<=5,"✓","✗")
A27: T20 | B27: Marié 2p, RFR 500k (limite basse) → CDHR = 0 | C27: Marié / pacsé | D27: 2 | E27: 500000 | F27: 0 | G27: =ROUND(IF(E27<=IF(C27="Marié / pacsé",CDHR_SEUIL_M,CDHR_SEUIL_C),0,MAX(0,CDHR_TAUX_PLANCHER*E27-((IF(E27/D27<=IR_PLAFOND_T1,0,IF(E27/D27<=IR_PLAFOND_T2,(E27/D27-IR_PLAFOND_T1)*IR_TAUX_T2,IF(E27/D27<=IR_PLAFOND_T3,(IR_PLAFOND_T2-IR_PLAFOND_T1)*IR_TAUX_T2+(E27/D27-IR_PLAFOND_T2)*IR_TAUX_T3,IF(E27/D27<=IR_PLAFOND_T4,(IR_PLAFOND_T2-IR_PLAFOND_T1)*IR_TAUX_T2+(IR_PLAFOND_T3-IR_PLAFOND_T2)*IR_TAUX_T3+(E27/D27-IR_PLAFOND_T3)*IR_TAUX_T4,(IR_PLAFOND_T2-IR_PLAFOND_T1)*IR_TAUX_T2+(IR_PLAFOND_T3-IR_PLAFOND_T2)*IR_TAUX_T3+(IR_PLAFOND_T4-IR_PLAFOND_T3)*IR_TAUX_T4+(E27/D27-IR_PLAFOND_T4)*IR_TAUX_T5)))))*D27+IF(C27="Marié / pacsé",IF(E27<=CEHR_SEUIL_M1,0,IF(E27<=CEHR_SEUIL_M2,(E27-CEHR_SEUIL_M1)*CEHR_TX_1,(CEHR_SEUIL_M2-CEHR_SEUIL_M1)*CEHR_TX_1+(E27-CEHR_SEUIL_M2)*CEHR_TX_2)),IF(E27<=CEHR_SEUIL_C1,0,IF(E27<=CEHR_SEUIL_C2,(E27-CEHR_SEUIL_C1)*CEHR_TX_1,(CEHR_SEUIL_C2-CEHR_SEUIL_C1)*CEHR_TX_1+(E27-CEHR_SEUIL_C2)*CEHR_TX_2)))))),0) | H27: =IF(ABS(F27-G27)<=5,"✓","✗")
A30: ℹ Les cas-tests utilisent une approximation simplifiée du calcul IR (sans plafonnement QF qui ne mord pas sur la plupart des revenus testés) et une CDHR sans lissage. Les valeurs attendues sont calibrées à partir du simulateur officiel impots.gouv.fr (barème 2026). Une tolérance de ±5 € est appliquée pour absorber les arrondis. En cas d'échec, vérifier les paramètres §1-2 (PASS, barème IR) et §9-10 (QF, CEHR) en Paramètres.
A32: 2. COHÉRENCE INTER-FEUILLES
A33: Vérifie en live que les mêmes calculs donnent les mêmes résultats dans toutes les feuilles où ils apparaissent. Un écart > 5 € révèle un bug de cohérence. Ces contrôles tournent automatiquement sur les inputs courants du Profil.
A35: ID | B35: Vérification | C35: Source 1 | D35: Valeur 1 (€) | E35: Source 2 | F35: Valeur 2 (€) | G35: Écart (€) | H35: Statut
A36: C1 | B36: Revenu salarial imposable | C36: Module Assimilé salarié | D36: =IFERROR(INDEX('7. Assimilé salarié'!C:C,MATCH("Revenu salarial imposable*",'7. Assimilé salarié'!B:B,0)),"#N/A") | E36: Détail calcul fiscal | F36: =IFERROR(INDEX('Détail calcul fiscal'!C:C,MATCH("→ Revenu salarial imposable",'Détail calcul fiscal'!B:B,0)),"#N/A") | G36: =IFERROR(ABS(D36-F36),"err") | H36: =IFERROR(IF(G36<=5,"✓","✗"),"?")
A37: C2 | B37: Revenu imposable global du foyer | C37: Module Assimilé salarié | D37: =IFERROR(INDEX('7. Assimilé salarié'!C:C,MATCH("Revenu imposable foyer*",'7. Assimilé salarié'!B:B,0)),"#N/A") | E37: Détail calcul fiscal | F37: =IFERROR(INDEX('Détail calcul fiscal'!C:C,MATCH("→ Revenu net imposable global du foyer",'Détail calcul fiscal'!B:B,0)),"#N/A") | G37: =IFERROR(ABS(D37-F37),"err") | H37: =IFERROR(IF(G37<=5,"✓","✗"),"?")
A38: C3 | B38: IR foyer après plafonnement QF | C38: Module Assimilé salarié | D38: =IFERROR(INDEX('7. Assimilé salarié'!C:C,MATCH("IR du foyer après plafonnement QF",'7. Assimilé salarié'!B:B,0)),"#N/A") | E38: Détail calcul fiscal | F38: =IFERROR(INDEX('Détail calcul fiscal'!C:C,MATCH("→ IR foyer après plafonnement QF",'Détail calcul fiscal'!B:B,0)),"#N/A") | G38: =IFERROR(ABS(D38-F38),"err") | H38: =IFERROR(IF(G38<=5,"✓","✗"),"?")
A39: C4 | B39: CEHR (contribution exceptionnelle) | C39: Module Assimilé salarié | D39: =IFERROR(INDEX('7. Assimilé salarié'!C:C,MATCH("CEHR (contribution exceptionnelle hauts revenus)",'7. Assimilé salarié'!B:B,0)),"#N/A") | E39: Détail calcul fiscal (col F) | F39: =IFERROR(INDEX('Détail calcul fiscal'!F:F,MATCH("CEHR totale",'Détail calcul fiscal'!B:B,0)),"#N/A") | G39: =IFERROR(ABS(D39-F39),"err") | H39: =IFERROR(IF(G39<=5,"✓","✗"),"?")
A40: C5 | B40: CDHR (contribution différentielle) | C40: Module Assimilé salarié | D40: =IFERROR(INDEX('7. Assimilé salarié'!C:C,MATCH("CDHR (contribution différentielle hauts revenus)",'7. Assimilé salarié'!B:B,0)),"#N/A") | E40: Détail calcul fiscal | F40: =IFERROR(INDEX('Détail calcul fiscal'!C:C,MATCH("CDHR finale*",'Détail calcul fiscal'!B:B,0)),"#N/A") | G40: =IFERROR(ABS(D40-F40),"err") | H40: =IFERROR(IF(G40<=5,"✓","✗"),"?")
A41: C6 | B41: Total impôts foyer (incl. IR PFU) | C41: Module : Total + IR PFU sur divs | D41: =IFERROR(INDEX('7. Assimilé salarié'!C:C,MATCH("Total impôts foyer*",'7. Assimilé salarié'!B:B,0))+DIVIDENDES_FOYER*0.128,"#N/A") | E41: Détail calcul fiscal | F41: =IFERROR(INDEX('Détail calcul fiscal'!C:C,MATCH("→ IMPOSITION TOTALE FOYER",'Détail calcul fiscal'!B:B,0)),"#N/A") | G41: =IFERROR(ABS(D41-F41),"err") | H41: =IFERROR(IF(G41<=5,"✓","✗"),"?")
A42: C7 | B42: Total impôts = IR + CEHR + CDHR (module Assimilé) | C42: Module : Total impôts foyer | D42: =IFERROR(INDEX('7. Assimilé salarié'!C:C,MATCH("Total impôts foyer*",'7. Assimilé salarié'!B:B,0)),"#N/A") | E42: Module : IR + CEHR + CDHR (somme) | F42: =IFERROR(INDEX('7. Assimilé salarié'!C:C,MATCH("IR du foyer après plafonnement QF",'7. Assimilé salarié'!B:B,0))+INDEX('7. Assimilé salarié'!C:C,MATCH("CEHR (contribution exceptionnelle hauts revenus)",'7. Assimilé salarié'!B:B,0))+INDEX('7. Assimilé salarié'!C:C,MATCH("CDHR (contribution différentielle hauts revenus)",'7. Assimilé salarié'!B:B,0)),"#N/A") | G42: =IFERROR(ABS(D42-F42),"err") | H42: =IFERROR(IF(G42<=5,"✓","✗"),"?")
A43: C8 | B43: RFR élargi = Revenu imp. foyer + DIVIDENDES_FOYER | C43: Module : RFR élargi | D43: =IFERROR(INDEX('7. Assimilé salarié'!C:C,MATCH("RFR élargi*",'7. Assimilé salarié'!B:B,0)),"#N/A") | E43: Calcul théorique | F43: =IFERROR(INDEX('7. Assimilé salarié'!C:C,MATCH("Revenu imposable foyer*",'7. Assimilé salarié'!B:B,0))+DIVIDENDES_FOYER,"#N/A") | G43: =IFERROR(ABS(D43-F43),"err") | H43: =IFERROR(IF(G43<=5,"✓","✗"),"?")
A44: C9 | B44: Net salaire après IR : Synthèse ↔ Arbitrage | C44: Synthèse (livrable) | D44: =IFERROR(INDEX('12. Synthèse'!C:C,MATCH("Net salaire après IR",'12. Synthèse'!B:B,0)),"#N/A") | E44: Arbitrage | F44: =IFERROR(INDEX('11. Arbitrage'!C:C,MATCH("Net salaire après IR (€)",'11. Arbitrage'!B:B,0)),"#N/A") | G44: =IFERROR(ABS(D44-F44),"err") | H44: =IFERROR(IF(G44<=5,"✓","✗"),"?")
A45: C10 | B45: TOTAL Strat A : Arbitrage ↔ Synthèse (composition) | C45: Arbitrage Stratégie A (col C) | D45: =IFERROR(INDEX('11. Arbitrage'!C:C,MATCH("TOTAL NET DIRIGEANT APRÈS FISCALITÉ (€)",'11. Arbitrage'!B:B,0)),"#N/A") | E45: Synthèse - tableau composition TOTAL (col C) | F45: =IFERROR(INDEX('12. Synthèse'!C:C,MATCH("TOTAL",'12. Synthèse'!B:B,0)),"#N/A") | G45: =IFERROR(ABS(D45-F45),"err") | H45: =IFERROR(IF(G45<=5,"✓","✗"),"?")
A48: ℹ Les vérifications C1-C6 comparent les valeurs entre le Module Assimilé salarié et la feuille Détail calcul fiscal. Elles ne sont pertinentes que si REGIME_SOCIAL = « Assimilé salarié » (sinon les chiffres divergent normalement car les régimes calculent différemment). Pour les autres régimes, comparer manuellement avec le module concerné. Les C7-C10 sont des cohérences structurelles toujours valides.
